Workbook

Sheet Hoja14
M2: AFP ahorro Obligatorio (APO) | P2: Capital | AA2: =+Y17-AB17-AC17-AD17-AE17 -> 3190663.5 | AD2: =+AD3-AD17 -> -57149.47
M3: Tipo de afiliado | P3: Pensionado no cotizante | AA3: =+AA2*Z17-AA17 -> -27076.229 | AD3: 183008
M4: Retiro APV B (2025) | P4: 10000000 | R4: Impuesto Único | T4: =Hoja9!I21 -> 0.34936739 | W4: YN | Y4: =IF(P3=Z34,1,0) -> 0 | AC4: =VLOOKUP(P2,$CF$14:$CG$19,2) -> 0.0144
F5: AFP cotiza ahorro APO | M5: Intereses crédito hipotecario (2025) | P5: 0 | R5: =Hoja9!Q15 -> 0 | T5: =Hoja9!R14 -> 0.50234715 | W5: =IF(R5=6164736,"(Tope UTA 8)"," ") | AF5: Si | AG5: No | AH5: =IF(Q270="Si",1,0) -> 1 | AX5: =IF(P3="No pensionado",0,IF(P3="Pensionado cotizante",3,2)) -> 2 | HM5: =MIN(P5,Hoja15!J19) -> 0
M6: Inversión 57 bis | N6: Saldo Ahorro Neto | R6: 0 | X6: , | AC6: 1510523 | AD6: =AC6/67.4 -> 22411.32 | HP6: Seguro cesantía | HS6: Si
N7: Años SAN positivo | P7: 0 | Q7: =IF(R6=0," ",IF(T45=1,"Credito","Débito")) | R7: =IF(R6=" "," ",IF(R6=0,0,IF(Q7="Débito",Q48,Q48*-1))) -> 0 | AA7: =IF(P3="No pensionado",0,1) -> 1 | BF7: =IF(P3="Pensionado no cotizante",0,1) -> 0
K11: APV opción A | AE11: APV B | AG11: APV A
E12: Mes | F12: UF | G12: Total renta afecta ($) | H12: Pensión Bruta ($) | I12: APV máximo vía empleador ($) | J12: Vía Empleador | K12: Directo | L12: Vía Empleador | M12: Directo | N12: Renta Tributable ($) | P12: Impuesto mensual ($) | R12: Pensión Tributable ($) | T12: Impuesto Pensión ($) | V12: Honorarios ($) | X12: Retención 14,5% ($) | Z12: Tramo impuesto | AA12: Rebaja | AB12: Obligatorio | AC12: Comisión AFP | AD12: Salud | AE12: Seguro Cesantía | AF12: Vía Empleador | AG12: Directo | AH12: Vía Empleador | AI12: Directo | AX12: Tramo impuesto | AY12: Rebaja | AZ12: Obligatorio | BA12: Comisión Pensión | BB12: Salud pensión | BC12: Seguro Cesantía | BD12: Comisión AFP | BJ12: Tramo impuesto | BK12: Rebaja
AJ13: =SUM(AJ14:AJ25) -> 0 | CK13: Factor actualización | CM13: Renta tributable | CN13: Pensión Tributable | CO13: Impuetso sueldo | CP13: Impuesto Pensión | CQ13: Honorarios | CR13: Retenciones | CS13: APV empleador | CT13: APV directo
A14: =P14/Hoja15!C6 -> 8.0044058 | B14: =J14/F14 -> 0.00078156731 | E14: Enero | F14: =H229 -> 38384.41 | G14: 7000000 | I14: =IF($Y$4=1,Y14*0.1,IF(G14-AB14-AC14-AD14-AE14<(50*F14),G14-AB14-AC14-AD14-AE14,50*F14)) -> 1919220.5 | J14: 30 | K14: 0 | L14: 0 | N14: =G14-AB14-AC14-AD14-AE14-AF14 -> 5612557.1 | P14: =N14*Z14-AA14 -> 539729.08 | R14: =AW14 -> 0 | T14: =AW14*AX14-AY14 -> 0 | X14: =+V14*0.145 -> 0 | Y14: =IF(G14>87.8*F14,87.8*F14,G14) -> 3370151.2 | Z14: =VLOOKUP(N14,Hoja15!$E$6:$H$13,3) -> 0.23 | AA14: =VLOOKUP(N14,Hoja15!$E$6:$H$14,4) -> 751159.06 | AB14: =IF($AX$5=2,0,Y14*0.1) -> 0 | AC14: =IF($BF$7=0,0,(IF(G14>87.8*F14,87.8*F14*$AC$4,$AC$4*G14))) -> 0 | AD14: =IF(G14>87.8*F14,87.8*7%*F14,7%*G14) -> 235910.58 | AE14: =(IF($BF$7=0,0,IF($HS$6="No",0,IF(G14>131.8*F14,0.6%*131.8*F14,0.6%*G14))))*AH5 -> 0 | AF14: =IF($AJ$42=2,J14*F14,J14) -> 1151532.3 | AG14: =IF($AK$42=2,M14*F14,M14) -> 0 | AH14: =IF($AL$42=2,L14*F14,L14) -> 0 | AI14: =IF($AM$42=2,M14*F14,M14) -> 0 | AJ14: =IF(AF14>I14,1,0) -> 0 | AK14: =I14/F14 -> 50 | AL14: =AF14/F14 -> 30 | AM14: =AG14/F14 -> 0 | AN14: =AH14/F14 -> 0 | AO14: =AI14/F14 -> 0 | AR14: =P14/F14 -> 14.061153 | AW14: =BF14-BB14-AZ14 -> 0 | AX14: =VLOOKUP(AW14,Hoja15!$E$6:$H$13,3) -> 0 | AY14: =VLOOKUP(AW14,Hoja15!$E$6:$H$13,4) -> 0 | AZ14: 0 | BA14: =1.25%*BF14 -> 0 | BB14: =IF(BF14>60*F14,60*7%*F14,7%*BF14) -> 0 | BC14: 0 | BD14: 0 | BF14: =IF($P$3="No pensionado",0,H14) -> 0 | BI14: =N14+R14 -> 5612557.1 | BJ14: =VLOOKUP(BI14,Hoja15!$E$6:$H$13,3) -> 0.23 | BK14: =VLOOKUP(BI14,Hoja15!$E$6:$H$13,4) -> 751159.06 | BL14: =BI14*BJ14-BK14 -> 539729.08 | BM14: =BL14/Hoja15!C6 -> 8.0044058 | BP14: =P14/Hoja15!C6 -> 8.0044058 | BQ14: =T14/Hoja15!C6 -> 0 | BT14: =I14/F14 -> 50 | BU14: =M14 -> 0 | BX14: =IF($AJ$42=1,M14/F14,J14) -> 30 | BY14: =IF($AJ$42=1,J14/F14,J14) -> 30 | BZ14: =I14/F14 -> 50 | CF14: Capital | CG14: 0.0144 | CJ14: enero | CK14: =J229 -> 0 | CM14: =N14*(1+CK14) -> 5612557.1 | CN14: =R14*(1+CK14) -> 0 | CO14: =P14*(1+CK14) -> 539729.08 | CP14: =T14*(1+CK14) -> 0 | CQ14: =V14*(1+CK14) -> 0 | CR14: =X14*(1+CK14) -> 0 | CS14: =IF($AJ$42=2,J14*H229,J14)*(1+CK14) -> 1151532.3 | CT14: =IF($AK$42=2,M14*H229,M14)*(1+CK14) -> 0 | DO14: =H14-10*H229 -> -383844.1
A15: =P15/Hoja15!C7 -> 8.010255 | B15: =J15/F15 -> 0.00077623801 | E15: Febrero | F15: =H230 -> 38647.94 | G15: 7000000 | I15: =IF($Y$4=1,Y15*0.1,IF(G15-AB15-AC15-AD15-AE15<(50*F15),G15-AB15-AC15-AD15-AE15,50*F15)) -> 1932397 | J15: 30 | K15: 0 | L15: 0 | N15: =G15-AB15-AC15-AD15-AE15-AF15 -> 5603031.6 | P15: =N15*Z15-AA15 -> 539042.1 | R15: =AW15 -> 0 | T15: =AW15*AX15-AY15 -> 0 | X15: =+V15*0.145 -> 0 | Y15: =IF(G15>87.8*F15,87.8*F15,G15) -> 3393289.1 | Z15: =VLOOKUP(N15,Hoja15!$E$15:$H$22,3) -> 0.23 | AA15: =VLOOKUP(N15,Hoja15!$E$15:$H$22,4) -> 749655.16 | AB15: =IF($AX$5=2,0,Y15*0.1) -> 0 | AC15: =IF($BF$7=0,0,(IF(G15>87.8*F15,87.8*F15*$AC$4,$AC$4*G15))) -> 0 | AD15: =IF(G15>87.8*F15,87.8*7%*F15,7%*G15) -> 237530.24 | AE15: =(IF($BF$7=0,0,IF($HS$6="No",0,IF(G15>131.8*F15,0.6%*131.8*F15,0.6%*G15))))*$AH$5 -> 0 | AF15: =IF($AJ$42=2,J15*F15,J15) -> 1159438.2 | AG15: =IF($AK$42=2,M15*F15,M15) -> 0 | AH15: =IF($AL$42=2,L15*F15,L15) -> 0 | AI15: =IF($AM$42=2,M15*F15,M15) -> 0 | AJ15: =IF(AF15>I15,1,0) -> 0 | AK15: =I15/F15 -> 50 | AL15: =AF15/F15 -> 30 | AM15: =AG15/F15 -> 0 | AN15: =AH15/F15 -> 0 | AO15: =AI15/F15 -> 0 | AR15: =P15/F15 -> 13.947499 | AW15: =BF15-BB15-AZ15 -> 0 | AX15: =VLOOKUP(AW15,Hoja15!$E$15:$H$22,3) -> 0 | AY15: =VLOOKUP(AW15,Hoja15!$E$15:$H$22,4) -> 0 | AZ15: 0 | BA15: =1.25%*BF15 -> 0 | BB15: =IF(BF15>60*F15,60*7%*F15,7%*BF15) -> 0 | BC15: 0 | BD15: 0 | BF15: =IF($P$3="No pensionado",0,H15) -> 0 | BI15: =N15+R15 -> 5603031.6 | BJ15: =VLOOKUP(BI15,Hoja15!$E$15:$H$22,3) -> 0.23 | BK15: =VLOOKUP(BI15,Hoja15!$E$15:$H$22,4) -> 749655.16 | BL15: =BI15*BJ15-BK15 -> 539042.1 | BM15: =BL15/Hoja15!C7 -> 8.010255 | BP15: =P15/Hoja15!C7 -> 8.010255 | BQ15: =T15/Hoja15!C7 -> 0 | BT15: =I15/F15 -> 50 | BX15: =IF($AJ$42=1,M15/F15,J15) -> 30 | BY15: =IF($AJ$42=1,J15/F15,J15) -> 30 | BZ15: =I15/F15 -> 50 | CF15: Cuprum | CG15: 0.0144 | CJ15: febrero | CK15: =J230 -> 0 | CM15: =N15*(1+CK15) -> 5603031.6 | CN15: =R15*(1+CK15) -> 0 | CO15: =P15*(1+CK15) -> 539042.1 | CP15: =T15*(1+CK15) -> 0 | CQ15: =V15*(1+CK15) -> 0 | CR15: =X15*(1+CK15) -> 0 | CS15: =IF($AJ$42=2,J15*H230,J15)*(1+CK15) -> 1159438.2 | CT15: =IF($AK$42=2,M15*H230,M15)*(1+CK15) -> 0 | DO15: =H15-10*H230 -> -386479.4
A16: =P16/Hoja15!C8 -> 117.5379 | B16: =J16/F16 -> 0.00077132502 | E16: Marzo | F16: =H231 -> 38894.11 | G16: 28000000 | I16: =IF($Y$4=1,Y16*0.1,IF(G16-AB16-AC16-AD16-AE16<(50*F16),G16-AB16-AC16-AD16-AE16,50*F16)) -> 1944705.5 | J16: 30 | K16: 0 | L16: 0 | N16: =G16-AB16-AC16-AD16-AE16-AF16 -> 26594133 | P16: =N16*Z16-AA16 -> 7996573.5 | R16: =AW16 -> 0 | T16: =AW16*AX16-AY16 -> 0 | X16: =+V16*0.145 -> 0 | Y16: =IF(G16>87.8*F16,87.8*F16,G16) -> 3414902.9 | Z16: =VLOOKUP(N16,Hoja15!$E$24:$H$31,3) -> 0.4 | AA16: =VLOOKUP(N16,Hoja15!$E$24:$H$31,4) -> 2641079.9 | AB16: =IF($AX$5=2,0,Y16*0.1) -> 0 | AC16: =IF($BF$7=0,0,(IF(G16>87.8*F16,87.8*F16*$AC$4,$AC$4*G16))) -> 0 | AD16: =IF(G16>87.8*F16,87.8*7%*F16,7%*G16) -> 239043.2 | AE16: =(IF($BF$7=0,0,IF($HS$6="No",0,IF(G16>131.8*F16,0.6%*131.8*F16,0.6%*G16))))*$AH$5 -> 0 | AF16: =IF($AJ$42=2,J16*F16,J16) -> 1166823.3 | AG16: =IF($AK$42=2,M16*F16,M16) -> 0 | AH16: =IF($AL$42=2,L16*F16,L16) -> 0 | AI16: =IF($AM$42=2,M16*F16,M16) -> 0 | AJ16: =IF(AF16>I16,1,0) -> 0 | AK16: =I16/F16 -> 50 | AL16: =AF16/F16 -> 30 | AM16: =AG16/F16 -> 0 | AN16: =AH16/F16 -> 0 | AO16: =AI16/F16 -> 0 | AR16: =P16/F16 -> 205.59857 | AW16: =BF16-BB16-AZ16 -> 0 | AX16: =VLOOKUP(AW16,Hoja15!$E$24:$H$31,3) -> 0 | AY16: =VLOOKUP(AW16,Hoja15!$E$24:$H$31,4) -> 0 | AZ16: 0 | BA16: =1.25%*BF16 -> 0 | BB16: =IF(BF16>60*F16,60*7%*F16,7%*BF16) -> 0 | BC16: 0 | BD16: 0 | BF16: =IF($P$3="No pensionado",0,H16) -> 0 | BI16: =N16+R16 -> 26594133 | BJ16: =VLOOKUP(BI16,Hoja15!$E$24:$H$31,3) -> 0.4 | BK16: =VLOOKUP(BI16,Hoja15!$E$24:$H$31,4) -> 2641079.9 | BL16: =BI16*BJ16-BK16 -> 7996573.5 | BM16: =BL16/Hoja15!C8 -> 117.5379 | BP16: =P16/Hoja15!C8 -> 117.5379 | BQ16: =T16/Hoja15!C8 -> 0 | BT16: =I16/F16 -> 50 | BX16: =IF($AJ$42=1,M16/F16,J16) -> 30 | BY16: =IF($AJ$42=1,J16/F16,J16) -> 30 | BZ16: =I16/F16 -> 50 | CF16: Habitat | CG16: 0.0127 | CJ16: marzo | CK16: =J231 -> 0 | CM16: =N16*(1+CK16) -> 26594133 | CN16: =R16*(1+CK16) -> 0 | CO16: =P16*(1+CK16) -> 7996573.5 | CP16: =T16*(1+CK16) -> 0 | CQ16: =V16*(1+CK16) -> 0 | CR16: =X16*(1+CK16) -> 0 | CS16: =IF($AJ$42=2,J16*H231,J16)*(1+CK16) -> 1166823.3 | CT16: =IF($AK$42=2,M16*H231,M16)*(1+CK16) -> 0 | DK16: APV independiente | DO16: =H16-10*H231 -> -388941.1 | EM16: =IF(AVERAGE(G14:G25)=G26/12,1,0) -> 1
A17: =P17/Hoja15!C9 -> 7.6745032 | B17: =J17/F17 -> 0.00076774626 | E17: Abril | F17: =H232 -> 39075.41 | G17: 7000000 | I17: =IF($Y$4=1,Y17*0.1,IF(G17-AB17-AC17-AD17-AE17<(50*F17),G17-AB17-AC17-AD17-AE17,50*F17)) -> 1953770.5 | J17: 30 | K17: 0 | L17: 0 | N17: =G17-AB17-AC17-AD17-AE17-AF17 -> 5587580.2 | P17: =N17*Z17-AA17 -> 524214.61 | R17: =AW17 -> 0 | T17: =AW17*AX17-AY17 -> 0 | X17: =+V17*0.145 -> 0 | Y17: =IF(G17>87.8*F17,87.8*F17,G17) -> 3430821 | Z17: =VLOOKUP(N17,Hoja15!$E$33:$H$40,3) -> 0.23 | AA17: =VLOOKUP(N17,Hoja15!$E$33:$H$40,4) -> 760928.84 | AB17: =IF($AX$5=2,0,Y17*0.1) -> 0 | AC17: =IF($BF$7=0,0,(IF(G17>87.8*F17,87.8*F17*$AC$4,$AC$4*G17))) -> 0 | AD17: =IF(G17>87.8*F17,87.8*7%*F17,7%*G17) -> 240157.47 | AE17: =(IF($BF$7=0,0,IF($HS$6="No",0,IF(G17>131.8*F17,0.6%*131.8*F17,0.6%*G17))))*$AH$5 -> 0 | AF17: =IF($AJ$42=2,J17*F17,J17) -> 1172262.3 | AG17: =IF($AK$42=2,M17*F17,M17) -> 0 | AH17: =IF($AL$42=2,L17*F17,L17) -> 0 | AI17: =IF($AM$42=2,M17*F17,M17) -> 0 | AJ17: =IF(AF17>I17,1,0) -> 0 | AK17: =I17/F17 -> 50 | AL17: =AF17/F17 -> 30 | AM17: =AG17/F17 -> 0 | AN17: =AH17/F17 -> 0 | AO17: =AI17/F17 -> 0 | AR17: =P17/F17 -> 13.41546 | AW17: =BF17-BB17-AZ17 -> 0 | AX17: =VLOOKUP(AW17,Hoja15!$E$33:$H$40,3) -> 0 | AY17: =VLOOKUP(AW17,Hoja15!$E$33:$H$40,4) -> 0 | AZ17: 0 | BA17: =1.25%*BF17 -> 0 | BB17: =IF(BF17>60*F17,60*7%*F17,7%*BF17) -> 0 | BC17: 0 | BD17: 0 | BF17: =IF($P$3="No pensionado",0,H17) -> 0 | BI17: =N17+R17 -> 5587580.2 | BJ17: =VLOOKUP(BI17,Hoja15!$E$33:$H$40,3) -> 0.23 | BK17: =VLOOKUP(BI17,Hoja15!$E$33:$H$40,4) -> 760928.84 | BL17: =BI17*BJ17-BK17 -> 524214.61 | BM17: =BL17/Hoja15!C9 -> 7.6745032 | BP17: =P17/Hoja15!C9 -> 7.6745032 | BQ17: =T17/Hoja15!C9 -> 0 | BT17: =I17/F17 -> 50 | BX17: =IF($AJ$42=1,M17/F17,J17) -> 30 | BY17: =IF($AJ$42=1,J17/F17,J17) -> 30 | BZ17: =I17/F17 -> 50 | CF17: Modelo | CG17: 0.0058 | CJ17: abril | CK17: =J232 -> 0 | CM17: =N17*(1+CK17) -> 5587580.2 | CN17: =R17*(1+CK17) -> 0 | CO17: =P17*(1+CK17) -> 524214.61 | CP17: =T17*(1+CK17) -> 0 | CQ17: =V17*(1+CK17) -> 0 | CR17: =X17*(1+CK17) -> 0 | CS17: =IF($AJ$42=2,J17*H232,J17)*(1+CK17) -> 1172262.3 | CT17: =IF($AK$42=2,M17*H232,M17)*(1+CK17) -> 0 | DK17: =15*I240*12 -> 12517560 | DO17: =H17-10*H232 -> -390754.1 | EM17: =IF(H26+J26+M26+V26+P4+P5+R6+J34=0,1,0) -> 0
A18: =P18/Hoja15!C10 -> 7.5669597 | B18: =J18/F18 -> 0.00076551215 | E18: Mayo | F18: =H233 -> 39189.45 | G18: 7000000 | I18: =IF($Y$4=1,Y18*0.1,IF(G18-AB18-AC18-AD18-AE18<(50*F18),G18-AB18-AC18-AD18-AE18,50*F18)) -> 1959472.5 | J18: 30 | K18: 0 | L18: 0 | N18: =G18-AB18-AC18-AD18-AE18-AF18 -> 5583458.1 | P18: =N18*Z18-AA18 -> 519456.65 | R18: =AW18 -> 0 | T18: =AW18*AX18-AY18 -> 0 | X18: =+V18*0.145 -> 0 | Y18: =IF(G18>87.8*F18,87.8*F18,G18) -> 3440833.7 | Z18: =VLOOKUP(N18,Hoja15!$E$42:$H$49,3) -> 0.23 | AA18: =VLOOKUP(N18,Hoja15!$E$42:$H$49,4) -> 764738.72 | AB18: =IF($AX$5=2,0,Y18*0.1) -> 0 | AC18: =IF($BF$7=0,0,(IF(G18>87.8*F18,87.8*F18*$AC$4,$AC$4*G18))) -> 0 | AD18: =IF(G18>87.8*F18,87.8*7%*F18,7%*G18) -> 240858.36 | AE18: =(IF($BF$7=0,0,IF($HS$6="No",0,IF(G18>131.8*F18,0.6%*131.8*F18,0.6%*G18))))*$AH$5 -> 0 | AF18: =IF($AJ$42=2,J18*F18,J18) -> 1175683.5 | AG18: =IF($AK$42=2,M18*F18,M18) -> 0 | AH18: =IF($AL$42=2,L18*F18,L18) -> 0 | AI18: =IF($AM$42=2,M18*F18,M18) -> 0 | AJ18: =IF(AF18>I18,1,0) -> 0 | AK18: =I18/F18 -> 50 | AL18: =AF18/F18 -> 30 | AM18: =AG18/F18 -> 0 | AN18: =AH18/F18 -> 0 | AO18: =AI18/F18 -> 0 | AR18: =P18/F18 -> 13.255013 | AW18: =BF18-BB18-AZ18 -> 0 | AX18: =VLOOKUP(AW18,Hoja15!$E$42:$H$49,3) -> 0 | AY18: =VLOOKUP(AW18,Hoja15!$E$42:$H$49,4) -> 0 | AZ18: 0 | BA18: =1.25%*BF18 -> 0 | BB18: =IF(BF18>60*F18,60*7%*F18,7%*BF18) -> 0 | BC18: 0 | BD18: 0 | BF18: =IF($P$3="No pensionado",0,H18) -> 0 | BI18: =N18+R18 -> 5583458.1 | BJ18: =VLOOKUP(BI18,Hoja15!$E$42:$H$49,3) -> 0.23 | BK18: =VLOOKUP(BI18,Hoja15!$E$42:$H$49,4) -> 764738.72 | BL18: =BI18*BJ18-BK18 -> 519456.65 | BM18: =BL18/Hoja15!C10 -> 7.5669597 | BP18: =P18/Hoja15!C10 -> 7.5669597 | BQ18: =T18/Hoja15!C10 -> 0 | BT18: =I18/F18 -> 50 | BX18: =IF($AJ$42=1,M18/F18,J18) -> 30 | BY18: =IF($AJ$42=1,J18/F18,J18) -> 30 | BZ18: =I18/F18 -> 50 | CF18: Planvital | CG18: 0.0116 | CJ18: mayo | CK18: =J233 -> 0 | CM18: =N18*(1+CK18) -> 5583458.1 | CN18: =R18*(1+CK18) -> 0 | CO18: =P18*(1+CK18) -> 519456.65 | CP18: =T18*(1+CK18) -> 0 | CQ18: =V18*(1+CK18) -> 0 | CR18: =X18*(1+CK18) -> 0 | CS18: =IF($AJ$42=2,J18*H233,J18)*(1+CK18) -> 1175683.5 | CT18: =IF($AK$42=2,M18*H233,M18)*(1+CK18) -> 0 | DK18: =V26-(MIN(30%*V26,DK17)) -> 0 | DO18: =H18-10*H233 -> -391894.5 | EM18: =EM16+EM17 -> 1
A19: =P19/Hoja15!C11 -> 7.5203194 | B19: =J19/F19 -> 0.00076399894 | E19: Junio | F19: =H234 -> 39267.07 | G19: 7000000 | I19: =IF($Y$4=1,Y19*0.1,IF(G19-AB19-AC19-AD19-AE19<(50*F19),G19-AB19-AC19-AD19-AE19,50*F19)) -> 1963353.5 | J19: 30 | K19: 0 | L19: 0 | N19: =G19-AB19-AC19-AD19-AE19-AF19 -> 5580652.5 | P19: =N19*Z19-AA19 -> 517285.17 | R19: =AW19 -> 0 | T19: =AW19*AX19-AY19 -> 0 | X19: =+V19*0.145 -> 0 | Y19: =IF(G19>87.8*F19,87.8*F19,G19) -> 3447648.7 | Z19: =VLOOKUP(N19,Hoja15!$E$51:$H$58,3) -> 0.23 | AA19: =VLOOKUP(N19,Hoja15!$E$51:$H$58,4) -> 766264.9 | AB19: =IF($AX$5=2,0,Y19*0.1) -> 0 | AC19: =IF($BF$7=0,0,(IF(G19>87.8*F19,87.8*F19*$AC$4,$AC$4*G19))) -> 0 | AD19: =IF(G19>87.8*F19,87.8*7%*F19,7%*G19) -> 241335.41 | AE19: =(IF($BF$7=0,0,IF($HS$6="No",0,IF(G19>131.8*F19,0.6%*131.8*F19,0.6%*G19))))*$AH$5 -> 0 | AF19: =IF($AJ$42=2,J19*F19,J19) -> 1178012.1 | AG19: =IF($AK$42=2,M19*F19,M19) -> 0 | AH19: =IF($AL$42=2,L19*F19,L19) -> 0 | AI19: =IF($AM$42=2,M19*F19,M19) -> 0 | AJ19: =IF(AF19>I19,1,0) -> 0 | AK19: =I19/F19 -> 50 | AL19: =AF19/F19 -> 30 | AM19: =AG19/F19 -> 0 | AN19: =AH19/F19 -> 0 | AO19: =AI19/F19 -> 0 | AR19: =P19/F19 -> 13.173511 | AW19: =BF19-BB19-AZ19 -> 0 | AX19: =VLOOKUP(AW19,Hoja15!$E$51:$H$58,3) -> 0 | AY19: =VLOOKUP(AW19,Hoja15!$E$51:$H$58,4) -> 0 | AZ19: 0 | BA19: =1.25%*BF19 -> 0 | BB19: =IF(BF19>60*F19,60*7%*F19,7%*BF19) -> 0 | BC19: 0 | BD19: 0 | BF19: =IF($P$3="No pensionado",0,H19) -> 0 | BI19: =N19+R19 -> 5580652.5 | BJ19: =VLOOKUP(BI19,Hoja15!$E$51:$H$58,3) -> 0.23 | BK19: =VLOOKUP(BI19,Hoja15!$E$51:$H$58,4) -> 766264.9 | BL19: =BI19*BJ19-BK19 -> 517285.17 | BM19: =BL19/Hoja15!C11 -> 7.5203194 | BP19: =P19/Hoja15!C11 -> 7.5203194 | BQ19: =T19/Hoja15!C11 -> 0 | BT19: =I19/F19 -> 50 | BX19: =IF($AJ$42=1,M19/F19,J19) -> 30 | BY19: =IF($AJ$42=1,J19/F19,J19) -> 30 | BZ19: =I19/F19 -> 50 | CF19: Provida | CG19: 0.0145 | CJ19: junio | CK19: =J234 -> 0 | CM19: =N19*(1+CK19) -> 5580652.5 | CN19: =R19*(1+CK19) -> 0 | CO19: =P19*(1+CK19) -> 517285.17 | CP19: =T19*(1+CK19) -> 0 | CQ19: =V19*(1+CK19) -> 0 | CR19: =X19*(1+CK19) -> 0 | CS19: =IF($AJ$42=2,J19*H234,J19)*(1+CK19) -> 1178012.1 | CT19: =IF($AK$42=2,M19*H234,M19)*(1+CK19) -> 0 | DK19: =MIN(600*H240,DK18) -> 0 | DO19: =H19-10*H234 -> -392670.7
A20: =P20/Hoja15!C12 -> 7.493579 | B20: =J20/F20 -> 0.00076571613 | E20: Julio | F20: =H235 -> 39179.01 | G20: 7000000 | I20: =IF($Y$4=1,Y20*0.1,IF(G20-AB20-AC20-AD20-AE20<(50*F20),G20-AB20-AC20-AD20-AE20,50*F20)) -> 1958950.5 | J20: 30 | K20: 0 | L20: 0 | N20: =G20-AB20-AC20-AD20-AE20-AF20 -> 5583835.5 | P20: =N20*Z20-AA20 -> 516479.95 | R20: =AW20 -> 0 | T20: =AW20*AX20-AY20 -> 0 | X20: =+V20*0.145 -> 0 | Y20: =IF(G20>87.8*F20,87.8*F20,G20) -> 3439917.1 | Z20: =VLOOKUP(N20,Hoja15!$E$60:$H$67,3) -> 0.23 | AA20: =VLOOKUP(N20,Hoja15!$E$60:$H$67,4) -> 767802.22 | AB20: =IF($AX$5=2,0,Y20*0.1) -> 0 | AC20: =IF($BF$7=0,0,(IF(G20>87.8*F20,87.8*F20*$AC$4,$AC$4*G20))) -> 0 | AD20: =IF(G20>87.8*F20,87.8*7%*F20,7%*G20) -> 240794.2 | AE20: =(IF($BF$7=0,0,IF($HS$6="No",0,IF(G20>131.8*F20,0.6%*131.8*F20,0.6%*G20))))*$AH$5 -> 0 | AF20: =IF($AJ$42=2,J20*F20,J20) -> 1175370.3 | AG20: =IF($AK$42=2,M20*F20,M20) -> 0 | AH20: =IF($AL$42=2,L20*F20,L20) -> 0 | AI20: =IF($AM$42=2,M20*F20,M20) -> 0 | AJ20: =IF(AF20>I20,1,0) -> 0 | AK20: =I20/F20 -> 50 | AL20: =AF20/F20 -> 30 | AM20: =AG20/F20 -> 0 | AN20: =AH20/F20 -> 0 | AO20: =AI20/F20 -> 0 | AR20: =P20/F20 -> 13.182568 | AW20: =BF20-BB20-AZ20 -> 0 | AX20: =VLOOKUP(AW20,Hoja15!$E$60:$H$67,3) -> 0 | AY20: =VLOOKUP(AW20,Hoja15!$E$60:$H$67,4) -> 0 | AZ20: 0 | BA20: =1.25%*BF20 -> 0 | BB20: =IF(BF20>60*F20,60*7%*F20,7%*BF20) -> 0 | BC20: 0 | BD20: 0 | BF20: =IF($P$3="No pensionado",0,H20) -> 0 | BI20: =N20+R20 -> 5583835.5 | BJ20: =VLOOKUP(BI20,Hoja15!$E$60:$H$67,3) -> 0.23 | BK20: =VLOOKUP(BI20,Hoja15!$E$60:$H$67,4) -> 767802.22 | BL20: =BI20*BJ20-BK20 -> 516479.95 | BM20: =BL20/Hoja15!C12 -> 7.493579 | BP20: =P20/Hoja15!C12 -> 7.493579 | BQ20: =T20/Hoja15!C12 -> 0 | BT20: =I20/F20 -> 50 | BX20: =IF($AJ$42=1,M20/F20,J20) -> 30 | BY20: =IF($AJ$42=1,J20/F20,J20) -> 30 | BZ20: =I20/F20 -> 50 | CJ20: julio | CK20: =J235 -> 0 | CM20: =N20*(1+CK20) -> 5583835.5 | CN20: =R20*(1+CK20) -> 0 | CO20: =P20*(1+CK20) -> 516479.95 | CP20: =T20*(1+CK20) -> 0 | CQ20: =V20*(1+CK20) -> 0 | CR20: =X20*(1+CK20) -> 0 | CS20: =IF($AJ$42=2,J20*H235,J20)*(1+CK20) -> 1175370.3 | CT20: =IF($AK$42=2,M20*H235,M20)*(1+CK20) -> 0 | DK20: =IF(((AK26-(AL26+AM26))*F25)<0,0,(AK26-(AL26+AM26))*F25) -> 9514461.6 | DO20: =H20-10*H235 -> -391790.1
A21: =P21/Hoja15!C13 -> 7.5437837 | B21: =J21/F21 -> 0.00076174864 | E21: Agosto | F21: =H236 -> 39383.07 | G21: 7000000 | I21: =IF($Y$4=1,Y21*0.1,IF(G21-AB21-AC21-AD21-AE21<(50*F21),G21-AB21-AC21-AD21-AE21,50*F21)) -> 1969153.5 | J21: 30 | K21: 0 | L21: 0 | N21: =G21-AB21-AC21-AD21-AE21-AF21 -> 5576459.6 | P21: =N21*Z21-AA21 -> 517858.12 | R21: =AW21 -> 0 | T21: =AW21*AX21-AY21 -> 0 | X21: =+V21*0.145 -> 0 | Y21: =IF(G21>87.8*F21,87.8*F21,G21) -> 3457833.5 | Z21: =VLOOKUP(N21,Hoja15!$E$69:$H$76,3) -> 0.23 | AA21: =VLOOKUP(N21,Hoja15!$E$69:$H$76,4) -> 764727.58 | AB21: =IF($AX$5=2,0,Y21*0.1) -> 0 | AC21: =IF($BF$7=0,0,(IF(G21>87.8*F21,87.8*F21*$AC$4,$AC$4*G21))) -> 0 | AD21: =IF(G21>87.8*F21,87.8*7%*F21,7%*G21) -> 242048.35 | AE21: =(IF($BF$7=0,0,IF($HS$6="No",0,IF(G21>131.8*F21,0.6%*131.8*F21,0.6%*G21))))*$AH$5 -> 0 | AF21: =IF($AJ$42=2,J21*F21,J21) -> 1181492.1 | AG21: =IF($AK$42=2,M21*F21,M21) -> 0 | AH21: =IF($AL$42=2,L21*F21,L21) -> 0 | AI21: =IF($AM$42=2,M21*F21,M21) -> 0 | AJ21: =IF(AF21>I21,1,0) -> 0 | AK21: =I21/F21 -> 50 | AL21: =AF21/F21 -> 30 | AM21: =AG21/F21 -> 0 | AN21: =AH21/F21 -> 0 | AO21: =AI21/F21 -> 0 | AR21: =P21/F21 -> 13.149257 | AW21: =BF21-BB21-AZ21 -> 0 | AX21: =VLOOKUP(AW21,Hoja15!$E$69:$H$76,3) -> 0 | AY21: =VLOOKUP(AW21,Hoja15!$E$69:$H$76,4) -> 0 | AZ21: 0 | BA21: =1.25%*BF21 -> 0 | BB21: =IF(BF21>60*F21,60*7%*F21,7%*BF21) -> 0 | BC21: 0 | BD21: 0 | BF21: =IF($P$3="No pensionado",0,H21) -> 0 | BI21: =N21+R21 -> 5576459.6 | BJ21: =VLOOKUP(BI21,Hoja15!$E$69:$H$76,3) -> 0.23 | BK21: =VLOOKUP(BI21,Hoja15!$E$69:$H$76,4) -> 764727.58 | BL21: =BI21*BJ21-BK21 -> 517858.12 | BM21: =BL21/Hoja15!C13 -> 7.5437837 | BP21: =P21/Hoja15!C13 -> 7.5437837 | BQ21: =T21/Hoja15!C13 -> 0 | BT21: =I21/F21 -> 50 | BX21: =IF($AJ$42=1,M21/F21,J21) -> 30 | BY21: =IF($AJ$42=1,J21/F21,J21) -> 30 | BZ21: =I21/F21 -> 50 | CJ21: agosto | CK21: =J236 -> 0 | CM21: =N21*(1+CK21) -> 5576459.6 | CN21: =R21*(1+CK21) -> 0 | CO21: =P21*(1+CK21) -> 517858.12 | CP21: =T21*(1+CK21) -> 0 | CQ21: =V21*(1+CK21) -> 0 | CR21: =X21*(1+CK21) -> 0 | CS21: =IF($AJ$42=2,J21*H236,J21)*(1+CK21) -> 1181492.1 | CT21: =IF($AK$42=2,M21*H236,M21)*(1+CK21) -> 0 | DO21: =H21-10*H236 -> -393830.7
A22: =P22/Hoja15!C14 -> 7.3647699 | B22: =J22/F22 -> 0.00075976969 | E22: Septiembre | F22: =H237 -> 39485.65 | G22: 7000000 | I22: =IF($Y$4=1,Y22*0.1,IF(G22-AB22-AC22-AD22-AE22<(50*F22),G22-AB22-AC22-AD22-AE22,50*F22)) -> 1974282.5 | J22: 30 | K22: 0 | L22: 0 | N22: =G22-AB22-AC22-AD22-AE22-AF22 -> 5572751.7 | P22: =N22*Z22-AA22 -> 510120.79 | R22: =AW22 -> 0 | T22: =AW22*AX22-AY22 -> 0 | X22: =+V22*0.145 -> 0 | Y22: =IF(G22>87.8*F22,87.8*F22,G22) -> 3466840.1 | Z22: =VLOOKUP(N22,Hoja15!$E$78:$H$85,3) -> 0.23 | AA22: =VLOOKUP(N22,Hoja15!$E$78:$H$85,4) -> 771612.1 | AB22: =IF($AX$5=2,0,Y22*0.1) -> 0 | AC22: =IF($BF$7=0,0,(IF(G22>87.8*F22,87.8*F22*$AC$4,$AC$4*G22))) -> 0 | AD22: =IF(G22>87.8*F22,87.8*7%*F22,7%*G22) -> 242678.8 | AE22: =(IF($BF$7=0,0,IF($HS$6="No",0,IF(G22>131.8*F22,0.6%*131.8*F22,0.6%*G22))))*$AH$5 -> 0 | AF22: =IF($AJ$42=2,J22*F22,J22) -> 1184569.5 | AG22: =IF($AK$42=2,M22*F22,M22) -> 0 | AH22: =IF($AL$42=2,L22*F22,L22) -> 0 | AI22: =IF($AM$42=2,M22*F22,M22) -> 0 | AJ22: =IF(AF22>I22,1,0) -> 0 | AK22: =I22/F22 -> 50 | AL22: =AF22/F22 -> 30 | AM22: =AG22/F22 -> 0 | AN22: =AH22/F22 -> 0 | AO22: =AI22/F22 -> 0 | AR22: =P22/F22 -> 12.919144 | AW22: =BF22-BB22-AZ22 -> 0 | AX22: =VLOOKUP(AW22,Hoja15!$E$78:$H$85,3) -> 0 | AY22: =VLOOKUP(AW22,Hoja15!$E$78:$H$85,4) -> 0 | AZ22: 0 | BA22: =1.25%*BF22 -> 0 | BB22: =IF(BF22>60*F22,60*7%*F22,7%*BF22) -> 0 | BC22: 0 | BD22: 0 | BF22: =IF($P$3="No pensionado",0,H22) -> 0 | BI22: =N22+R22 -> 5572751.7 | BJ22: =VLOOKUP(BI22,Hoja15!$E$78:$H$85,3) -> 0.23 | BK22: =VLOOKUP(BI22,Hoja15!$E$78:$H$85,4) -> 771612.1 | BL22: =BI22*BJ22-BK22 -> 510120.79 | BM22: =BL22/Hoja15!C14 -> 7.3647699 | BP22: =P22/Hoja15!C14 -> 7.3647699 | BQ22: =T22/Hoja15!C14 -> 0 | BT22: =I22/F22 -> 50 | BX22: =IF($AJ$42=1,M22/F22,J22) -> 30 | BY22: =IF($AJ$42=1,J22/F22,J22) -> 30 | BZ22: =I22/F22 -> 50 | CJ22: septiembre | CK22: =J237 -> 0 | CM22: =N22*(1+CK22) -> 5572751.7 | CN22: =R22*(1+CK22) -> 0 | CO22: =P22*(1+CK22) -> 510120.79 | CP22: =T22*(1+CK22) -> 0 | CQ22: =V22*(1+CK22) -> 0 | CR22: =X22*(1+CK22) -> 0 | CS22: =IF($AJ$42=2,J22*H237,J22)*(1+CK22) -> 1184569.5 | CT22: =IF($AK$42=2,M22*H237,M22)*(1+CK22) -> 0 | DO22: =H22-10*H237 -> -394856.5
A23: =P23/Hoja15!C15 -> 7.3647699 | B23: =J23/F23 -> 0.00075976969 | E23: Octubre | F23: =H238 -> 39485.65 | G23: 7000000 | I23: =IF($Y$4=1,Y23*0.1,IF(G23-AB23-AC23-AD23-AE23<(50*F23),G23-AB23-AC23-AD23-AE23,50*F23)) -> 1974282.5 | J23: 30 | K23: 0 | L23: 0 | N23: =G23-AB23-AC23-AD23-AE23-AF23 -> 5572751.7 | P23: =N23*Z23-AA23 -> 510120.79 | R23: =AW23 -> 0 | T23: =AW23*AX23-AY23 -> 0 | X23: =+V23*0.145 -> 0 | Y23: =IF(G23>87.8*F23,87.8*F23,G23) -> 3466840.1 | Z23: =VLOOKUP(N23,Hoja15!$E$87:$H$94,3) -> 0.23 | AA23: =VLOOKUP(N23,Hoja15!$E$87:$H$94,4) -> 771612.1 | AB23: =IF($AX$5=2,0,Y23*0.1) -> 0 | AC23: =IF($BF$7=0,0,(IF(G23>87.8*F23,87.8*F23*$AC$4,$AC$4*G23))) -> 0 | AD23: =IF(G23>87.8*F23,87.8*7%*F23,7%*G23) -> 242678.8 | AE23: =(IF($BF$7=0,0,IF($HS$6="No",0,IF(G23>131.8*F23,0.6%*131.8*F23,0.6%*G23))))*$AH$5 -> 0 | AF23: =IF($AJ$42=2,J23*F23,J23) -> 1184569.5 | AG23: =IF($AK$42=2,M23*F23,M23) -> 0 | AH23: =IF($AL$42=2,L23*F23,L23) -> 0 | AI23: =IF($AM$42=2,M23*F23,M23) -> 0 | AJ23: =IF(AF23>I23,1,0) -> 0 | AK23: =I23/F23 -> 50 | AL23: =AF23/F23 -> 30 | AM23: =AG23/F23 -> 0 | AN23: =AH23/F23 -> 0 | AO23: =AI23/F23 -> 0 | AR23: =P23/F23 -> 12.919144 | AW23: =BF23-BB23-AZ23 -> 0 | AX23: =VLOOKUP(AW23,Hoja15!$E$87:$H$94,3) -> 0 | AY23: =VLOOKUP(AW23,Hoja15!$E$87:$H$94,4) -> 0 | AZ23: 0 | BA23: =1.25%*BF23 -> 0 | BB23: =IF(BF23>60*F23,60*7%*F23,7%*BF23) -> 0 | BC23: 0 | BD23: 0 | BF23: =IF($P$3="No pensionado",0,H23) -> 0 | BI23: =N23+R23 -> 5572751.7 | BJ23: =VLOOKUP(BI23,Hoja15!$E$87:$H$94,3) -> 0.23 | BK23: =VLOOKUP(BI23,Hoja15!$E$87:$H$94,4) -> 771612.1 | BL23: =BI23*BJ23-BK23 -> 510120.79 | BM23: =BL23/Hoja15!C15 -> 7.3647699 | BP23: =P23/Hoja15!C15 -> 7.3647699 | BQ23: =T23/Hoja15!C15 -> 0 | BT23: =I23/F23 -> 50 | BX23: =IF($AJ$42=1,M23/F23,J23) -> 30 | BY23: =IF($AJ$42=1,J23/F23,J23) -> 30 | BZ23: =I23/F23 -> 50 | CJ23: octubre | CK23: =J238 -> 0 | CM23: =N23*(1+CK23) -> 5572751.7 | CN23: =R23*(1+CK23) -> 0 | CO23: =P23*(1+CK23) -> 510120.79 | CP23: =T23*(1+CK23) -> 0 | CQ23: =V23*(1+CK23) -> 0 | CR23: =X23*(1+CK23) -> 0 | CS23: =IF($AJ$42=2,J23*H238,J23)*(1+CK23) -> 1184569.5 | CT23: =IF($AK$42=2,M23*H238,M23)*(1+CK23) -> 0 | DO23: =H23-10*H238 -> -394856.5
A24: =P24/Hoja15!C16 -> 7.2776699 | B24: =J24/F24 -> 0.00075762033 | E24: Noviembre | F24: =H239 -> 39597.67 | G24: 7000000 | I24: =IF($Y$4=1,Y24*0.1,IF(G24-AB24-AC24-AD24-AE24<(50*F24),G24-AB24-AC24-AD24-AE24,50*F24)) -> 1979883.5 | J24: 30 | K24: 0 | L24: 0 | N24: =G24-AB24-AC24-AD24-AE24-AF24 -> 5568702.6 | P24: =N24*Z24-AA24 -> 506103.72 | R24: =AW24 -> 0 | T24: =AW24*AX24-AY24 -> 0 | X24: =+V24*0.145 -> 0 | Y24: =IF(G24>87.8*F24,87.8*F24,G24) -> 3476675.4 | Z24: =VLOOKUP(N24,Hoja15!$E$96:$H$103,3) -> 0.23 | AA24: =VLOOKUP(N24,Hoja15!$E$96:$H$103,4) -> 774697.88 | AB24: =IF($AX$5=2,0,Y24*0.1) -> 0 | AC24: =IF($BF$7=0,0,(IF(G24>87.8*F24,87.8*F24*$AC$4,$AC$4*G24))) -> 0 | AD24: =IF(G24>87.8*F24,87.8*7%*F24,7%*G24) -> 243367.28 | AE24: =(IF($BF$7=0,0,IF($HS$6="No",0,IF(G24>131.8*F24,0.6%*131.8*F24,0.6%*G24))))*$AH$5 -> 0 | AF24: =IF($AJ$42=2,J24*F24,J24) -> 1187930.1 | AG24: =IF($AK$42=2,M24*F24,M24) -> 0 | AH24: =IF($AL$42=2,L24*F24,L24) -> 0 | AI24: =IF($AM$42=2,M24*F24,M24) -> 0 | AJ24: =IF(AF24>I24,1,0) -> 0 | AK24: =I24/F24 -> 50 | AL24: =AF24/F24 -> 30 | AM24: =AG24/F24 -> 0 | AN24: =AH24/F24 -> 0 | AO24: =AI24/F24 -> 0 | AR24: =P24/F24 -> 12.781149 | AW24: =BF24-BB24-AZ24 -> 0 | AX24: =VLOOKUP(AW24,Hoja15!$E$96:$H$103,3) -> 0 | AY24: =VLOOKUP(AW24,Hoja15!$E$96:$H$103,4) -> 0 | AZ24: 0 | BA24: =1.25%*BF24 -> 0 | BB24: =IF(BF24>60*F24,60*7%*F24,7%*BF24) -> 0 | BC24: 0 | BD24: 0 | BF24: =IF($P$3="No pensionado",0,H24) -> 0 | BI24: =N24+R24 -> 5568702.6 | BJ24: =VLOOKUP(BI24,Hoja15!$E$96:$H$103,3) -> 0.23 | BK24: =VLOOKUP(BI24,Hoja15!$E$96:$H$103,4) -> 774697.88 | BL24: =BI24*BJ24-BK24 -> 506103.72 | BM24: =BL24/Hoja15!C16 -> 7.2776699 | BP24: =P24/Hoja15!C16 -> 7.2776699 | BQ24: =T24/Hoja15!C16 -> 0 | BT24: =I24/F24 -> 50 | BX24: =IF($AJ$42=1,M24/F24,J24) -> 30 | BY24: =IF($AJ$42=1,J24/F24,J24) -> 30 | BZ24: =I24/F24 -> 50 | CJ24: noviembre | CK24: =J239 -> 0 | CM24: =N24*(1+CK24) -> 5568702.6 | CN24: =R24*(1+CK24) -> 0 | CO24: =P24*(1+CK24) -> 506103.72 | CP24: =T24*(1+CK24) -> 0 | CQ24: =V24*(1+CK24) -> 0 | CR24: =X24*(1+CK24) -> 0 | CS24: =IF($AJ$42=2,J24*H239,J24)*(1+CK24) -> 1187930.1 | CT24: =IF($AK$42=2,M24*H239,M24)*(1+CK24) -> 0 | DK24: =G38/20000000 -> 0.19188476 | DO24: =H24-10*H239 -> -395976.7
A25: =P25/Hoja15!C17 -> 7.2721803 | B25: =J25/F25 -> 0.00075674277 | E25: Diciembre | F25: =H240 -> 39643.59 | G25: 7000000 | I25: =IF($Y$4=1,Y25*0.1,IF(G25-AB25-AC25-AD25-AE25<(50*F25),G25-AB25-AC25-AD25-AE25,50*F25)) -> 1982179.5 | J25: 30 | K25: 0 | L25: 0 | N25: =G25-AB25-AC25-AD25-AE25-AF25 -> 5567042.8 | P25: =N25*Z25-AA25 -> 505721.96 | R25: =AW25 -> 0 | T25: =AW25*AX25-AY25 -> 0 | X25: =+V25*0.145 -> 0 | Y25: =IF(G25>87.8*F25,87.8*F25,G25) -> 3480707.2 | Z25: =VLOOKUP(N25,Hoja15!$E$105:$H$112,3) -> 0.23 | AA25: =VLOOKUP(N25,Hoja15!$E$105:$H$112,4) -> 774697.88 | AB25: =IF($AX$5=2,0,Y25*0.1) -> 0 | AC25: =IF($BF$7=0,0,(IF(G25>87.8*F25,87.8*F25*$AC$4,$AC$4*G25))) -> 0 | AD25: =IF(G25>87.8*F25,87.8*7%*F25,7%*G25) -> 243649.5 | AE25: =(IF($BF$7=0,0,IF($HS$6="No",0,IF(G25>131.8*F25,0.6%*131.8*F25,0.6%*G25))))*$AH$5 -> 0 | AF25: =IF($AJ$42=2,J25*F25,J25) -> 1189307.7 | AG25: =IF($AK$42=2,M25*F25,M25) -> 0 | AH25: =IF($AL$42=2,L25*F25,L25) -> 0 | AI25: =IF($AM$42=2,M25*F25,M25) -> 0 | AJ25: =IF(AF25>I25,1,0) -> 0 | AK25: =I25/F25 -> 50 | AL25: =AF25/F25 -> 30 | AM25: =AG25/F25 -> 0 | AN25: =AH25/F25 -> 0 | AO25: =AI25/F25 -> 0 | AR25: =P25/F25 -> 12.756715 | AW25: =BF25-BB25-AZ25 -> 0 | AX25: =VLOOKUP(AW25,Hoja15!$E$105:$H$112,3) -> 0 | AY25: =VLOOKUP(AW25,Hoja15!$E$105:$H$112,4) -> 0 | AZ25: 0 | BA25: =1.25%*BF25 -> 0 | BB25: =IF(BF25>60*F25,60*7%*F25,7%*BF25) -> 0 | BC25: 0 | BD25: 0 | BF25: =IF($P$3="No pensionado",0,H25) -> 0 | BI25: =N25+R25 -> 5567042.8 | BJ25: =VLOOKUP(BI25,Hoja15!$E$105:$H$112,3) -> 0.23 | BK25: =VLOOKUP(BI25,Hoja15!$E$105:$H$112,4) -> 774697.88 | BL25: =BI25*BJ25-BK25 -> 505721.96 | BM25: =BL25/Hoja15!C17 -> 7.2721803 | BP25: =P25/Hoja15!C17 -> 7.2721803 | BQ25: =T25/Hoja15!C17 -> 0 | BT25: =I25/F25 -> 50 | BX25: =IF($AJ$42=1,M25/F25,J25) -> 30 | BY25: =IF($AJ$42=1,J25/F25,J25) -> 30 | BZ25: =I25/F25 -> 50 | CJ25: diciembre | CK25: =J240 -> 0 | CM25: =N25*(1+CK25) -> 5567042.8 | CN25: =R25*(1+CK25) -> 0 | CO25: =P25*(1+CK25) -> 505721.96 | CP25: =T25*(1+CK25) -> 0 | CQ25: =V25*(1+CK25) -> 0 | CR25: =X25*(1+CK25) -> 0 | CS25: =IF($AJ$42=2,J25*H240,J25)*(1+CK25) -> 1189307.7 | CT25: =IF($AK$42=2,M25*H240,M25)*(1+CK25) -> 0 | DO25: =H25-10*H240 -> -396435.9
E26: Total | G26: =SUM(G14:G25) -> 105000000 | H26: =SUM(H14:H25) -> 0 | I26: =SUM(I14:I25) -> 23511652 | J26: =AF26 -> 14106991 | K26: =AG26 -> 0 | L26: =AH26 -> 0 | M26: =(IF(AK42=1,SUM(M14:M25),AI26))+V62 -> 0 | N26: =SUM(N14:N25) -> 88002957 | P26: =SUM(P14:P25) -> 13702706 | R26: =SUM(R14:R25) -> 0 | T26: =SUM(T14:T25) -> 0 | V26: =SUM(V14:V25) -> 0 | X26: =SUM(X14:X25) -> 0 | AB26: =SUM(AB14:AB25) -> 0 | AC26: =SUM(AC14:AC25) -> 0 | AD26: =SUM(AD14:AD25) -> 2890052.2 | AE26: =SUM(AE14:AE25) -> 0 | AF26: =SUM(AF14:AF25) -> 14106991 | AG26: =SUM(AG14:AG25) -> 0 | AH26: =IF(AK42=2,SUMPRODUCT(F14:F25,AH14:AH25),SUM(AH14:AH25)) -> 0 | AI26: =SUMPRODUCT(AI14:AI25,F14:F25) -> 0 | AJ26: =IF(AF26>I26,1,0) -> 0 | AK26: =SUM(AK14:AK25) -> 600 | AL26: =SUM(AL14:AL25) -> 360 | AM26: =SUM(AM14:AM25) -> 0 | AN26: =SUM(AN14:AN25) -> 0 | AO26: =SUM(AO14:AO25) -> 0 | AR26: =SUM(AR14:AR25) -> 351.15919 | AS26: =AR26*Hoja14!F25 -> 13921211 | AW26: =SUM(AW14:AW25) -> 0 | AZ26: =SUM(AZ14:AZ25) -> 0 | BA26: =SUM(BA14:BA25) -> 0 | BB26: =SUM(BB14:BB25) -> 0 | BC26: =SUM(BC14:BC25) -> 0 | BD26: =SUM(BD14:BD25) -> 0 | BL26: =SUM(BL14:BL25) -> 13702706 | BM26: =SUM(BM14:BM25)*Hoja15!C17 -> 13952288 | BP26: =SUM(BP14:BP25)*Hoja15!C17 -> 13952288 | BQ26: =SUM(BQ14:BQ25)*Hoja15!C17 -> 0 | BR26: =BP26+BQ26 -> 13952288 | BX26: =SUM(BX14:BX25) -> 360 | BY26: =SUM(BY14:BY25) -> 360 | BZ26: =SUM(BZ14:BZ25) -> 600 | CA26: =BZ26-BY26-BX26 -> -120 | CB26: =CA26*F25 -> -4757230.8 | CM26: =SUM(CM14:CM25) -> 88002957 | CN26: =SUM(CN14:CN25) -> 0 | CO26: =SUM(CO14:CO25) -> 13702706 | CP26: =SUM(CP14:CP25) -> 0 | CQ26: =SUM(CQ14:CQ25) -> 0 | CR26: =SUM(CR14:CR25) -> 0 | CS26: =SUM(CS14:CS25) -> 14106991 | CT26: =SUM(CT14:CT25) -> 0 | DO26: =SUM(DO14:DO25) -> -4702330.3
CP27: =T27 -> 0 | CT27: =IF($AK$42=2,M27*H242,M27) -> 0
E30: Pagos Directos y Vía Empleador corregidos efectuados en el año | J30: =AL32+AM32 -> 14271692 | N30: Otras Rentas afectas a IGC | R30: 12000000 | DK30: APV máx. dependiente (Art. 42 N° 1) | DN30: =DK20 -> 9514461.6
E31: APV B máx. para utilizar 100% del beneficio tributario (*) | J31: =MIN(600*H240-J30,DK20+DK19) -> 9514461.6 | M31: =IF(((AK26-(AL26+AM26))*F25)<0,"Supera límite anual"," ") | Z31: 20939.49 | AA31: 20865.85 | AB31: 20924.09 | AC31: 21000.55 | AD31: 21032.2 | AE31: 21115.8 | AF31: 21204.99 | AG31: 21227.57 | AL31: =AL26+AM26 -> 360 | CM31: =CM26*Hoja15!L111-Hoja15!M111 -> 11340402 | DK31: APV max. Independiente (Art. 42 N° 2) | DN31: =DK19 -> 0
E32: =IF(Y4=1,"APV B máx. socio que se asigna Sueldo Empresarial","APV B máx. en calidad de trabajador dependiente (Art. 42 N° 1)") -> APV B máx. en calidad de trabajador dependiente (Art. 42 N° 1) | J32: =DN30 -> 9514461.6 | AL32: =AL26*H240 -> 14271692 | AM32: =AM26*H240 -> 0
E33: APV B máx. en calidad de trabajador independiente (Art. 42 N° 2) | J33: =MIN(J31,DN31) -> 0 | AL33: =AK26*H240 -> 23786154
E34: Pago Directo APV opción B final | Z34: Sueldo Empresarial | AA34: =R197+Hoja1!L17 -> -1305364.3 | AL34: =AL33-AL32 -> 9514461.6
Z35: No pensionado
G36: RESULTADO RELIQUIDACIÓN DE IMPUESTO : | Z36: Pensionado no cotizante | AB36: =IF(P5>8*Hoja15!B23,8*Hoja15!B23,Hoja14!P5) -> 0 | AZ36: =P26 -> 13702706
G37: =Z64 -> (En contra) | Z37: Pensionado cotizante | AZ37: =X26 -> 0
G38: =Hoja9!C23 -> 3837695.2 | AZ38: =N26 -> 88002957 | BA38: =AZ38+AZ39 -> 88002957
X39: =IF(G38=0,1,0) -> 0 | AB39: =Hoja15!C17*15*12 -> 12517560 | AZ39: =V26 -> 0
AB40: =IF(30%*V26>AB39,AB39,30%*V26) -> 0 | AD40: Directos anuales | AE40: =IF(M26>0,1,0) -> 0 | AJ40: pesos ($) | AK40: Si | AZ40: =IF((L110+L111)=0,0,IF(L111=0,0,M84-M94)) -> 0
Q41: =IF(P7=4,1,0) -> 0 | AB41: =V26-AB40 -> 0 | AD41: Directo final | AE41: =IF(J34>0,1,0) -> 0 | AJ41: UF | AK41: No
AD42: 55 bis | AE42: =IF(R5>0,1,0) -> 0 | AJ42: 2 | AK42: 1 | AL42: 1 | AM42: 1 | AZ42: =IF((M86+M88)>0,AZ40,IF(V26>0,Hoja15!R109,Hoja14!AZ40)) -> 0
Q43: =IF(T45=1,R6*1,R6*-1) -> 0 | T43: =IF(T45=1,1,-1) -> -1 | AA43: =N26+R26 -> 88002957 | AE43: =SUM(AE40:AE42) -> 0
E44: =SUM(B14:B25)*F25 -> 364.23559 | X44: =R197+R198-Y132-R199-#REF! -> #REF! | AA44: =Hoja14!AA43*Hoja15!L110-Hoja15!M110 -> 11898728
E45: =SUM(BT14:BT25)*F25 -> 23786154 | Q45: =15%*MIN(65*Hoja15!C17*12,30%*Hoja5!F8,Hoja14!R6) -> 0 | T45: 2
E46: =E45-E44 -> 23785790 | R46: 0 | T46: positivo
Q47: =R6*T43 -> 0 | R47: 1 | T47: negativo | X47: =IF(AE43=0,0,R197) -> 0
E48: Renta | H48: =IF(G26>0,1,0) -> 1 | L48: 0 | Q48: =IF(R6=0," ",IF(Q47>0,Q45,S53)) | R48: 2
E49: Pensión | H49: =IF(AW26>0,1,0) -> 0 | L49: =MAX(0,J31) -> 9514461.6 | R49: 3 | X49: =R197+R198+Y132-R199-#REF! -> #REF! | AA49: =IF(V26>0,1,0) -> 0
E50: Honorarios | H50: =IF(V26>0,1,0) -> 0 | R50: 4 | AA50: =IF((SUM(M14:M25)+J34+P5)=0,0,1) -> 0
E51: Pago directo parcial | H51: =IF(J272>0,1,0) -> 0
E52: Pago directo final | H52: =IF(J34>0,1,0) -> 0 | L52: =SUM(A14:A25) -> 200.6311 | Q52: min | R52: =MIN(R6,R53) -> 0 | S52: =R6-R52 -> 0 | X52: =IF(AE43>0,AA136-Z130,0) -> 0 | AA52: =IF(V26>0,IF(AA50=0,Hoja2!U33,X52),X52) -> 0
E53: 55 bis | H53: =IF(R5>0,1,0) -> 0 | Q53: CE | R53: =Q41*10*Hoja15!C17*12 -> 0 | S53: =S52*15% -> 0
E54: Retiro APV | H54: =IF(W8>0,1,0) -> 0 | AA54: Retiro APV opción B
AA55: Retiro APV opción B | AF55: =W8 -> 0
AA56: Impuesto al retiro de APV opción B (%) | AF56: =IF(AF55=0,0,AF55*AF57) -> 0
AA57: Impuesto al retiro de APV opción B ($) | AF57: =IF(AF55=0,0,IF(P3="No pensionado",Hoja15!R118,Hoja15!R117)) -> 0
AA58: Retención 15% | AF58: =IF(AF55=0,0,W8*15%) -> 0
AA59: Diferencia a reliquidar | AF59: =IF(AF55=0,0,AF58-AF56) -> 0
J60: =Hoja15!B39*Hoja15!C17 -> 13952288
V61: 0 | AA61: =P26+T26 -> 13702706
V62: =IF(V26>0,V61,0) -> 0
Z64: =IF(G38=0," ",IF(G38>0,"(En contra)","(A favor)")) -> (En contra)
Z67: 20939.49
Z68: 20865.85
Z69: 20924.09
Z70: 21000.55
Z71: 21032.2
Z72: 21115.8
Z73: 21204.99
Z74: 21227.57
E79: Nueva Base tributable anual | M79: =J138-#REF!-J272-J34 -> #REF!
E80: Impuesto Calculado sobre nueva Base | M80: =Hoja15!R78 -> 0
E81: Reliquidación Anual de Impuesto | M81: =J140-M80+W3 -> 0
E83: Base tributable anual | M83: =N26+R26+V26+Hoja14!R30 -> 1.0000296e+08
E84: Impuestos Pagados y retenciones enteradas en el año | M84: =P26+X26+T26 -> 13702706
E86: Pagos Directos efectuados en el año | M86: =AG26 -> 0
E87: APV B máximo restante para utilizar 100% del beneficio tributario | M87: =(AK26-(AL26+AM26))*F25 -> 9514461.6
E88: Pago Directo APV opción B final | M88: 0
E89: Intereses Crédito Hipotecario (Art. 55 bis)
E93: Nueva Base tributable anual | M93: =M83-R5-M86-M88 -> 1.0000296e+08
E94: Impuesto Calculado sobre nueva Base | M94: =Hoja15!R113 -> 15546728
E95: Reliquidación Anual de Impuesto | M95: =M84-M94+AF59 -> -1844021.2
F103: (*) Total Haberes afectos: Renta bruta menos asignación de colación y movilización.
F104: (**) APV opción B máximo con Beneficio Tributario = sumatoria cotizaciones obligatorias enteradas durante el año * 8.33, con tope UF 600.
F108: =STDEV(G14:G25) -> 6062177.8 | L108: =M84-M94 -> -1844021.2
J109: =IF((M86+M88)=0,M84,(M93*Hoja15!J114-Hoja15!K114)) -> 13702706 | L109: =IF((M86+M88)>0,M84-M94,0) -> 0
J110: =M93*Hoja15!J114-Hoja15!K114 -> 15546728 | L110: =IF(F108>0,1,0) -> 1 | M110: =IF(L110=0,"FIJO","VARIABLE") -> VARIABLE
F111: Impuestos Pagados durante el año | L111: =IF((M86+M88)>0,1,0) -> 0 | M111: =IF(L111=0,"NO HAY","SI HAY") -> NO HAY
F112: Base tributable anual | J112: =P26 -> 13702706
F113: Pagos Directos efectuados en el año | J113: =N26 -> 88002957 | L113: =IF((L110+L111)=0,0,IF(L111=0,0,M84-M94)) -> 0
F114: Pago Directo APV opción B final | J114: 0
Z130: =Hoja1!G17 -> 13952288
J131: =J135-J136 -> -1641584.1
P132: Impuesto único por retiros de Ahorro Previsional Voluntario | Y132: =AF56 -> 0
E134: BASE IMPONIBLE GLOBAL COMPLEMENTARIO | J134: =SUM(J138:J140) -> 89358141 | AA134: =J138+J140-J272-J34-R5 -> 89358141
E135: Impuesto global complementario según tabla. (Art. 52) | J135: =IF(I26>0,AA140,AA136) -> 12310704
E136: Crédito por impuesto único segunda categoría. (Art. 56 N° 2) | J136: =Z130+Hoja1!O17 -> 13952288 | M136: (actualizado) | AA136: =(AA134*VLOOKUP(AA134,Hoja15!$J$105:$M$112,3))-(VLOOKUP(AA134,Hoja15!$J$105:$M$112,4)) -> 12310704
E138: Rentas Artículo 42 N° 1 (sueldos) | J138: =Hoja1!F17 -> 89358141 | M138: (actualizado) | AA138: =AA134+J139 -> 89358141
E139: Rentas Artículo 42 N° 1 (pensiones) | J139: =R26 -> 0
E140: Rentas Artículo 42 N° 2 (honorarios) | J140: =AB41 -> 0 | AA140: =(AA138*VLOOKUP(AA138,Hoja15!$J$105:$M$112,3))-(VLOOKUP(AA138,Hoja15!$J$105:$M$112,4)) -> 12310704
X144: =Hoja4!C44 -> 0
V191: ANTIGUO CALCULO | X191: =IF((R197+R198+Y132-R199-#REF!)>0,(R197+R198+Y132-R199-#REF!),IF(AE43=0,0,R197+R198+Y132-R199-#REF!)) -> #REF!
I197: IMPUESTO GLOBAL COMPLEMENTARIO | R197: =IF(V26>0,IF(AA50=0,Hoja2!U33,X52),X52) -> 0
I198: Diferencia de Reliquidación Formulario 2514 | R198: =BL26-P26-T26 -> 0
I199: Retención de honorarios | R199: =X26 -> 0
...

Sheet Hoja8

Sheet Hoja7

Sheet Hoja15
B6: Enero | C6: =Hoja14!I229 -> 67429 | E6: =$C$6*J6 -> 0 | F6: =$C$6*$K$6 -> 910291.5 | G6: =L6 -> 0 | H6: =$C$6*$M$6 -> 0 | J6: 0 | K6: 13.5 | L6: 0 | M6: 0 | U6: =C6 -> 67429 | AJ6: =B6 -> Enero | AK6: =Hoja14!P14/C6 -> 8.0044058
B7: Febrero | C7: =Hoja14!I230 -> 67294 | E7: =$C$6*$J$7 -> 910291.5 | F7: =$C$6*$K$7 -> 2022870 | G7: =L7 -> 0.04 | H7: =$C$6*$M$7 -> 36411.66 | J7: 13.5 | K7: 30 | L7: 0.04 | M7: 0.54 | O7: 36679 | U7: =C7 -> 67294 | AJ7: =B7 -> Febrero | AK7: =Hoja14!P15/C7 -> 8.010255
B8: Marzo | C8: =Hoja14!I231 -> 68034 | E8: =$C$6*$J$8 -> 2022870 | F8: =$C$6*$K$8 -> 3371450 | G8: =L8 -> 0.08 | H8: =$C$6*$M$8 -> 117326.46 | J8: 30 | K8: 50 | L8: 0.08 | M8: 1.74 | O8: 36569 | U8: =C8 -> 68034 | AJ8: =B8 -> Marzo | AK8: =Hoja14!P16/C8 -> 117.5379
B9: Abril | C9: =Hoja14!I232 -> 68306 | E9: =$C$6*$J$9 -> 3371450 | F9: =$C$6*$K$9 -> 4720030 | G9: =L9 -> 0.135 | H9: =$C$6*$M$9 -> 302756.21 | J9: 50 | K9: 70 | L9: 0.135 | M9: 4.49 | O9: 36752 | U9: =C9 -> 68306 | AJ9: =B9 -> Abril | AK9: =Hoja14!P17/C9 -> 7.6745032
B10: Mayo | C10: =Hoja14!I233 -> 68648 | E10: =$C$6*$J$10 -> 4720030 | F10: =$C$6*$K$10 -> 6068610 | G10: =L10 -> 0.23 | H10: =$C$6*$M$10 -> 751159.06 | J10: 70 | K10: 90 | L10: 0.23 | M10: 11.14 | O10: 36862 | U10: =C10 -> 68648 | AJ10: =B10 -> Mayo | AK10: =Hoja14!P18/C10 -> 7.5669597
B11: Junio | C11: =Hoja14!I234 -> 68785 | E11: =$C$6*$J$11 -> 6068610 | F11: =$C$6*$K$11 -> 8091480 | G11: =L11 -> 0.304 | H11: =$C$6*$M$11 -> 1200236.2 | J11: 90 | K11: 120 | L11: 0.304 | M11: 17.8 | O11: 36899 | U11: =C11 -> 68785 | AA11: 2014 | AB11: UTM (1) | AC11: UTA (2) | AD11: Indice de Precios al Consumidor (IPC) | AE11: Variación Porcentual | AJ11: =B11 -> Junio | AK11: =Hoja14!P19/C11 -> 7.5203194
B12: Julio | C12: =Hoja14!I235 -> 68923 | E12: =$C$6*$J$12 -> 8091480 | F12: =$C$6*$K$12 -> 20902990 | G12: =L12 -> 0.35 | H12: =$C$6*$M$12 -> 1572444.3 | J12: 120 | K12: 310 | L12: 0.35 | M12: 23.32 | O12: 37083 | U12: =C12 -> 68923 | AD12: Valor en puntos (6) | AE12: Mensual (3) | AF12: Acumulado 2014 (4) | AG12: Ultimos 12 meses (5) | AJ12: =B12 -> Julio | AK12: =Hoja14!P20/C12 -> 7.493579
B13: Agosto | C13: =Hoja14!I236 -> 68647 | E13: =$C$6*$J$13 -> 20902990 | F13: =$C$6*$K$13 -> 674290000 | G13: =L13 -> 0.4 | H13: =$C$6*$M$13 -> 2617593.8 | J13: 310 | K13: 10000 | L13: 0.4 | M13: 38.82 | O13: 37231 | U13: =C13 -> 68647 | AA13: Enero | AB13: 40935 | AC13: 491220 | AD13: 101.69 | AE13: 0.2 | AF13: 0.2 | AG13: 3 | AJ13: =B13 -> Agosto | AK13: =Hoja14!P21/C13 -> 7.5437837
B14: Septiembre | C14: =Hoja14!I237 -> 69265 | O14: 37231 | U14: =C14 -> 69265 | AA14: Febrero | AB14: 41181 | AC14: 494172 | AD14: 102.18 | AE14: 0.5 | AF14: 0.7 | AG14: 3.4 | AJ14: =B14 -> Septiembre | AK14: =Hoja14!P22/C14 -> 7.3647699 | AM14: |
B15: Octubre | C15: =Hoja14!I238 -> 69265 | E15: =$C$7*J6 -> 0 | F15: =$C$7*K6 -> 908469 | G15: 0 | H15: =$C$7*M6 -> 0 | O15: 37231 | U15: =C15 -> 69265 | AA15: Marzo | AB15: 41263 | AC15: 495156 | AD15: 103.04 | AE15: 0.8 | AF15: 1.5 | AG15: 3.9 | AJ15: =B15 -> Octubre | AK15: =Hoja14!P23/C15 -> 7.3647699
B16: Noviembre | C16: =Hoja14!I239 -> 69542 | E16: =$C$7*J7 -> 908469 | F16: =$C$7*K7 -> 2018820 | G16: 0.04 | H16: =$C$7*M7 -> 36338.76 | O16: 37231 | U16: =C16 -> 69542 | AA16: Abril | AB16: 41469 | AC16: 497628 | AD16: 103.68 | AE16: 0.6 | AF16: 2.1 | AG16: 5 | AJ16: =B16 -> Noviembre | AK16: =Hoja14!P24/C16 -> 7.2776699
B17: Diciembre | C17: =Hoja14!I240 -> 69542 | E17: =$C$7*J8 -> 2018820 | F17: =$C$7*K8 -> 3364700 | G17: 0.08 | H17: =$C$7*M8 -> 117091.56 | J17: =Hoja14!N15*Hoja15!G17-Hoja15!H17 -> 331150.96 | O17: 37231 | U17: =C17 -> 69542 | AA17: Mayo | AB17: 41801 | AC17: 501612 | AD17: 104.03 | AE17: 0.3 | AF17: 2.5 | AG17: 5.4 | AJ17: =B17 -> Diciembre | AK17: =Hoja14!P25/C17 -> 7.2721803
E18: =$C$7*J9 -> 3364700 | F18: =$C$7*K9 -> 4710580 | G18: 0.135 | H18: =$C$7*M9 -> 302150.06 | O18: 37231 | AA18: Junio | AB18: 42052 | AC18: 504624 | AD18: 104.08 | AE18: 0.1 | AF18: 2.5 | AG18: 4.8 | AK18: =SUM(AK6:AK17) -> 200.6311 | AL18: =AK18*C17 -> 13952288
E19: =$C$7*J10 -> 4710580 | F19: =$C$7*K10 -> 6056460 | G19: 0.23 | H19: =$C$7*M10 -> 749655.16 | J19: =8*C17*12 -> 6676032 | AA19: Julio | AB19: 42178 | AC19: 506136 | AD19: 104.32 | AE19: 0.2 | AF19: 2.8 | AG19: 4.7
C20: =(C17-C6)/C6 -> 0.031336665 | E20: =$C$7*J11 -> 6056460 | F20: =$C$7*K11 -> 8075280 | G20: 0.304 | H20: =$C$7*M11 -> 1197833.2 | Q20: =Hoja14!J138+Hoja14!J140-Hoja14!J272-Hoja14!J34 -> 89358141 | X20: =455*34000 -> 15470000 | AA20: Agosto | AB20: 42220 | AC20: 506640 | AD20: 104.66 | AE20: 0.3 | AF20: 3.1 | AG20: 4.8
E21: =$C$7*J12 -> 8075280 | F21: =$C$7*K12 -> 20861140 | G21: 0.35 | H21: =$C$7*M12 -> 1569296.1 | AA21: Septiembre | AB21: 42304 | AC21: 507648 | AD21: 105.54 | AE21: 0.8 | AF21: 4 | AG21: 5.1
E22: =$C$7*J13 -> 20861140 | F22: =$C$7*K13 -> 672940000 | G22: 0.4 | H22: =$C$7*M13 -> 2612353.1 | M22: 0 | N22: =90*B23 -> 75105360 | O22: 1 | Q22: =Q20/B23 -> 107.07934 | AA22: Octubre | AB22: 42431 | AC22: 509172 | AD22: 106.64 | AE22: 1 | AF22: 5.1 | AG22: 6.1 | AK22: =Hoja14!N26*Hoja15!L111-Hoja15!M111 -> 11340402
B23: =C17*12 -> 834504 | M23: =N22+0.1 -> 75105360 | N23: =150*B23 -> 125175600 | O23: =Q23 -> 0.71498734 | Q23: =(250-Q22*1.667)/100 -> 0.71498734 | AA23: Noviembre | AB23: 42770 | AC23: 513240
E24: =$C$8*J6 -> 0 | F24: =$C$8*K6 -> 918459 | G24: 0 | H24: =$C$8*M6 -> 0 | M24: =N23+0.1 -> 1.251756e+08 | N24: y más | O24: 0 | AA24: Diciembre | AB24: 43198 | AC24: 518376
E25: =$C$8*J7 -> 918459 | F25: =$C$8*K7 -> 2041020 | G25: 0.04 | H25: =$C$8*M7 -> 36738.36 | J25: 47646524
E26: =$C$8*J8 -> 2041020 | F26: =$C$8*K8 -> 3401700 | G26: 0.08 | H26: =$C$8*M8 -> 118379.16
B27: =Hoja14!P14/Hoja15!C6 -> 8.0044058 | C27: =Hoja14!P14/Hoja14!F14 -> 14.061153 | E27: =$C$8*J9 -> 3401700 | F27: =$C$8*K9 -> 4762380 | G27: 0.135 | H27: =$C$8*M9 -> 305472.66 | N27: =VLOOKUP($Q$20,$M$22:$O$24,3) -> 0.71498734
B28: =Hoja14!P15/Hoja15!C7 -> 8.010255 | C28: =Hoja14!P15/Hoja14!F15 -> 13.947499 | E28: =$C$8*J10 -> 4762380 | F28: =$C$8*K10 -> 6123060 | G28: 0.23 | H28: =$C$8*M10 -> 757898.76
B29: =Hoja14!P16/Hoja15!C8 -> 117.5379 | C29: =Hoja14!P16/Hoja14!F16 -> 205.59857 | E29: =$C$8*J11 -> 6123060 | F29: =$C$8*K11 -> 8164080 | G29: 0.304 | H29: =$C$8*M11 -> 1211005.2
B30: =Hoja14!P17/Hoja15!C9 -> 7.6745032 | C30: =Hoja14!P17/Hoja14!F17 -> 13.41546 | E30: =$C$8*J12 -> 8164080 | F30: =$C$8*K12 -> 21090540 | G30: 0.35 | H30: =$C$8*M12 -> 1586552.9 | J30: =J25*G31-H31 -> 16417530
B31: =Hoja14!P18/Hoja15!C10 -> 7.5669597 | C31: =Hoja14!P18/Hoja14!F18 -> 13.255013 | E31: =$C$8*J13 -> 21090540 | F31: =$C$8*K13 -> 680340000 | G31: 0.4 | H31: =$C$8*M13 -> 2641079.9
B32: =Hoja14!P19/Hoja15!C11 -> 7.5203194 | C32: =Hoja14!P19/Hoja14!F19 -> 13.173511
B33: =Hoja14!P20/Hoja15!C12 -> 7.493579 | C33: =Hoja14!P20/Hoja14!F20 -> 13.182568 | E33: =$C$9*$J$6 -> 0 | F33: =$C$9*$K$6 -> 922131 | G33: 0 | H33: =$C$9*$M$6 -> 0
B34: =Hoja14!P21/Hoja15!C13 -> 7.5437837 | C34: =Hoja14!P21/Hoja14!F21 -> 13.149257 | E34: =$C$9*$J$7 -> 922131 | F34: =$C$9*$K$7 -> 2049180 | G34: 0.04 | H34: =$C$9*$M$7 -> 36885.24
B35: =Hoja14!P22/Hoja15!C14 -> 7.3647699 | C35: =Hoja14!P22/Hoja14!F22 -> 12.919144 | E35: =$C$9*$J$8 -> 2049180 | F35: =$C$9*$K$8 -> 3415300 | G35: 0.08 | H35: =$C$9*$M$8 -> 118852.44 | J35: =Hoja14!N17*Hoja15!G35-Hoja15!H35 -> 328153.98
B36: =Hoja14!P23/Hoja15!C15 -> 7.3647699 | C36: =Hoja14!P23/Hoja14!F23 -> 12.919144 | E36: =$C$9*$J$9 -> 3415300 | F36: =$C$9*$K$9 -> 4781420 | G36: 0.135 | H36: =$C$9*$M$9 -> 306693.94
B37: =Hoja14!P24/Hoja15!C16 -> 7.2776699 | C37: =Hoja14!P24/Hoja14!F24 -> 12.781149 | E37: =$C$9*$J$10 -> 4781420 | F37: =$C$9*$K$10 -> 6147540 | G37: 0.23 | H37: =$C$9*$M$10 -> 760928.84
B38: =Hoja14!P25/Hoja15!C17 -> 7.2721803 | C38: =Hoja14!P25/Hoja14!F25 -> 12.756715 | E38: =$C$9*$J$11 -> 6147540 | F38: =$C$9*$K$11 -> 8196720 | G38: 0.304 | H38: =$C$9*$M$11 -> 1215846.8
B39: =SUM(B27:B38) -> 200.6311 | C39: =SUM(C27:C38) -> 351.15919 | E39: =$C$9*$J$12 -> 8196720 | F39: =$C$9*$K$12 -> 21174860 | G39: 0.35 | H39: =$C$9*$M$12 -> 1592895.9
C40: =C39*Hoja14!F25 -> 13921211 | E40: =$C$9*$J$13 -> 21174860 | F40: =$C$9*$K$13 -> 683060000 | G40: 0.4 | H40: =$C$9*$M$13 -> 2651638.9
E42: =$C$10*$J$6 -> 0 | F42: =$C$10*$K$6 -> 926748 | G42: 0 | H42: =$C$10*$M$6 -> 0
E43: =$C$10*$J$7 -> 926748 | F43: =$C$10*$K$7 -> 2059440 | G43: 0.04 | H43: =$C$10*$M$7 -> 37069.92 | K43: =25629*8*50 -> 10251600
E44: =$C$10*$J$8 -> 2059440 | F44: =$C$10*$K$8 -> 3432400 | G44: 0.08 | H44: =$C$10*$M$8 -> 119447.52
E45: =$C$10*$J$9 -> 3432400 | F45: =$C$10*$K$9 -> 4805360 | G45: 0.135 | H45: =$C$10*$M$9 -> 308229.52
E46: =$C$10*$J$10 -> 4805360 | F46: =$C$10*$K$10 -> 6178320 | G46: 0.23 | H46: =$C$10*$M$10 -> 764738.72
E47: =$C$10*$J$11 -> 6178320 | F47: =$C$10*$K$11 -> 8237760 | G47: 0.304 | H47: =$C$10*$M$11 -> 1221934.4
E48: =$C$10*$J$12 -> 8237760 | F48: =$C$10*$K$12 -> 21280880 | G48: 0.35 | H48: =$C$10*$M$12 -> 1600871.4
E49: =$C$10*$J$13 -> 21280880 | F49: =$C$10*$K$13 -> 686480000 | G49: 0.4 | H49: =$C$10*$M$13 -> 2664915.4
E51: =$C$11*$J$6 -> 0 | F51: =$C$11*$K$6 -> 928597.5 | G51: 0 | H51: =$C$11*$M$6 -> 0
E52: =$C$11*$J$7 -> 928597.5 | F52: =$C$11*$K$7 -> 2063550 | G52: 0.04 | H52: =$C$11*$M$7 -> 37143.9
E53: =$C$11*$J$8 -> 2063550 | F53: =$C$11*$K$8 -> 3439250 | G53: 0.08 | H53: =$C$11*$M$8 -> 119685.9
E54: =$C$11*$J$9 -> 3439250 | F54: =$C$11*$K$9 -> 4814950 | G54: 0.135 | H54: =$C$11*$M$9 -> 308844.65
E55: =$C$11*$J$10 -> 4814950 | F55: =$C$11*$K$10 -> 6190650 | G55: 0.23 | H55: =$C$11*$M$10 -> 766264.9
E56: =$C$11*$J$11 -> 6190650 | F56: =$C$11*$K$11 -> 8254200 | G56: 0.304 | H56: =$C$11*$M$11 -> 1224373
E57: =$C$11*$J$12 -> 8254200 | F57: =$C$11*$K$12 -> 21323350 | G57: 0.35 | H57: =$C$11*$M$12 -> 1604066.2
E58: =$C$11*$J$13 -> 21323350 | F58: =$C$11*$K$13 -> 687850000 | G58: 0.4 | H58: =$C$11*$M$13 -> 2670233.7
E60: =$C$12*$J$6 -> 0 | F60: =$C$12*$K$6 -> 930460.5 | G60: 0 | H60: =$C$12*$M$6 -> 0
E61: =$C$12*$J$7 -> 930460.5 | F61: =$C$12*$K$7 -> 2067690 | G61: 0.04 | H61: =$C$12*$M$7 -> 37218.42
E62: =$C$12*$J$8 -> 2067690 | F62: =$C$12*$K$8 -> 3446150 | G62: 0.08 | H62: =$C$12*$M$8 -> 119926.02
E63: =$C$12*$J$9 -> 3446150 | F63: =$C$12*$K$9 -> 4824610 | G63: 0.135 | H63: =$C$12*$M$9 -> 309464.27
E64: =$C$12*$J$10 -> 4824610 | F64: =$C$12*$K$10 -> 6203070 | G64: 0.23 | H64: =$C$12*$M$10 -> 767802.22
E65: =$C$12*$J$11 -> 6203070 | F65: =$C$12*$K$11 -> 8270760 | G65: 0.304 | H65: =$C$12*$M$11 -> 1226829.4
E66: =$C$12*$J$12 -> 8270760 | F66: =$C$12*$K$12 -> 21366130 | G66: 0.35 | H66: =$C$12*$M$12 -> 1607284.4
E67: =$C$12*$J$13 -> 21366130 | F67: =$C$12*$K$13 -> 689230000 | G67: 0.4 | H67: =$C$12*$M$13 -> 2675590.9
E69: =$C$13*$J$6 -> 0 | F69: =$C$13*$K$6 -> 926734.5 | G69: 0 | H69: =$C$13*$M$6 -> 0
E70: =$C$13*$J$7 -> 926734.5 | F70: =$C$13*$K$7 -> 2059410 | G70: 0.04 | H70: =$C$13*$M$7 -> 37069.38
E71: =$C$13*$J$8 -> 2059410 | F71: =$C$13*$K$8 -> 3432350 | G71: 0.08 | H71: =$C$13*$M$8 -> 119445.78
E72: =$C$13*$J$9 -> 3432350 | F72: =$C$13*$K$9 -> 4805290 | G72: 0.135 | H72: =$C$13*$M$9 -> 308225.03
E73: =$C$13*$J$10 -> 4805290 | F73: =$C$13*$K$10 -> 6178230 | G73: 0.23 | H73: =$C$13*$M$10 -> 764727.58
E74: =$C$13*$J$11 -> 6178230 | F74: =$C$13*$K$11 -> 8237640 | G74: 0.304 | H74: =$C$13*$M$11 -> 1221916.6
E75: =$C$13*$J$12 -> 8237640 | F75: =$C$13*$K$12 -> 21280570 | G75: 0.35 | H75: =$C$13*$M$12 -> 1600848
E76: =$C$13*$J$13 -> 21280570 | F76: =$C$13*$K$13 -> 686470000 | G76: 0.4 | H76: =$C$13*$M$13 -> 2664876.5
E78: =$C$14*$J$6 -> 0 | F78: =$C$14*$K$6 -> 935077.5 | G78: 0 | H78: =$C$14*$M$6 -> 0
E79: =$C$14*$J$7 -> 935077.5 | F79: =$C$14*$K$7 -> 2077950 | G79: 0.04 | H79: =$C$14*$M$7 -> 37403.1
E80: =$C$14*$J$8 -> 2077950 | F80: =$C$14*$K$8 -> 3463250 | G80: 0.08 | H80: =$C$14*$M$8 -> 120521.1
E81: =$C$14*$J$9 -> 3463250 | F81: =$C$14*$K$9 -> 4848550 | G81: 0.135 | H81: =$C$14*$M$9 -> 310999.85
E82: =$C$14*$J$10 -> 4848550 | F82: =$C$14*$K$10 -> 6233850 | G82: 0.23 | H82: =$C$14*$M$10 -> 771612.1
E83: =$C$14*$J$11 -> 6233850 | F83: =$C$14*$K$11 -> 8311800 | G83: 0.304 | H83: =$C$14*$M$11 -> 1232917
E84: =$C$14*$J$12 -> 8311800 | F84: =$C$14*$K$12 -> 21472150 | G84: 0.35 | H84: =$C$14*$M$12 -> 1615259.8
E85: =$C$14*$J$13 -> 21472150 | F85: =$C$14*$K$13 -> 692650000 | G85: 0.4 | H85: =$C$14*$M$13 -> 2688867.3
E87: =$C$15*$J$6 -> 0 | F87: =$C$15*$K$6 -> 935077.5 | G87: 0 | H87: =$C$15*$M$6 -> 0
E88: =$C$15*$J$7 -> 935077.5 | F88: =$C$15*$K$7 -> 2077950 | G88: 0.04 | H88: =$C$15*$M$7 -> 37403.1
E89: =$C$15*$J$8 -> 2077950 | F89: =$C$15*$K$8 -> 3463250 | G89: 0.08 | H89: =$C$15*$M$8 -> 120521.1
E90: =$C$15*$J$9 -> 3463250 | F90: =$C$15*$K$9 -> 4848550 | G90: 0.135 | H90: =$C$15*$M$9 -> 310999.85 | O90: Tramo | P90: Desde | Q90: Hasta | R90: Factor | S90: Rebaja | V90: Tramo | W90: Desde | X90: Hasta | Y90: Factor | Z90: Rebaja | AB90: Tramo | AC90: Desde | AD90: Hasta | AE90: Factor | AF90: Rebaja
E91: =$C$15*$J$10 -> 4848550 | F91: =$C$15*$K$10 -> 6233850 | G91: 0.23 | H91: =$C$15*$M$10 -> 771612.1 | O91: 1 | P91: 0 | Q91: 13.5 | R91: 0 | S91: 0 | V91: 1 | W91: =E105 -> 0 | X91: =F105 -> 938817 | Y91: 0 | Z91: =H105 -> 0 | AB91: 1 | AC91: =P91*$C$17 -> 0 | AD91: =Q91*$C$17 -> 938817 | AE91: 0 | AF91: =S91*$C$17 -> 0
E92: =$C$15*$J$11 -> 6233850 | F92: =$C$15*$K$11 -> 8311800 | G92: 0.304 | H92: =$C$15*$M$11 -> 1232917 | K92: =Hoja14!AA134*Hoja15!L112-Hoja15!M112 -> 3347811 | O92: 2 | P92: 13.5 | Q92: 30 | R92: 0.04 | S92: 0.54 | V92: 2 | W92: =E106 -> 938817 | X92: =F106 -> 2086260 | Y92: 0.04 | Z92: =H106 -> 37552.68 | AB92: 2 | AC92: =P92*$C$17 -> 938817 | AD92: =Q92*$C$17 -> 2086260 | AE92: 0.04 | AF92: =S92*$C$17 -> 37552.68
E93: =$C$15*$J$12 -> 8311800 | F93: =$C$15*$K$12 -> 21472150 | G93: 0.35 | H93: =$C$15*$M$12 -> 1615259.8 | O93: 3 | P93: 30 | Q93: 50 | R93: 0.08 | S93: 1.74 | V93: 3 | W93: =E107 -> 2086260 | X93: =F107 -> 3477100 | Y93: 0.08 | Z93: =H107 -> 121003.08 | AB93: 3 | AC93: =P93*$C$17 -> 2086260 | AD93: =Q93*$C$17 -> 3477100 | AE93: 0.08 | AF93: =S93*$C$17 -> 121003.08
E94: =$C$15*$J$13 -> 21472150 | F94: =$C$15*$K$13 -> 692650000 | G94: 0.4 | H94: =$C$15*$M$13 -> 2688867.3 | O94: 4 | P94: 50 | Q94: 70 | R94: 0.135 | S94: 4.49 | V94: 4 | W94: =E108 -> 3477100 | X94: =F108 -> 4867940 | Y94: 0.135 | Z94: =H108 -> 312243.58 | AB94: 4 | AC94: =P94*$C$17 -> 3477100 | AD94: =Q94*$C$17 -> 4867940 | AE94: 0.135 | AF94: =S94*$C$17 -> 312243.58
O95: 5 | P95: 70 | Q95: 90 | R95: 0.23 | S95: 11.14 | V95: 5 | W95: =E109 -> 4867940 | X95: =F109 -> 6258780 | Y95: 0.23 | Z95: =H109 -> 774697.88 | AB95: 5 | AC95: =P95*$C$17 -> 4867940 | AD95: =Q95*$C$17 -> 6258780 | AE95: 0.23 | AF95: =S95*$C$17 -> 774697.88
E96: =$C$16*$J$6 -> 0 | F96: =$C$16*$K$6 -> 938817 | G96: 0 | H96: =$C$16*$M$6 -> 0 | O96: 6 | P96: 90 | Q96: 120 | R96: 0.304 | S96: 17.8 | V96: 6 | W96: =E110 -> 6258780 | X96: =F110 -> 8345040 | Y96: 0.304 | Z96: =H110 -> 1237847.6 | AB96: 6 | AC96: =P96*$C$17 -> 6258780 | AD96: =Q96*$C$17 -> 8345040 | AE96: 0.304 | AF96: =S96*$C$17 -> 1237847.6
E97: =$C$16*$J$7 -> 938817 | F97: =$C$16*$K$7 -> 2086260 | G97: 0.04 | H97: =$C$16*$M$7 -> 37552.68 | O97: 7 | P97: 120 | Q97: y más | R97: 0.35 | S97: 23.32 | V97: 7 | W97: =E111 -> 8345040 | X97: =F111 -> 21558020 | Y97: 0.355 | Z97: =H111 -> 1621719.4 | AB97: 7 | AC97: =P97*$C$17 -> 8345040 | AD97: y más | AE97: 0.35 | AF97: =S97*$C$17 -> 1621719.4
E98: =$C$16*$J$8 -> 2086260 | F98: =$C$16*$K$8 -> 3477100 | G98: 0.08 | H98: =$C$16*$M$8 -> 121003.08 | V98: 7 | W98: =E112 -> 21558020 | X98: y más | Y98: 0.4 | Z98: =H112 -> 2699620.4
E99: =$C$16*$J$9 -> 3477100 | F99: =$C$16*$K$9 -> 4867940 | G99: 0.135 | H99: =$C$16*$M$9 -> 312243.58 | J99: =2700000*G109-H109 -> -153697.88
E100: =$C$16*$J$10 -> 4867940 | F100: =$C$16*$K$10 -> 6258780 | G100: 0.23 | H100: =$C$16*$M$10 -> 774697.88
E101: =$C$16*$J$11 -> 6258780 | F101: =$C$16*$K$11 -> 8345040 | G101: 0.304 | H101: =$C$16*$M$11 -> 1237847.6
E102: =$C$16*$J$12 -> 8345040 | F102: =$C$16*$K$12 -> 21558020 | G102: 0.35 | H102: =$C$16*$M$12 -> 1621719.4
E103: =$C$16*$J$13 -> 21558020 | F103: =$C$16*$K$13 -> 695420000 | G103: 0.4 | H103: =$C$16*$M$13 -> 2699620.4
E105: =$C$17*$J$6 -> 0 | F105: =$C$17*$K$6 -> 938817 | G105: 0 | H105: =$C$17*$M$6 -> 0 | J105: =E105*12 -> 0 | K105: =F105*12 -> 11265804 | L105: 0 | M105: =H105*12 -> 0 | O105: =Hoja14!AZ38 -> 88002957 | P105: =VLOOKUP(O105,$J$105:$M$112,3) -> 0.304 | Q105: =VLOOKUP(O105,$J$105:$M$112,4) -> 14854171 | R105: =O105*P105-Q105 -> 11898728
E106: =$C$17*$J$7 -> 938817 | F106: =$C$17*$K$7 -> 2086260 | G106: 0.04 | H106: =$C$17*$M$7 -> 37552.68 | J106: =E106*12 -> 11265804 | K106: =F106*12 -> 25035120 | L106: 0.04 | M106: =H106*12 -> 450632.16 | O106: =Hoja14!BA38 -> 88002957 | P106: =VLOOKUP(O106,$J$105:$M$112,3) -> 0.304 | Q106: =VLOOKUP(O106,$J$105:$M$112,4) -> 14854171 | R106: =O106*P106-Q106 -> 11898728
E107: =$C$17*$J$8 -> 2086260 | F107: =$C$17*$K$8 -> 3477100 | G107: 0.08 | H107: =$C$17*$M$8 -> 121003.08 | J107: =E107*12 -> 25035120 | K107: =F107*12 -> 41725200 | L107: 0.08 | M107: =H107*12 -> 1452037 | R107: =R106-R105 -> 0
E108: =$C$17*$J$9 -> 3477100 | F108: =$C$17*$K$9 -> 4867940 | G108: 0.135 | H108: =$C$17*$M$9 -> 312243.58 | J108: =E108*12 -> 41725200 | K108: =F108*12 -> 58415280 | L108: 0.135 | M108: =H108*12 -> 3746923 | R108: =Hoja14!X26 -> 0
E109: =$C$17*$J$10 -> 4867940 | F109: =$C$17*$K$10 -> 6258780 | G109: 0.23 | H109: =$C$17*$M$10 -> 774697.88 | J109: =E109*12 -> 58415280 | K109: =F109*12 -> 75105360 | L109: 0.23 | M109: =H109*12 -> 9296374.6 | R109: =(R107-R108)*-1 -> 0
E110: =$C$17*$J$11 -> 6258780 | F110: =$C$17*$K$11 -> 8345040 | G110: 0.304 | H110: =$C$17*$M$11 -> 1237847.6 | J110: =E110*12 -> 75105360 | K110: =F110*12 -> 100140480 | L110: 0.304 | M110: =H110*12 -> 14854171
E111: =$C$17*$J$12 -> 8345040 | F111: =$C$17*$K$12 -> 21558020 | G111: 0.35 | H111: =$C$17*$M$12 -> 1621719.4 | J111: =E111*12 -> 1.0014048e+08 | K111: =F111*12 -> 258696240 | L111: 0.35 | M111: =H111*12 -> 19460633
E112: =$C$17*$J$13 -> 21558020 | F112: =$C$17*$K$13 -> 695420000 | G112: 0.4 | H112: =$C$17*$M$13 -> 2699620.4 | J112: =E112*12 -> 2.5869624e+08 | K112: =F112*12 -> 8345040000 | L112: 0.4 | M112: =H112*12 -> 32395445
...

Sheet Hoja9
L2: UTA | M2: =Hoja14!I240*12 -> 834504
B3: Renta tributable | C3: Pensión Tributable | D3: Impuetso sueldo | E3: Impuesto Pensión | F3: Honorarios | G3: Retenciones | H3: APV empleador | I3: APV directo | L3: UTA 15 | M3: =Hoja14!I240*12*15 -> 12517560
B4: =Hoja14!CM26 -> 88002957 | C4: =Hoja14!CN26 -> 0 | D4: =Hoja14!CO26 -> 13702706 | E4: =Hoja14!CP26 -> 0 | F4: =Hoja14!CQ26 -> 0 | G4: =Hoja14!CR26 -> 0 | H4: =Hoja14!CS26 -> 14106991 | I4: =Hoja14!AM32 -> 0 | L4: UTA 8 | M4: =Hoja14!I240*12*8 -> 6676032
L6: Base UTA | M6: =C13/M2 -> 119.8352 | O6: Intereses | P6: =Hoja14!P5 -> 0
P7: =P6/M2 -> 0 | R7: 0 | S7: 90 | T7: 1
B8: Sueldo | C8: =B4+Hoja14!R30 -> 1.0000296e+08 | O8: Maximo | P8: =MIN(P7*T12,8)*M2 -> 0 | R8: 90.0001 | S8: 150 | T8: =(250-1.667*M6)/100 -> 0.50234715
B9: Pensión | C9: =C4 -> 0 | L9: Gastos | M9: =MIN(30%*Hoja14!CQ26,Hoja9!M3) -> 0 | R9: 150.0001 | S9: y más | T9: 0
B10: Honorarios | C10: =F4 -> 0 | G10: Retención | H10: =H15*15% -> 1500000
B11: Gastos presuntos | C11: =MIN(C10*30%,M3) -> 0
B12: APV directo | C12: =I4+Hoja14!J34 -> 0 | T12: =VLOOKUP(M6,R7:T9,3) -> 0.50234715
B13: Subtotal | C13: =C8+C9+C10-C11-C12 -> 1.0000296e+08 | G13: 57 bis | H13: =Hoja14!R7 -> 0
B14: Intereses | C14: =Q15 -> 0 | Q14: =MIN(M4,Hoja14!P5) -> 0 | R14: =IF(M6<=90,100%,IF(M6>150,0%,T8)) -> 0.50234715
B15: Base Global | C15: =C13-C14 -> 1.0000296e+08 | G15: Retiro | H15: =Hoja14!P4 -> 10000000 | Q15: =Q14*R14 -> 0
B16: Impuesto Global | C16: =C15*VLOOKUP(C15,Hoja15!$J$105:$M$112,3)-VLOOKUP(C15,Hoja15!$J$105:$M$112,4) -> 15546728 | G16: B+R | H16: =C15+H15 -> 1.1000296e+08
B17: Crédito IUSC | C17: =D4+E4 -> 13702706 | D17: =C16-C17 -> 1844021.2 | G17: IGC B+R | H17: =H16*VLOOKUP(H16,Hoja15!$J$105:$M$112,3)-VLOOKUP(H16,Hoja15!$J$105:$M$112,4) -> 19040402
B18: Retenciones | C18: =G4 -> 0 | G18: Pensionado | H18: =IFERROR((H17-C16)/H15,0) -> 0.34936739 | I18: =H18*H15 -> 3493673.9
B19: Resultado | C19: =C16-C17-C18 -> 1844021.2 | G19: No pensionado | H19: =(H18*1.1)+3% -> 0.41430413 | I19: =H19*H15 -> 4143041.3
B20: 55 bis | C20: =H13 -> 0 | I20: =IF(Hoja14!P3="no pensionado",Hoja9!I19,Hoja9!I18) -> 3493673.9
B21: Retiro APV | C21: =I20 -> 3493673.9 | I21: =IFERROR(I20/H15," ") -> 0.34936739
B22: Retención | C22: =-H10 -> -1500000
B23: Final | C23: =C19+C20+C21+C22 -> 3837695.2
E26: =Hoja14!P26+Hoja14!T26 -> 13702706
E27: =C16-E26 -> 1844021.2

Sheet Hoja1
C5: Enero | D5: =Hoja15!C6 -> 67429 | F5: =Hoja14!N14/D5*$D$16 -> 5788435.9 | G5: =Hoja14!P14/Hoja1!D5*Hoja1!$D$16 -> 556642.39 | I5: =Hoja2!K13/D5*$D$16 -> 8412468.3 | J5: =Hoja2!M13/Hoja1!D5*Hoja1!$D$16 -> 1322644.5 | N5: =Hoja14!R14/D5*$D$16 -> 0 | O5: =Hoja14!T14/Hoja1!D5*Hoja1!$D$16 -> 0
C6: Febrero | D6: =Hoja15!C7 -> 67294 | F6: =Hoja14!N15/D6*$D$16 -> 5790204.5 | G6: =Hoja14!P15/Hoja1!D6*Hoja1!$D$16 -> 557049.15 | I6: =Hoja2!K14/D6*$D$16 -> 8425136.5 | J6: =Hoja2!M14/Hoja1!D6*Hoja1!$D$16 -> 1327078.3 | N6: =Hoja14!R15/D6*$D$16 -> 0 | O6: =Hoja14!T15/Hoja1!D6*Hoja1!$D$16 -> 0
C7: Marzo | D7: =Hoja15!C8 -> 68034 | F7: =Hoja14!N16/D7*$D$16 -> 27183603 | G7: =Hoja14!P16/Hoja1!D7*Hoja1!$D$16 -> 8173820.7 | I7: =Hoja2!K15/D7*$D$16 -> 8329608.7 | J7: =Hoja2!M15/Hoja1!D7*Hoja1!$D$16 -> 1294353.4 | N7: =Hoja14!R16/D7*$D$16 -> 0 | O7: =Hoja14!T16/Hoja1!D7*Hoja1!$D$16 -> 0
C8: Abril | D8: =Hoja15!C9 -> 68306 | F8: =Hoja14!N17/D8*$D$16 -> 5688687.7 | G8: =Hoja14!P17/Hoja1!D8*Hoja1!$D$16 -> 533700.3 | I8: =Hoja2!K16/D8*$D$16 -> 8293587.3 | J8: =Hoja2!M16/Hoja1!D8*Hoja1!$D$16 -> 1283402.9 | N8: =Hoja14!R17/D8*$D$16 -> 0 | O8: =Hoja14!T17/Hoja1!D8*Hoja1!$D$16 -> 0
C9: Mayo | D9: =Hoja15!C10 -> 68648 | F9: =Hoja14!N18/D9*$D$16 -> 5656171.3 | G9: =Hoja14!P18/Hoja1!D9*Hoja1!$D$16 -> 526221.51 | I9: =Hoja2!K17/D9*$D$16 -> 8250484 | J9: =Hoja2!M17/Hoja1!D9*Hoja1!$D$16 -> 1270299.5 | N9: =Hoja14!R18/D9*$D$16 -> 0 | O9: =Hoja14!T18/Hoja1!D9*Hoja1!$D$16 -> 0
C10: Junio | D10: =Hoja15!C11 -> 68785 | F10: =Hoja14!N19/D10*$D$16 -> 5642069.3 | G10: =Hoja14!P19/Hoja1!D10*Hoja1!$D$16 -> 522978.05 | I10: =Hoja2!K18/D10*$D$16 -> 8232838.7 | J10: =Hoja2!M18/Hoja1!D10*Hoja1!$D$16 -> 1264935.4 | N10: =Hoja14!R19/D10*$D$16 -> 0 | O10: =Hoja14!T19/Hoja1!D10*Hoja1!$D$16 -> 0
C11: Julio | D11: =Hoja15!C12 -> 68923 | F11: =Hoja14!N20/D11*$D$16 -> 5633984.1 | G11: =Hoja14!P20/Hoja1!D11*Hoja1!$D$16 -> 521118.47 | I11: =Hoja2!K19/D11*$D$16 -> 8217727.6 | J11: =Hoja2!M19/Hoja1!D11*Hoja1!$D$16 -> 1260341.6 | N11: =Hoja14!R20/D11*$D$16 -> 0 | O11: =Hoja14!T20/Hoja1!D11*Hoja1!$D$16 -> 0
C12: Agosto | D12: =Hoja15!C13 -> 68647 | F12: =Hoja14!N21/D12*$D$16 -> 5649163.8 | G12: =Hoja14!P21/Hoja1!D12*Hoja1!$D$16 -> 524609.8 | I12: =Hoja2!K20/D12*$D$16 -> 8247573.2 | J12: =Hoja2!M20/Hoja1!D12*Hoja1!$D$16 -> 1269414.7 | N12: =Hoja14!R21/D12*$D$16 -> 0 | O12: =Hoja14!T21/Hoja1!D12*Hoja1!$D$16 -> 0
C13: Septiembre | D13: =Hoja15!C14 -> 69265 | F13: =Hoja14!N22/D13*$D$16 -> 5595037.9 | G13: =Hoja14!P22/Hoja1!D13*Hoja1!$D$16 -> 512160.83 | I13: =Hoja2!K21/D13*$D$16 -> 8172394.8 | J13: =Hoja2!M21/Hoja1!D13*Hoja1!$D$16 -> 1246560.4 | N13: =Hoja14!R22/D13*$D$16 -> 0 | O13: =Hoja14!T22/Hoja1!D13*Hoja1!$D$16 -> 0
C14: Octubre | D14: =Hoja15!C15 -> 69265 | F14: =Hoja14!N23/D14*$D$16 -> 5595037.9 | G14: =Hoja14!P23/Hoja1!D14*Hoja1!$D$16 -> 512160.83 | I14: =Hoja2!K22/D14*$D$16 -> 8172394.8 | J14: =Hoja2!M22/Hoja1!D14*Hoja1!$D$16 -> 1246560.4 | N14: =Hoja14!R23/D14*$D$16 -> 0 | O14: =Hoja14!T23/Hoja1!D14*Hoja1!$D$16 -> 0
C15: Noviembre | D15: =Hoja15!C16 -> 69542 | F15: =Hoja14!N24/D15*$D$16 -> 5568702.6 | G15: =Hoja14!P24/Hoja1!D15*Hoja1!$D$16 -> 506103.72 | I15: =Hoja2!K23/D15*$D$16 -> 8138111.5 | J15: =Hoja2!M23/Hoja1!D15*Hoja1!$D$16 -> 1236138.3 | N15: =Hoja14!R24/D15*$D$16 -> 0 | O15: =Hoja14!T24/Hoja1!D15*Hoja1!$D$16 -> 0
C16: Diciembre | D16: =Hoja15!C17 -> 69542 | F16: =Hoja14!N25/D16*$D$16 -> 5567042.8 | G16: =Hoja14!P25/Hoja1!D16*Hoja1!$D$16 -> 505721.96 | I16: =Hoja2!K24/D16*$D$16 -> 8137401.9 | J16: =Hoja2!M24/Hoja1!D16*Hoja1!$D$16 -> 1235922.6 | N16: =Hoja14!R25/D16*$D$16 -> 0 | O16: =Hoja14!T25/Hoja1!D16*Hoja1!$D$16 -> 0
F17: =SUM(F5:F16) -> 89358141 | G17: =SUM(G5:G16) -> 13952288 | I17: =SUM(I5:I16) -> 99029727 | J17: =SUM(J5:J16) -> 15257652 | L17: =G17-J17 -> -1305364.3 | N17: =SUM(N5:N16) -> 0 | O17: =SUM(O5:O16) -> 0
F18: =F23 -> 12310704 | I18: =I23 -> 15250866 | N18: =N23 -> 0
F20: =VLOOKUP(F17,Hoja15!$J$105:$M$112,3) -> 0.304 | I20: =VLOOKUP(I17,Hoja15!$J$105:$M$112,3) -> 0.304 | N20: =VLOOKUP(N17,Hoja15!$J$105:$M$112,3) -> 0
F21: =VLOOKUP(F17,Hoja15!$J$105:$M$112,4) -> 14854171 | I21: =VLOOKUP(I17,Hoja15!$J$105:$M$112,4) -> 14854171 | N21: =VLOOKUP(N17,Hoja15!$J$105:$M$112,4) -> 0
F23: =F17*F20-F21 -> 12310704 | I23: =I17*I20-I21 -> 15250866 | N23: =N17*N20-N21 -> 0
G26: =G17-F18 -> 1641584.1

Sheet imp cte
B6: Enero | C6: =Hoja15!C6 -> 67429 | E6: =$C$6*J6 -> 0 | F6: =$C$6*$K$6 -> 910291.5 | G6: =Hoja15!G6 -> 0 | H6: =$C$6*$M$6 -> 0 | J6: 0 | K6: 13.5 | L6: =Hoja15!L6 -> 0 | M6: =Hoja15!M6 -> 0
B7: Febrero | C7: =Hoja15!C7 -> 67294 | E7: =$C$6*$J$7 -> 910291.5 | F7: =$C$6*$K$7 -> 2022870 | G7: =Hoja15!G7 -> 0.04 | H7: =$C$6*$M$7 -> 36411.66 | J7: 13.5 | K7: 30 | L7: =Hoja15!L7 -> 0.04 | M7: =Hoja15!M7 -> 0.54 | O7: 36679
B8: Marzo | C8: =Hoja15!C8 -> 68034 | E8: =$C$6*$J$8 -> 2022870 | F8: =$C$6*$K$8 -> 3371450 | G8: =Hoja15!G8 -> 0.08 | H8: =$C$6*$M$8 -> 117326.46 | J8: 30 | K8: 50 | L8: =Hoja15!L8 -> 0.08 | M8: =Hoja15!M8 -> 1.74 | O8: 36569
B9: Abril | C9: =Hoja15!C9 -> 68306 | E9: =$C$6*$J$9 -> 3371450 | F9: =$C$6*$K$9 -> 4720030 | G9: =Hoja15!G9 -> 0.135 | H9: =$C$6*$M$9 -> 302756.21 | J9: 50 | K9: 70 | L9: =Hoja15!L9 -> 0.135 | M9: =Hoja15!M9 -> 4.49 | O9: 36752
B10: Mayo | C10: =Hoja15!C10 -> 68648 | E10: =$C$6*$J$10 -> 4720030 | F10: =$C$6*$K$10 -> 6068610 | G10: =Hoja15!G10 -> 0.23 | H10: =$C$6*$M$10 -> 751159.06 | J10: 70 | K10: 90 | L10: =Hoja15!L10 -> 0.23 | M10: =Hoja15!M10 -> 11.14 | O10: 36862
B11: Junio | C11: =Hoja15!C11 -> 68785 | E11: =$C$6*$J$11 -> 6068610 | F11: =$C$6*$K$11 -> 8091480 | G11: =Hoja15!G11 -> 0.304 | H11: =$C$6*$M$11 -> 1200236.2 | J11: 90 | K11: 120 | L11: =Hoja15!L11 -> 0.304 | M11: =Hoja15!M11 -> 17.8 | O11: 36899
B12: Julio | C12: =Hoja15!C12 -> 68923 | E12: =$C$6*$J$12 -> 8091480 | F12: =$C$6*$K$12 -> 10114350 | G12: =Hoja15!G12 -> 0.35 | H12: =$C$6*$M$12 -> 1572444.3 | J12: 120 | K12: 150 | L12: =Hoja15!L12 -> 0.35 | M12: =Hoja15!M12 -> 23.32 | O12: 37083
B13: Agosto | C13: =Hoja15!C13 -> 68647 | E13: =$C$6*$J$13 -> 10114350 | F13: y más | G13: =Hoja15!G13 -> 0.4 | H13: =$C$6*$M$13 -> 2617593.8 | J13: 150 | K13: y más | L13: =Hoja15!L13 -> 0.4 | M13: =Hoja15!M13 -> 38.82 | O13: 37231
B14: Septiembre | C14: =Hoja15!C14 -> 69265 | G14: =Hoja15!G14 -> 0 | O14: 37231
B15: Octubre | C15: =Hoja15!C15 -> 69265 | E15: =$C$7*J6 -> 0 | F15: =$C$7*K6 -> 908469 | G15: =Hoja15!G15 -> 0 | H15: =$C$7*M6 -> 0 | O15: 37231
B16: Noviembre | C16: =Hoja15!C16 -> 69542 | E16: =$C$7*J7 -> 908469 | F16: =$C$7*K7 -> 2018820 | G16: =Hoja15!G16 -> 0.04 | H16: =$C$7*M7 -> 36338.76 | O16: 37231
B17: Diciembre | C17: =Hoja15!C17 -> 69542 | E17: =$C$7*J8 -> 2018820 | F17: =$C$7*K8 -> 3364700 | G17: =Hoja15!G17 -> 0.08 | H17: =$C$7*M8 -> 117091.56 | J17: =Hoja14!N15*Hoja15!G17-Hoja15!H17 -> 331150.96 | O17: 37231
E18: =$C$7*J9 -> 3364700 | F18: =$C$7*K9 -> 4710580 | G18: =Hoja15!G18 -> 0.135 | H18: =$C$7*M9 -> 302150.06 | O18: 37231
E19: =$C$7*J10 -> 4710580 | F19: =$C$7*K10 -> 6056460 | G19: =Hoja15!G19 -> 0.23 | H19: =$C$7*M10 -> 749655.16
C20: =(C17-C6)/C6 -> 0.031336665 | E20: =$C$7*J11 -> 6056460 | F20: =$C$7*K11 -> 8075280 | G20: =Hoja15!G20 -> 0.304 | H20: =$C$7*M11 -> 1197833.2 | Q20: =Hoja14!J138+Hoja14!J140-Hoja14!J272-Hoja14!J34 -> 89358141
E21: =$C$7*J12 -> 8075280 | F21: =$C$7*K12 -> 10094100 | G21: =Hoja15!G21 -> 0.35 | H21: =$C$7*M12 -> 1569296.1
E22: =$C$7*J13 -> 10094100 | F22: y más | G22: =Hoja15!G22 -> 0.4 | H22: =$C$7*M13 -> 2612353.1 | M22: 0 | N22: =90*B23 -> 75105360 | O22: 1 | Q22: =Q20/B23 -> 107.07934
B23: =C17*12 -> 834504 | G23: =Hoja15!G23 -> 0 | M23: =N22+0.1 -> 75105360 | N23: =150*B23 -> 125175600 | O23: =Q23 -> 0.71498734 | Q23: =(250-Q22*1.667)/100 -> 0.71498734
E24: =$C$8*J6 -> 0 | F24: =$C$8*K6 -> 918459 | G24: =Hoja15!G24 -> 0 | H24: =$C$8*M6 -> 0 | M24: =N23+0.1 -> 1.251756e+08 | N24: y más | O24: 0
E25: =$C$8*J7 -> 918459 | F25: =$C$8*K7 -> 2041020 | G25: =Hoja15!G25 -> 0.04 | H25: =$C$8*M7 -> 36738.36
E26: =$C$8*J8 -> 2041020 | F26: =$C$8*K8 -> 3401700 | G26: =Hoja15!G26 -> 0.08 | H26: =$C$8*M8 -> 118379.16
B27: =Hoja14!P14/Hoja15!C6 -> 8.0044058 | C27: =Hoja14!P14/Hoja14!F14 -> 14.061153 | E27: =$C$8*J9 -> 3401700 | F27: =$C$8*K9 -> 4762380 | G27: =Hoja15!G27 -> 0.135 | H27: =$C$8*M9 -> 305472.66 | N27: =VLOOKUP($Q$20,$M$22:$O$24,3) -> 0.71498734
B28: =Hoja14!P15/Hoja15!C7 -> 8.010255 | C28: =Hoja14!P15/Hoja14!F15 -> 13.947499 | E28: =$C$8*J10 -> 4762380 | F28: =$C$8*K10 -> 6123060 | G28: =Hoja15!G28 -> 0.23 | H28: =$C$8*M10 -> 757898.76
B29: =Hoja14!P16/Hoja15!C8 -> 117.5379 | C29: =Hoja14!P16/Hoja14!F16 -> 205.59857 | E29: =$C$8*J11 -> 6123060 | F29: =$C$8*K11 -> 8164080 | G29: =Hoja15!G29 -> 0.304 | H29: =$C$8*M11 -> 1211005.2
B30: =Hoja14!P17/Hoja15!C9 -> 7.6745032 | C30: =Hoja14!P17/Hoja14!F17 -> 13.41546 | E30: =$C$8*J12 -> 8164080 | F30: =$C$8*K12 -> 10205100 | G30: =Hoja15!G30 -> 0.35 | H30: =$C$8*M12 -> 1586552.9
B31: =Hoja14!P18/Hoja15!C10 -> 7.5669597 | C31: =Hoja14!P18/Hoja14!F18 -> 13.255013 | E31: =$C$8*J13 -> 10205100 | F31: y más | G31: =Hoja15!G31 -> 0.4 | H31: =$C$8*M13 -> 2641079.9
B32: =Hoja14!P19/Hoja15!C11 -> 7.5203194 | C32: =Hoja14!P19/Hoja14!F19 -> 13.173511 | G32: =Hoja15!G32 -> 0
B33: =Hoja14!P20/Hoja15!C12 -> 7.493579 | C33: =Hoja14!P20/Hoja14!F20 -> 13.182568 | E33: =$C$9*$J$6 -> 0 | F33: =$C$9*$K$6 -> 922131 | G33: =Hoja15!G33 -> 0 | H33: =$C$9*$M$6 -> 0
B34: =Hoja14!P21/Hoja15!C13 -> 7.5437837 | C34: =Hoja14!P21/Hoja14!F21 -> 13.149257 | E34: =$C$9*$J$7 -> 922131 | F34: =$C$9*$K$7 -> 2049180 | G34: =Hoja15!G34 -> 0.04 | H34: =$C$9*$M$7 -> 36885.24
B35: =Hoja14!P22/Hoja15!C14 -> 7.3647699 | C35: =Hoja14!P22/Hoja14!F22 -> 12.919144 | E35: =$C$9*$J$8 -> 2049180 | F35: =$C$9*$K$8 -> 3415300 | G35: =Hoja15!G35 -> 0.08 | H35: =$C$9*$M$8 -> 118852.44 | J35: =Hoja14!N17*Hoja15!G35-Hoja15!H35 -> 328153.98
B36: =Hoja14!P23/Hoja15!C15 -> 7.3647699 | C36: =Hoja14!P23/Hoja14!F23 -> 12.919144 | E36: =$C$9*$J$9 -> 3415300 | F36: =$C$9*$K$9 -> 4781420 | G36: =Hoja15!G36 -> 0.135 | H36: =$C$9*$M$9 -> 306693.94 | L36: =B6 -> Enero | M36: =Hoja14!N14 -> 5612557.1 | N36: =(M36*VLOOKUP(M36,$E$6:$H$13,3))-(VLOOKUP(M36,$E$6:$H$13,4)) -> 539729.08
B37: =Hoja14!P24/Hoja15!C16 -> 7.2776699 | C37: =Hoja14!P24/Hoja14!F24 -> 12.781149 | E37: =$C$9*$J$10 -> 4781420 | F37: =$C$9*$K$10 -> 6147540 | G37: =Hoja15!G37 -> 0.23 | H37: =$C$9*$M$10 -> 760928.84 | L37: =B7 -> Febrero | M37: =Hoja14!N15 -> 5603031.6 | N37: =(M37*VLOOKUP(M37,$E$6:$H$13,3))-(VLOOKUP(M37,$E$6:$H$13,4)) -> 537538.2
B38: =Hoja14!P25/Hoja15!C17 -> 7.2721803 | C38: =Hoja14!P25/Hoja14!F25 -> 12.756715 | E38: =$C$9*$J$11 -> 6147540 | F38: =$C$9*$K$11 -> 8196720 | G38: =Hoja15!G38 -> 0.304 | H38: =$C$9*$M$11 -> 1215846.8 | L38: =B8 -> Marzo | M38: =Hoja14!N16 -> 26594133 | N38: =(M38*VLOOKUP(M38,$E$6:$H$13,3))-(VLOOKUP(M38,$E$6:$H$13,4)) -> 8020059.6
B39: =SUM(B27:B38) -> 200.6311 | C39: =SUM(C27:C38) -> 351.15919 | E39: =$C$9*$J$12 -> 8196720 | F39: =$C$9*$K$12 -> 10245900 | G39: =Hoja15!G39 -> 0.35 | H39: =$C$9*$M$12 -> 1592895.9 | L39: =B9 -> Abril | M39: =Hoja14!N17 -> 5587580.2 | N39: =(M39*VLOOKUP(M39,$E$6:$H$13,3))-(VLOOKUP(M39,$E$6:$H$13,4)) -> 533984.39
C40: =C39*Hoja14!F25 -> 13921211 | E40: =$C$9*$J$13 -> 10245900 | F40: y más | G40: =Hoja15!G40 -> 0.4 | H40: =$C$9*$M$13 -> 2651638.9 | L40: =B10 -> Mayo | M40: =Hoja14!N18 -> 5583458.1 | N40: =(M40*VLOOKUP(M40,$E$6:$H$13,3))-(VLOOKUP(M40,$E$6:$H$13,4)) -> 533036.31
G41: =Hoja15!G41 -> 0 | L41: =B11 -> Junio | M41: =Hoja14!N19 -> 5580652.5 | N41: =(M41*VLOOKUP(M41,$E$6:$H$13,3))-(VLOOKUP(M41,$E$6:$H$13,4)) -> 532391.01
E42: =$C$10*$J$6 -> 0 | F42: =$C$10*$K$6 -> 926748 | G42: =Hoja15!G42 -> 0 | H42: =$C$10*$M$6 -> 0 | L42: =B12 -> Julio | M42: =Hoja14!N20 -> 5583835.5 | N42: =(M42*VLOOKUP(M42,$E$6:$H$13,3))-(VLOOKUP(M42,$E$6:$H$13,4)) -> 533123.11
E43: =$C$10*$J$7 -> 926748 | F43: =$C$10*$K$7 -> 2059440 | G43: =Hoja15!G43 -> 0.04 | H43: =$C$10*$M$7 -> 37069.92 | L43: =B13 -> Agosto | M43: =Hoja14!N21 -> 5576459.6 | N43: =(M43*VLOOKUP(M43,$E$6:$H$13,3))-(VLOOKUP(M43,$E$6:$H$13,4)) -> 531426.64
E44: =$C$10*$J$8 -> 2059440 | F44: =$C$10*$K$8 -> 3432400 | G44: =Hoja15!G44 -> 0.08 | H44: =$C$10*$M$8 -> 119447.52 | L44: =B14 -> Septiembre | M44: =Hoja14!N22 -> 5572751.7 | N44: =(M44*VLOOKUP(M44,$E$6:$H$13,3))-(VLOOKUP(M44,$E$6:$H$13,4)) -> 530573.83
E45: =$C$10*$J$9 -> 3432400 | F45: =$C$10*$K$9 -> 4805360 | G45: =Hoja15!G45 -> 0.135 | H45: =$C$10*$M$9 -> 308229.52 | L45: =B15 -> Octubre | M45: =Hoja14!N23 -> 5572751.7 | N45: =(M45*VLOOKUP(M45,$E$6:$H$13,3))-(VLOOKUP(M45,$E$6:$H$13,4)) -> 530573.83
E46: =$C$10*$J$10 -> 4805360 | F46: =$C$10*$K$10 -> 6178320 | G46: =Hoja15!G46 -> 0.23 | H46: =$C$10*$M$10 -> 764738.72 | L46: =B16 -> Noviembre | M46: =Hoja14!N24 -> 5568702.6 | N46: =(M46*VLOOKUP(M46,$E$6:$H$13,3))-(VLOOKUP(M46,$E$6:$H$13,4)) -> 529642.54
E47: =$C$10*$J$11 -> 6178320 | F47: =$C$10*$K$11 -> 8237760 | G47: =Hoja15!G47 -> 0.304 | H47: =$C$10*$M$11 -> 1221934.4 | L47: =B17 -> Diciembre | M47: =Hoja14!N25 -> 5567042.8 | N47: =(M47*VLOOKUP(M47,$E$6:$H$13,3))-(VLOOKUP(M47,$E$6:$H$13,4)) -> 529260.78
E48: =$C$10*$J$12 -> 8237760 | F48: =$C$10*$K$12 -> 10297200 | G48: =Hoja15!G48 -> 0.35 | H48: =$C$10*$M$12 -> 1600871.4 | N48: =SUM(N36:N47) -> 13881339
E49: =$C$10*$J$13 -> 10297200 | F49: y más | G49: =Hoja15!G49 -> 0.4 | H49: =$C$10*$M$13 -> 2664915.4
G50: =Hoja15!G50 -> 0
E51: =$C$11*$J$6 -> 0 | F51: =$C$11*$K$6 -> 928597.5 | G51: =Hoja15!G51 -> 0 | H51: =$C$11*$M$6 -> 0
E52: =$C$11*$J$7 -> 928597.5 | F52: =$C$11*$K$7 -> 2063550 | G52: =Hoja15!G52 -> 0.04 | H52: =$C$11*$M$7 -> 37143.9
E53: =$C$11*$J$8 -> 2063550 | F53: =$C$11*$K$8 -> 3439250 | G53: =Hoja15!G53 -> 0.08 | H53: =$C$11*$M$8 -> 119685.9
E54: =$C$11*$J$9 -> 3439250 | F54: =$C$11*$K$9 -> 4814950 | G54: =Hoja15!G54 -> 0.135 | H54: =$C$11*$M$9 -> 308844.65
E55: =$C$11*$J$10 -> 4814950 | F55: =$C$11*$K$10 -> 6190650 | G55: =Hoja15!G55 -> 0.23 | H55: =$C$11*$M$10 -> 766264.9
E56: =$C$11*$J$11 -> 6190650 | F56: =$C$11*$K$11 -> 8254200 | G56: =Hoja15!G56 -> 0.304 | H56: =$C$11*$M$11 -> 1224373
E57: =$C$11*$J$12 -> 8254200 | F57: =$C$11*$K$12 -> 10317750 | G57: =Hoja15!G57 -> 0.35 | H57: =$C$11*$M$12 -> 1604066.2
E58: =$C$11*$J$13 -> 10317750 | F58: y más | G58: =Hoja15!G58 -> 0.4 | H58: =$C$11*$M$13 -> 2670233.7
G59: =Hoja15!G59 -> 0
E60: =$C$12*$J$6 -> 0 | F60: =$C$12*$K$6 -> 930460.5 | G60: =Hoja15!G60 -> 0 | H60: =$C$12*$M$6 -> 0
E61: =$C$12*$J$7 -> 930460.5 | F61: =$C$12*$K$7 -> 2067690 | G61: =Hoja15!G61 -> 0.04 | H61: =$C$12*$M$7 -> 37218.42
E62: =$C$12*$J$8 -> 2067690 | F62: =$C$12*$K$8 -> 3446150 | G62: =Hoja15!G62 -> 0.08 | H62: =$C$12*$M$8 -> 119926.02
E63: =$C$12*$J$9 -> 3446150 | F63: =$C$12*$K$9 -> 4824610 | G63: =Hoja15!G63 -> 0.135 | H63: =$C$12*$M$9 -> 309464.27
E64: =$C$12*$J$10 -> 4824610 | F64: =$C$12*$K$10 -> 6203070 | G64: =Hoja15!G64 -> 0.23 | H64: =$C$12*$M$10 -> 767802.22
E65: =$C$12*$J$11 -> 6203070 | F65: =$C$12*$K$11 -> 8270760 | G65: =Hoja15!G65 -> 0.304 | H65: =$C$12*$M$11 -> 1226829.4
E66: =$C$12*$J$12 -> 8270760 | F66: =$C$12*$K$12 -> 10338450 | G66: =Hoja15!G66 -> 0.35 | H66: =$C$12*$M$12 -> 1607284.4
E67: =$C$12*$J$13 -> 10338450 | F67: y más | G67: =Hoja15!G67 -> 0.4 | H67: =$C$12*$M$13 -> 2675590.9
G68: =Hoja15!G68 -> 0
E69: =$C$13*$J$6 -> 0 | F69: =$C$13*$K$6 -> 926734.5 | G69: =Hoja15!G69 -> 0 | H69: =$C$13*$M$6 -> 0
E70: =$C$13*$J$7 -> 926734.5 | F70: =$C$13*$K$7 -> 2059410 | G70: =Hoja15!G70 -> 0.04 | H70: =$C$13*$M$7 -> 37069.38
E71: =$C$13*$J$8 -> 2059410 | F71: =$C$13*$K$8 -> 3432350 | G71: =Hoja15!G71 -> 0.08 | H71: =$C$13*$M$8 -> 119445.78
E72: =$C$13*$J$9 -> 3432350 | F72: =$C$13*$K$9 -> 4805290 | G72: =Hoja15!G72 -> 0.135 | H72: =$C$13*$M$9 -> 308225.03
E73: =$C$13*$J$10 -> 4805290 | F73: =$C$13*$K$10 -> 6178230 | G73: =Hoja15!G73 -> 0.23 | H73: =$C$13*$M$10 -> 764727.58
E74: =$C$13*$J$11 -> 6178230 | F74: =$C$13*$K$11 -> 8237640 | G74: =Hoja15!G74 -> 0.304 | H74: =$C$13*$M$11 -> 1221916.6
E75: =$C$13*$J$12 -> 8237640 | F75: =$C$13*$K$12 -> 10297050 | G75: =Hoja15!G75 -> 0.35 | H75: =$C$13*$M$12 -> 1600848
E76: =$C$13*$J$13 -> 10297050 | F76: y más | G76: =Hoja15!G76 -> 0.4 | H76: =$C$13*$M$13 -> 2664876.5
G77: =Hoja15!G77 -> 0
E78: =$C$14*$J$6 -> 0 | F78: =$C$14*$K$6 -> 935077.5 | G78: =Hoja15!G78 -> 0 | H78: =$C$14*$M$6 -> 0
E79: =$C$14*$J$7 -> 935077.5 | F79: =$C$14*$K$7 -> 2077950 | G79: =Hoja15!G79 -> 0.04 | H79: =$C$14*$M$7 -> 37403.1
E80: =$C$14*$J$8 -> 2077950 | F80: =$C$14*$K$8 -> 3463250 | G80: =Hoja15!G80 -> 0.08 | H80: =$C$14*$M$8 -> 120521.1
E81: =$C$14*$J$9 -> 3463250 | F81: =$C$14*$K$9 -> 4848550 | G81: =Hoja15!G81 -> 0.135 | H81: =$C$14*$M$9 -> 310999.85
E82: =$C$14*$J$10 -> 4848550 | F82: =$C$14*$K$10 -> 6233850 | G82: =Hoja15!G82 -> 0.23 | H82: =$C$14*$M$10 -> 771612.1
E83: =$C$14*$J$11 -> 6233850 | F83: =$C$14*$K$11 -> 8311800 | G83: =Hoja15!G83 -> 0.304 | H83: =$C$14*$M$11 -> 1232917
E84: =$C$14*$J$12 -> 8311800 | F84: =$C$14*$K$12 -> 10389750 | G84: =Hoja15!G84 -> 0.35 | H84: =$C$14*$M$12 -> 1615259.8
E85: =$C$14*$J$13 -> 10389750 | F85: y más | G85: =Hoja15!G85 -> 0.4 | H85: =$C$14*$M$13 -> 2688867.3
G86: =Hoja15!G86 -> 0
E87: =$C$15*$J$6 -> 0 | F87: =$C$15*$K$6 -> 935077.5 | G87: =Hoja15!G87 -> 0 | H87: =$C$15*$M$6 -> 0
E88: =$C$15*$J$7 -> 935077.5 | F88: =$C$15*$K$7 -> 2077950 | G88: =Hoja15!G88 -> 0.04 | H88: =$C$15*$M$7 -> 37403.1
E89: =$C$15*$J$8 -> 2077950 | F89: =$C$15*$K$8 -> 3463250 | G89: =Hoja15!G89 -> 0.08 | H89: =$C$15*$M$8 -> 120521.1
E90: =$C$15*$J$9 -> 3463250 | F90: =$C$15*$K$9 -> 4848550 | G90: =Hoja15!G90 -> 0.135 | H90: =$C$15*$M$9 -> 310999.85
E91: =$C$15*$J$10 -> 4848550 | F91: =$C$15*$K$10 -> 6233850 | G91: =Hoja15!G91 -> 0.23 | H91: =$C$15*$M$10 -> 771612.1
E92: =$C$15*$J$11 -> 6233850 | F92: =$C$15*$K$11 -> 8311800 | G92: =Hoja15!G92 -> 0.304 | H92: =$C$15*$M$11 -> 1232917 | K92: =Hoja14!AA134*Hoja15!L112-Hoja15!M112 -> 3347811
E93: =$C$15*$J$12 -> 8311800 | F93: =$C$15*$K$12 -> 10389750 | G93: =Hoja15!G93 -> 0.35 | H93: =$C$15*$M$12 -> 1615259.8
E94: =$C$15*$J$13 -> 10389750 | F94: y más | G94: =Hoja15!G94 -> 0.4 | H94: =$C$15*$M$13 -> 2688867.3
G95: =Hoja15!G95 -> 0
E96: =$C$16*$J$6 -> 0 | F96: =$C$16*$K$6 -> 938817 | G96: =Hoja15!G96 -> 0 | H96: =$C$16*$M$6 -> 0
E97: =$C$16*$J$7 -> 938817 | F97: =$C$16*$K$7 -> 2086260 | G97: =Hoja15!G97 -> 0.04 | H97: =$C$16*$M$7 -> 37552.68
E98: =$C$16*$J$8 -> 2086260 | F98: =$C$16*$K$8 -> 3477100 | G98: =Hoja15!G98 -> 0.08 | H98: =$C$16*$M$8 -> 121003.08
E99: =$C$16*$J$9 -> 3477100 | F99: =$C$16*$K$9 -> 4867940 | G99: =Hoja15!G99 -> 0.135 | H99: =$C$16*$M$9 -> 312243.58 | J99: =2700000*G109-H109 -> -153697.88
E100: =$C$16*$J$10 -> 4867940 | F100: =$C$16*$K$10 -> 6258780 | G100: =Hoja15!G100 -> 0.23 | H100: =$C$16*$M$10 -> 774697.88
E101: =$C$16*$J$11 -> 6258780 | F101: =$C$16*$K$11 -> 8345040 | G101: =Hoja15!G101 -> 0.304 | H101: =$C$16*$M$11 -> 1237847.6
E102: =$C$16*$J$12 -> 8345040 | F102: =$C$16*$K$12 -> 10431300 | G102: =Hoja15!G102 -> 0.35 | H102: =$C$16*$M$12 -> 1621719.4
E103: =$C$16*$J$13 -> 10431300 | F103: y más | G103: =Hoja15!G103 -> 0.4 | H103: =$C$16*$M$13 -> 2699620.4
G104: =Hoja15!G104 -> 0
E105: =$C$17*$J$6 -> 0 | F105: =$C$17*$K$6 -> 938817 | G105: =Hoja15!G105 -> 0 | H105: =$C$17*$M$6 -> 0 | J105: =E105*12 -> 0 | K105: =F105*12 -> 11265804 | L105: 0 | M105: =H105*12 -> 0 | O105: =Hoja14!AZ38 -> 88002957 | P105: =VLOOKUP(O105,$J$105:$M$112,3) -> 0.32 | Q105: =VLOOKUP(O105,$J$105:$M$112,4) -> 14854171 | R105: =O105*P105-Q105 -> 13306775
...

Sheet Hoja3
B2: Día | C2: Ene | D2: Feb | E2: Mar | F2: Abr | G2: May | H2: Jun | I2: Jul | J2: Ago | K2: Sep | L2: Oct | M2: Nov | N2: Dic
B3: 1 | C3: 22296.19 | D3: 22412.68 | E3: 22463.56 | F3: 22536.41 | G3: 22592.72 | H3: 22621.53 | I3: 22627.36 | J3: 22576.98 | K3: 22559.48 | L3: 22592.56 | M3: 22738.63
B4: 2 | C4: 22298.34 | D4: 22417.01 | E4: 22464.34 | F4: 22539.31 | G4: 22594.22 | H4: 22622.26 | I4: 22627.36 | J4: 22574.79 | K4: 22559.48 | L4: 22594.06 | M4: 22744.48
B5: 3 | C5: 22300.5 | D5: 22421.34 | E5: 22465.11 | F5: 22542.22 | G5: 22595.73 | H5: 22622.99 | I5: 22627.36 | J5: 22572.6 | K5: 22559.48 | L5: 22595.57 | M5: 22750.32
B6: 4 | C6: 22302.65 | D6: 22425.66 | E6: 22465.89 | F6: 22545.12 | G6: 22597.23 | H6: 22623.72 | I6: 22627.36 | J6: 22570.41 | K6: 22559.48 | L6: 22597.07 | M6: 22756.17
B7: 5 | C7: 22304.81 | D7: 22429.99 | E7: 22466.66 | F7: 22548.02 | G7: 22598.74 | H7: 22624.45 | I7: 22627.36 | J7: 22568.23 | K7: 22559.48 | L7: 22598.58 | M7: 22762.02
B8: 6 | C8: 22306.96 | D8: 22434.32 | E8: 22467.43 | F8: 22550.93 | G8: 22600.24 | H8: 22625.18 | I8: 22627.36 | J8: 22566.04 | K8: 22559.48 | L8: 22600.08 | M8: 22767.87
B9: 7 | C9: 22309.12 | D9: 22438.65 | E9: 22468.21 | F9: 22553.83 | G9: 22601.75 | H9: 22625.91 | I9: 22627.36 | J9: 22563.85 | K9: 22559.48 | L9: 22601.59 | M9: 22773.73
B10: 8 | C10: 22311.27 | D10: 22442.98 | E10: 22468.98 | F10: 22556.73 | G10: 22603.25 | H10: 22626.64 | I10: 22627.36 | J10: 22561.66 | K10: 22559.48 | L10: 22603.09 | M10: 22779.58 | P10: 22408.36
B11: 9 | C11: 22313.43 | D11: 22447.31 | E11: 22469.76 | F11: 22559.64 | G11: 22604.76 | H11: 22627.36 | I11: 22627.36 | J11: 22559.48 | K11: 22559.48 | L11: 22604.6 | M11: 22785.44 | P11: 22462.79
B12: 10 | C12: 22317.74 | D12: 22448.08 | E12: 22472.65 | F12: 22561.14 | G12: 22605.49 | H12: 22627.36 | I12: 22625.17 | J12: 22559.48 | K12: 22560.98 | L12: 22610.41 | M12: 22785.44 | P12: 22533.51
B13: 11 | C13: 22322.04 | D13: 22448.86 | E13: 22475.55 | F13: 22562.65 | G13: 22606.22 | H13: 22627.36 | I13: 22622.97 | J13: 22559.48 | K13: 22562.49 | L13: 22616.22 | M13: 22785.44 | P13: 22591.21
B14: 12 | C14: 22326.35 | D14: 22449.63 | E14: 22478.44 | F14: 22564.15 | G14: 22606.95 | H14: 22627.36 | I14: 22620.78 | J14: 22559.48 | K14: 22563.99 | L14: 22622.04 | M14: 22785.44 | P14: 22620.8
B15: 13 | C15: 22330.66 | D15: 22450.4 | E15: 22481.34 | F15: 22565.65 | G15: 22607.68 | H15: 22627.36 | I15: 22618.59 | J15: 22559.48 | K15: 22565.49 | L15: 22627.85 | M15: 22785.44 | P15: 22627.36
B16: 14 | C16: 22334.97 | D16: 22451.18 | E16: 22484.23 | F16: 22567.15 | G16: 22608.4 | H16: 22627.36 | I16: 22616.4 | J16: 22559.48 | K16: 22566.99 | L16: 22633.67 | M16: 22785.44 | P16: 22579.16
B17: 15 | C17: 22339.28 | D17: 22451.95 | E17: 22487.13 | F17: 22568.66 | G17: 22609.13 | H17: 22627.36 | I17: 22614.21 | J17: 22559.48 | K17: 22568.5 | L17: 22639.49 | M17: 22785.44 | P17: 22559.48
B18: 16 | C18: 22343.59 | D18: 22452.73 | E18: 22490.02 | F18: 22570.16 | G18: 22609.86 | H18: 22627.36 | I18: 22612.01 | J18: 22559.48 | K18: 22570 | L18: 22645.31 | M18: 22785.44 | P18: 22591.05
B19: 17 | C19: 22347.9 | D19: 22453.5 | E19: 22492.92 | F19: 22571.66 | G19: 22610.59 | H19: 22627.36 | I19: 22609.82 | J19: 22559.48 | K19: 22571.5 | L19: 22651.13 | M19: 22785.44 | P19: 22732.79
B20: 18 | C20: 22352.22 | D20: 22454.27 | E20: 22495.82 | F20: 22573.17 | G20: 22611.32 | H20: 22627.36 | I20: 22607.63 | J20: 22559.48 | K20: 22573.01 | L20: 22656.95 | M20: 22785.44 | P20: 22785.44
B21: 19 | C21: 22356.53 | D21: 22455.05 | E21: 22498.71 | F21: 22574.67 | G21: 22612.05 | H21: 22627.36 | I21: 22605.44 | J21: 22559.48 | K21: 22574.51 | L21: 22662.78 | M21: 22785.44
B22: 20 | C22: 22360.84 | D22: 22455.82 | E22: 22501.61 | F22: 22576.17 | G22: 22612.78 | H22: 22627.36 | I22: 22603.25 | J22: 22559.48 | K22: 22576.01 | L22: 22668.6 | M22: 22785.44
B23: 21 | C23: 22365.16 | D23: 22456.6 | E23: 22504.51 | F23: 22577.68 | G23: 22613.51 | H23: 22627.36 | I23: 22601.06 | J23: 22559.48 | K23: 22577.52 | L23: 22674.43 | M23: 22785.44
B24: 22 | C24: 22369.48 | D24: 22457.37 | E24: 22507.41 | F24: 22579.18 | G24: 22614.24 | H24: 22627.36 | I24: 22598.87 | J24: 22559.48 | K24: 22579.02 | L24: 22680.26 | M24: 22785.44
B25: 23 | C25: 22373.79 | D25: 22458.14 | E25: 22510.31 | F25: 22580.68 | G25: 22614.97 | H25: 22627.36 | I25: 22596.68 | J25: 22559.48 | K25: 22580.52 | L25: 22686.09 | M25: 22785.44
B26: 24 | C26: 22378.11 | D26: 22458.92 | E26: 22513.21 | F26: 22582.19 | G26: 22615.69 | H26: 22627.36 | I26: 22594.49 | J26: 22559.48 | K26: 22582.03 | L26: 22691.92 | M26: 22785.44
B27: 25 | C27: 22382.43 | D27: 22459.69 | E27: 22516.1 | F27: 22583.69 | G27: 22616.42 | H27: 22627.36 | I27: 22592.3 | J27: 22559.48 | K27: 22583.53 | L27: 22697.76 | M27: 22785.44
B28: 26 | C28: 22386.75 | D28: 22460.47 | E28: 22519 | F28: 22585.2 | G28: 22617.15 | H28: 22627.36 | I28: 22590.11 | J28: 22559.48 | K28: 22585.04 | L28: 22703.59 | M28: 22785.44
B29: 27 | C29: 22391.07 | D29: 22461.24 | E29: 22521.9 | F29: 22586.7 | G29: 22617.88 | H29: 22627.36 | I29: 22587.92 | J29: 22559.48 | K29: 22586.54 | L29: 22709.43 | M29: 22785.44
B30: 28 | C30: 22395.39 | D30: 22462.01 | E30: 22524.8 | F30: 22588.21 | G30: 22618.61 | H30: 22627.36 | I30: 22585.73 | J30: 22559.48 | K30: 22588.04 | L30: 22715.26 | M30: 22785.44
B31: 29 | C31: 22399.71 | D31: 22462.79 | E31: 22527.71 | F31: 22589.71 | G31: 22619.34 | H31: 22627.36 | I31: 22583.54 | J31: 22559.48 | K31: 22589.55 | L31: 22721.1 | M31: 22785.44
B32: 30 | C32: 22404.04 | D32: 22462.79 | E32: 22530.61 | F32: 22591.21 | G32: 22620.07 | H32: 22627.36 | I32: 22581.35 | J32: 22559.48 | K32: 22591.05 | L32: 22726.94 | M32: 22785.44
B33: 31 | C33: 22408.36 | D33: 22462.79 | E33: 22533.51 | F33: 22591.21 | G33: 22620.8 | H33: 22627.36 | I33: 22579.16 | J33: 22559.48 | K33: 22591.05 | L33: 22732.79 | M33: 22785.44 | N33: 22785.44

Sheet Hoja4
C3: Impuesto 1(UTM) | D3: Impuesto 1 (UF) | E3: Renta 1 (UTM) | F3: Renta 1 (UF) | G3: Impuesto 2(UTM) | H3: Renta 2 (UTM) | I3: Honorarios | J3: Retención | L3: Reliquidación 2 rentas
B4: Enero | C4: =Hoja14!P14/Hoja15!C6 -> 8.0044058 | D4: =Hoja14!P14/Hoja14!F14 -> 14.061153 | E4: =Hoja14!N14/Hoja15!C6 -> 83.236547 | F4: =Hoja14!N14/Hoja14!F14 -> 146.21971 | G4: =Hoja14!T14/Hoja15!C6 -> 0 | H4: =Hoja14!R14/Hoja15!C6 -> 0 | I4: =Hoja14!V14/Hoja15!C6 -> 0 | J4: =Hoja14!X14/Hoja15!C6 -> 0 | L4: =Hoja14!BM26 -> 13952288
B5: Febrero | C5: =Hoja14!P15/Hoja15!C7 -> 8.010255 | D5: =Hoja14!P15/Hoja14!F15 -> 13.947499 | E5: =Hoja14!N15/Hoja15!C7 -> 83.261978 | F5: =Hoja14!N15/Hoja14!F15 -> 144.9762 | G5: =Hoja14!T15/Hoja15!C7 -> 0 | H5: =Hoja14!R15/Hoja15!C7 -> 0 | I5: =Hoja14!V15/Hoja15!C7 -> 0 | J5: =Hoja14!X15/Hoja15!C7 -> 0
B6: Marzo | C6: =Hoja14!P16/Hoja15!C8 -> 117.5379 | D6: =Hoja14!P16/Hoja14!F16 -> 205.59857 | E6: =Hoja14!N16/Hoja15!C8 -> 390.89475 | F6: =Hoja14!N16/Hoja14!F16 -> 683.75735 | G6: =Hoja14!T16/Hoja15!C8 -> 0 | H6: =Hoja14!R16/Hoja15!C8 -> 0 | I6: =Hoja14!V16/Hoja15!C8 -> 0 | J6: =Hoja14!X16/Hoja15!C8 -> 0
B7: Abril | C7: =Hoja14!P17/Hoja15!C9 -> 7.6745032 | D7: =Hoja14!P17/Hoja14!F17 -> 13.41546 | E7: =Hoja14!N17/Hoja15!C9 -> 81.802188 | F7: =Hoja14!N17/Hoja14!F17 -> 142.99479 | G7: =Hoja14!T17/Hoja15!C9 -> 0 | H7: =Hoja14!R17/Hoja15!C9 -> 0 | I7: =Hoja14!V17/Hoja15!C9 -> 0 | J7: =Hoja14!X17/Hoja15!C9 -> 0 | L7: 2514 | M7: =C17+G17-L4 -> 0
B8: Mayo | C8: =Hoja14!P18/Hoja15!C10 -> 7.5669597 | D8: =Hoja14!P18/Hoja14!F18 -> 13.255013 | E8: =Hoja14!N18/Hoja15!C10 -> 81.334608 | F8: =Hoja14!N18/Hoja14!F18 -> 142.4735 | G8: =Hoja14!T18/Hoja15!C10 -> 0 | H8: =Hoja14!R18/Hoja15!C10 -> 0 | I8: =Hoja14!V18/Hoja15!C10 -> 0 | J8: =Hoja14!X18/Hoja15!C10 -> 0
B9: Junio | C9: =Hoja14!P19/Hoja15!C11 -> 7.5203194 | D9: =Hoja14!P19/Hoja14!F19 -> 13.173511 | E9: =Hoja14!N19/Hoja15!C11 -> 81.131824 | F9: =Hoja14!N19/Hoja14!F19 -> 142.12042 | G9: =Hoja14!T19/Hoja15!C11 -> 0 | H9: =Hoja14!R19/Hoja15!C11 -> 0 | I9: =Hoja14!V19/Hoja15!C11 -> 0 | J9: =Hoja14!X19/Hoja15!C11 -> 0
B10: Julio | C10: =Hoja14!P20/Hoja15!C12 -> 7.493579 | D10: =Hoja14!P20/Hoja14!F20 -> 13.182568 | E10: =Hoja14!N20/Hoja15!C12 -> 81.015561 | F10: =Hoja14!N20/Hoja14!F20 -> 142.5211 | G10: =Hoja14!T20/Hoja15!C12 -> 0 | H10: =Hoja14!R20/Hoja15!C12 -> 0 | I10: =Hoja14!V20/Hoja15!C12 -> 0 | J10: =Hoja14!X20/Hoja15!C12 -> 0
B11: Agosto | C11: =Hoja14!P21/Hoja15!C13 -> 7.5437837 | D11: =Hoja14!P21/Hoja14!F21 -> 13.149257 | E11: =Hoja14!N21/Hoja15!C13 -> 81.233842 | F11: =Hoja14!N21/Hoja14!F21 -> 141.59535 | G11: =Hoja14!T21/Hoja15!C13 -> 0 | H11: =Hoja14!R21/Hoja15!C13 -> 0 | I11: =Hoja14!V21/Hoja15!C13 -> 0 | J11: =Hoja14!X21/Hoja15!C13 -> 0 | M11: Boleta y renta | N11: =K33 -> 0
B12: Septiembre | C12: =Hoja14!P22/Hoja15!C14 -> 7.3647699 | D12: =Hoja14!P22/Hoja14!F22 -> 12.919144 | E12: =Hoja14!N22/Hoja15!C14 -> 80.455521 | F12: =Hoja14!N22/Hoja14!F22 -> 141.13359 | G12: =Hoja14!T22/Hoja15!C14 -> 0 | H12: =Hoja14!R22/Hoja15!C14 -> 0 | I12: =Hoja14!V22/Hoja15!C14 -> 0 | J12: =Hoja14!X22/Hoja15!C14 -> 0
B13: Octubre | C13: =Hoja14!P23/Hoja15!C15 -> 7.3647699 | D13: =Hoja14!P23/Hoja14!F23 -> 12.919144 | E13: =Hoja14!N23/Hoja15!C15 -> 80.455521 | F13: =Hoja14!N23/Hoja14!F23 -> 141.13359 | G13: =Hoja14!T23/Hoja15!C15 -> 0 | H13: =Hoja14!R23/Hoja15!C15 -> 0 | I13: =Hoja14!V23/Hoja15!C15 -> 0 | J13: =Hoja14!X23/Hoja15!C15 -> 0
B14: Noviembre | C14: =Hoja14!P24/Hoja15!C16 -> 7.2776699 | D14: =Hoja14!P24/Hoja14!F24 -> 12.781149 | E14: =Hoja14!N24/Hoja15!C16 -> 80.076826 | F14: =Hoja14!N24/Hoja14!F24 -> 140.63208 | G14: =Hoja14!T24/Hoja15!C16 -> 0 | H14: =Hoja14!R24/Hoja15!C16 -> 0 | I14: =Hoja14!V24/Hoja15!C16 -> 0 | J14: =Hoja14!X24/Hoja15!C16 -> 0
B15: Diciembre | C15: =Hoja14!P25/Hoja15!C17 -> 7.2721803 | D15: =Hoja14!P25/Hoja14!F25 -> 12.756715 | E15: =Hoja14!N25/Hoja15!C17 -> 80.052958 | F15: =Hoja14!N25/Hoja14!F25 -> 140.42731 | G15: =Hoja14!T25/Hoja15!C17 -> 0 | H15: =Hoja14!R25/Hoja15!C17 -> 0 | I15: =Hoja14!V25/Hoja15!C17 -> 0 | J15: =Hoja14!X25/Hoja15!C17 -> 0
B17: Actualizado | C17: =SUM(C4:C15)*Hoja15!C17 -> 13952288 | D17: =SUM(D4:D15)*Hoja14!F25 -> 13921211 | E17: =SUM(E4:E15)*Hoja15!C17 -> 89358141 | F17: =SUM(F4:F15)*Hoja14!F25 -> 89197483 | G17: =SUM(G4:G15)*Hoja15!C17 -> 0 | H17: =SUM(H4:H15)*Hoja15!C17 -> 0 | I17: =SUM(I4:I15)*Hoja15!$C$17 -> 0 | J17: =SUM(J4:J15)*Hoja15!$C$17 -> 0
D19: Con honorarios
B20: Renta tributable | C20: =E17+H17-Hoja14!J272-Hoja14!J34-Hoja14!R5 -> 89358141 | D20: =E17+H17-Hoja14!J272-Hoja14!J34+I22-Hoja14!R5 -> 89358141 | H20: Gasto presunto | I20: =MIN(30%*I17,15*Hoja15!C17*12) -> 0
B21: Tramo | C21: =IFERROR((VLOOKUP(C20,Hoja15!$J$105:$M$112,3)),0) -> 0.304 | D21: =VLOOKUP(D20,Hoja15!$J$105:$M$112,3) -> 0.304
B22: Rebaja | C22: =IFERROR((VLOOKUP(C20,Hoja15!$J$105:$M$112,4)),0) -> 14854171 | D22: =VLOOKUP(D20,Hoja15!$J$105:$M$112,4) -> 14854171 | H22: Base honorarios | I22: =I17-I20 -> 0
B23: Impuesto | C23: =C20*C21-C22 -> 12310704 | D23: =D20*D21-D22 -> 12310704 | K23: =H17 -> 0
K24: =E17 -> 89358141
B25: Impuesto pagados | C25: =C17+G17 -> 13952288 | D25: =C17+G17+J17 -> 13952288 | K25: =K23+K24 -> 89358141 | L25: =K25+I22 -> 89358141
K26: =C23 -> 12310704
B27: Reliquidación | C27: =C23-C25 -> -1641584.1 | D27: =D23-D25 -> -1641584.1 | G27: Pago directo parcial | H27: =IF(Hoja14!M26>0,1,0) -> 0
G28: Pago directo final | H28: =IF(Hoja14!J34>0,1,0) -> 0 | K28: =C23-D23 -> 0
G29: 55 bis | H29: =IF(Hoja14!R5>0,1,0) -> 0 | K29: =J17 -> 0
H30: =SUM(H27:H29) -> 0 | K30: =K28+K29 -> 0 | L30: Boleta
G31: Reliquida variable | H31: =IF(H30>0,"Si", "No") -> No
B32: Si no hay reliquidación honorarios y 2514
B33: Si hay reliquidación normal | G33: Honorarios | H33: =IF(Hoja14!V26=0,0,1) -> 0 | K33: =K30+M7 -> 0 | L33: Reliquidación
G34: Doble renta | H34: =IF(M7=0,0,1) -> 0
A36: =IF(AND(E17=0,H17=0,I17>0,H30=0),1,0) -> 0 | B36: Solo honorarios | C36: =D27 -> -1641584.1
A37: 0 | B37: Honorarios y renta | C37: =D27 -> -1641584.1
A38: =IF(AND(I17>0,M7>0,H30=0),1,0) -> 0 | B38: honorario y 2514 | C38: =K33*-1 -> 0
A39: =IF(H30=0,(IF(OR(ABS(I17)>0,ABS(M7)>0),1,0)),0) -> 0 | B39: variable sin reliqui CON BOLETA | C39: =K33*-1 -> 0
A40: =IF(H30>0,1,0) -> 0 | B40: con reliquidación | C40: =D27 -> -1641584.1
A41: =IF(H30+H33+H34=0,1,0) -> 1 | B41: Sin nada | C41: 0
C44: =VLOOKUP(1,A36:C41,3,) -> 0

Sheet Hoja2
K4: Tipo de afiliado | N4: Pensionado cotizante | Q4: Intereses Crédito Hipotecario (55 bis) | T4: 0 | HJ4: =MIN(T4,Hoja15!J19) -> 0
HM5: Seguro cesantía | HP5: Si
X6: =IF(N4="No pensionado",0,1) -> 1 | BC6: =IF(N4="Pensionado no cotizante",0,1) -> 1
H10: APV opción A | AB10: APV B | AD10: APV A
B11: Mes | C11: UF | D11: (*)Total renta afecta ($) | E11: Pensión Bruta ($) | F11: APV máximo vía empleador ($) | G11: Vía Empleador | H11: Directo | I11: Vía Empleador | J11: Directo | K11: Renta Tributable ($) | M11: Impuesto mensual ($) | O11: Pensión Tributable ($) | Q11: Impuesto Pensión ($) | S11: Honorarios ($) | U11: Retención 10% ($) | W11: Tramo impuesto | X11: Rebaja | Y11: Obligatorio | Z11: Comisión AFP | AA11: Salud | AB11: Seguro Cesantía | AC11: Vía Empleador | AD11: Directo | AE11: Vía Empleador | AF11: Directo | AU11: Tramo impuesto | AV11: Rebaja | AW11: Obligatorio | AX11: Comisión Pensión | AY11: Salud pensión | AZ11: Seguro Cesantía | BA11: Comisión AFP | BG11: Tramo impuesto | BH11: Rebaja
AG12: =SUM(AG13:AG24) -> 0
B13: Enero | C13: =Hoja14!F14 -> 38384.41 | D13: =Hoja14!$G$26/12 -> 8750000 | F13: =IF(D13-Y13-Z13-AA13-AB13<(50*C13),D13-Y13-Z13-AA13-AB13,50*C13) -> 1919220.5 | G13: 0 | H13: 0 | I13: 0 | J13: 0 | K13: =D13-Y13-Z13-AA13-AB13-AC13 -> 8156859.5 | M13: =K13*W13-X13 -> 1282456.6 | O13: =AT13 -> 0 | Q13: =AT13*AU13-AV13 -> 0 | S13: =Hoja14!V14 -> 0 | U13: =S13*12.25% -> 0 | W13: =VLOOKUP(K13,Hoja15!$E$6:$H$13,3) -> 0.35 | X13: =VLOOKUP(K13,Hoja15!$E$6:$H$14,4) -> 1572444.3 | Y13: =IF($BC$6=0,0,IF(D13>81.6*C13,7.83*C13,10%*D13)) -> 300549.93 | Z13: =IF($BC$6=0,0,(IF(D13>81.6*C13,81.6*C13*1.44%,1.44%*D13))) -> 45103.217 | AA13: =IF(D13>81.6*C13,81.6*7%*C13,7%*D13) -> 219251.75 | AB13: =IF($BC$6=0,0,IF($HP$5="No",0,IF(D13>122.6*C13,0.6%*122.6*C13,0.6%*D13))) -> 28235.572 | AC13: =IF($AG$41=2,G13*C13,G13) -> 0 | AD13: =IF($AH$41=2,J13*C13,J13) -> 0 | AE13: =IF($AI$41=2,I13*C13,I13) -> 0 | AF13: =IF($AJ$41=2,J13*C13,J13) -> 0 | AG13: =IF(AC13>F13,1,0) -> 0 | AH13: =F13/C13 -> 50 | AI13: =AC13/C13 -> 0 | AJ13: =AD13/C13 -> 0 | AK13: =AE13/C13 -> 0 | AL13: =AF13/C13 -> 0 | AO13: =M13/C13 -> 33.410871 | AT13: =BC13-AY13-AW13 -> 0 | AU13: =VLOOKUP(AT13,Hoja15!$E$6:$H$13,3) -> 0 | AV13: =VLOOKUP(AT13,Hoja15!$E$6:$H$13,4) -> 0 | AX13: =1.25%*BC13 -> 0 | AY13: =IF(BC13>81.6*C13,81.6*7%*C13,7%*BC13) -> 0 | AZ13: =IF($HP$5="No",0,IF(AI13>122.6*AH13,0.6%*122.6*AH13,0.6%*AI13)) -> 0 | BA13: =IF(BC13>81.6*C13,81.6*C13*1.44%,1.44%*BC13) -> 0 | BC13: =IF($N$4="No pensionado",0,E13) -> 0 | BF13: =K13+O13 -> 8156859.5 | BG13: =VLOOKUP(BF13,Hoja15!$E$6:$H$13,3) -> 0.35 | BH13: =VLOOKUP(BF13,Hoja15!$E$6:$H$13,4) -> 1572444.3 | BI13: =BF13*BG13-BH13 -> 1282456.6 | BM13: =M13/Hoja15!C6 -> 19.019362 | BN13: =Q13/Hoja15!C6 -> 0
B14: Febrero | C14: =Hoja14!F15 -> 38647.94 | D14: =Hoja14!$G$26/12 -> 8750000 | F14: =IF(D14-Y14-Z14-AA14-AB14<(50*C14),D14-Y14-Z14-AA14-AB14,50*C14) -> 1932397 | G14: 0 | H14: 0 | I14: 0 | J14: 0 | K14: =D14-Y14-Z14-AA14-AB14-AC14 -> 8152787.3 | M14: =K14*W14-X14 -> 1284179.5 | O14: =AT14 -> 0 | Q14: =AT14*AU14-AV14 -> 0 | S14: =Hoja14!V15 -> 0 | U14: =S14*12.25% -> 0 | W14: =VLOOKUP(K14,Hoja15!$E$15:$H$22,3) -> 0.35 | X14: =VLOOKUP(K14,Hoja15!$E$15:$H$22,4) -> 1569296.1 | Y14: =IF($BC$6=0,0,IF(D14>81.6*C14,7.83*C14,10%*D14)) -> 302613.37 | Z14: =IF($BC$6=0,0,(IF(D14>81.6*C14,81.6*C14*1.44%,1.44%*D14))) -> 45412.875 | AA14: =IF(D14>81.6*C14,81.6*7%*C14,7%*D14) -> 220757.03 | AB14: =IF($BC$6=0,0,IF($HP$5="No",0,IF(D14>122.6*C14,0.6%*122.6*C14,0.6%*D14))) -> 28429.425 | AC14: =IF($AG$41=2,G14*C14,G14) -> 0 | AD14: =IF($AH$41=2,J14*C14,J14) -> 0 | AE14: =IF($AI$41=2,I14*C14,I14) -> 0 | AF14: =IF($AJ$41=2,J14*C14,J14) -> 0 | AG14: =IF(AC14>F14,1,0) -> 0 | AH14: =F14/C14 -> 50 | AI14: =AC14/C14 -> 0 | AJ14: =AD14/C14 -> 0 | AK14: =AE14/C14 -> 0 | AL14: =AF14/C14 -> 0 | AO14: =M14/C14 -> 33.227631 | AT14: =BC14-AY14-AW14 -> 0 | AU14: =VLOOKUP(AT14,Hoja15!$E$15:$H$22,3) -> 0 | AV14: =VLOOKUP(AT14,Hoja15!$E$15:$H$22,4) -> 0 | AX14: =1.25%*BC14 -> 0 | AY14: =IF(BC14>81.6*C14,81.6*7%*C14,7%*BC14) -> 0 | AZ14: =IF($HP$5="No",0,IF(AI14>122.6*AH14,0.6%*122.6*AH14,0.6%*AI14)) -> 0 | BA14: =IF(BC14>81.6*C14,81.6*C14*1.44%,1.44%*BC14) -> 0 | BC14: =IF($N$4="No pensionado",0,E14) -> 0 | BF14: =K14+O14 -> 8152787.3 | BG14: =VLOOKUP(BF14,Hoja15!$E$15:$H$22,3) -> 0.35 | BH14: =VLOOKUP(BF14,Hoja15!$E$15:$H$22,4) -> 1569296.1 | BI14: =BF14*BG14-BH14 -> 1284179.5 | BM14: =M14/Hoja15!C7 -> 19.08312 | BN14: =Q14/Hoja15!C7 -> 0
B15: Marzo | C15: =Hoja14!F16 -> 38894.11 | D15: =Hoja14!$G$26/12 -> 8750000 | F15: =IF(D15-Y15-Z15-AA15-AB15<(50*C15),D15-Y15-Z15-AA15-AB15,50*C15) -> 1944705.5 | G15: 0 | H15: 0 | I15: 0 | J15: 0 | K15: =D15-Y15-Z15-AA15-AB15-AC15 -> 8148983.3 | M15: =K15*W15-X15 -> 1266285.7 | O15: =AT15 -> 0 | Q15: =AT15*AU15-AV15 -> 0 | S15: =Hoja14!V16 -> 0 | U15: =S15*12.25% -> 0 | W15: =VLOOKUP(K15,Hoja15!$E$24:$H$31,3) -> 0.304 | X15: =VLOOKUP(K15,Hoja15!$E$24:$H$31,4) -> 1211005.2 | Y15: =IF($BC$6=0,0,IF(D15>81.6*C15,7.83*C15,10%*D15)) -> 304540.88 | Z15: =IF($BC$6=0,0,(IF(D15>81.6*C15,81.6*C15*1.44%,1.44%*D15))) -> 45702.135 | AA15: =IF(D15>81.6*C15,81.6*7%*C15,7%*D15) -> 222163.16 | AB15: =IF($BC$6=0,0,IF($HP$5="No",0,IF(D15>122.6*C15,0.6%*122.6*C15,0.6%*D15))) -> 28610.507 | AC15: =IF($AG$41=2,G15*C15,G15) -> 0 | AD15: =IF($AH$41=2,J15*C15,J15) -> 0 | AE15: =IF($AI$41=2,I15*C15,I15) -> 0 | AF15: =IF($AJ$41=2,J15*C15,J15) -> 0 | AG15: =IF(AC15>F15,1,0) -> 0 | AH15: =F15/C15 -> 50 | AI15: =AC15/C15 -> 0 | AJ15: =AD15/C15 -> 0 | AK15: =AE15/C15 -> 0 | AL15: =AF15/C15 -> 0 | AO15: =M15/C15 -> 32.557262 | AT15: =BC15-AY15-AW15 -> 0 | AU15: =VLOOKUP(AT15,Hoja15!$E$24:$H$31,3) -> 0 | AV15: =VLOOKUP(AT15,Hoja15!$E$24:$H$31,4) -> 0 | AX15: =1.25%*BC15 -> 0 | AY15: =IF(BC15>81.6*C15,81.6*7%*C15,7%*BC15) -> 0 | AZ15: =IF($HP$5="No",0,IF(AI15>122.6*AH15,0.6%*122.6*AH15,0.6%*AI15)) -> 0 | BA15: =IF(BC15>81.6*C15,81.6*C15*1.44%,1.44%*BC15) -> 0 | BC15: =IF($N$4="No pensionado",0,E15) -> 0 | BF15: =K15+O15 -> 8148983.3 | BG15: =VLOOKUP(BF15,Hoja15!$E$24:$H$31,3) -> 0.304 | BH15: =VLOOKUP(BF15,Hoja15!$E$24:$H$31,4) -> 1211005.2 | BI15: =BF15*BG15-BH15 -> 1266285.7 | BM15: =M15/Hoja15!C8 -> 18.612543 | BN15: =Q15/Hoja15!C8 -> 0
B16: Abril | C16: =Hoja14!F17 -> 39075.41 | D16: =Hoja14!$G$26/12 -> 8750000 | F16: =IF(D16-Y16-Z16-AA16-AB16<(50*C16),D16-Y16-Z16-AA16-AB16,50*C16) -> 1953770.5 | G16: 0 | H16: 0 | I16: 0 | J16: 0 | K16: =D16-Y16-Z16-AA16-AB16-AC16 -> 8146181.8 | M16: =K16*W16-X16 -> 1260592.5 | O16: =AT16 -> 0 | Q16: =AT16*AU16-AV16 -> 0 | S16: =Hoja14!V17 -> 0 | U16: =S16*12.25% -> 0 | W16: =VLOOKUP(K16,Hoja15!$E$33:$H$40,3) -> 0.304 | X16: =VLOOKUP(K16,Hoja15!$E$33:$H$40,4) -> 1215846.8 | Y16: =IF($BC$6=0,0,IF(D16>81.6*C16,7.83*C16,10%*D16)) -> 305960.46 | Z16: =IF($BC$6=0,0,(IF(D16>81.6*C16,81.6*C16*1.44%,1.44%*D16))) -> 45915.17 | AA16: =IF(D16>81.6*C16,81.6*7%*C16,7%*D16) -> 223198.74 | AB16: =IF($BC$6=0,0,IF($HP$5="No",0,IF(D16>122.6*C16,0.6%*122.6*C16,0.6%*D16))) -> 28743.872 | AC16: =IF($AG$41=2,G16*C16,G16) -> 0 | AD16: =IF($AH$41=2,J16*C16,J16) -> 0 | AE16: =IF($AI$41=2,I16*C16,I16) -> 0 | AF16: =IF($AJ$41=2,J16*C16,J16) -> 0 | AG16: =IF(AC16>F16,1,0) -> 0 | AH16: =F16/C16 -> 50 | AI16: =AC16/C16 -> 0 | AJ16: =AD16/C16 -> 0 | AK16: =AE16/C16 -> 0 | AL16: =AF16/C16 -> 0 | AO16: =M16/C16 -> 32.260505 | AT16: =BC16-AY16-AW16 -> 0 | AU16: =VLOOKUP(AT16,Hoja15!$E$33:$H$40,3) -> 0 | AV16: =VLOOKUP(AT16,Hoja15!$E$33:$H$40,4) -> 0 | AX16: =1.25%*BC16 -> 0 | AY16: =IF(BC16>81.6*C16,81.6*7%*C16,7%*BC16) -> 0 | AZ16: =IF($HP$5="No",0,IF(AI16>122.6*AH16,0.6%*122.6*AH16,0.6%*AI16)) -> 0 | BA16: =IF(BC16>81.6*C16,81.6*C16*1.44%,1.44%*BC16) -> 0 | BC16: =IF($N$4="No pensionado",0,E16) -> 0 | BF16: =K16+O16 -> 8146181.8 | BG16: =VLOOKUP(BF16,Hoja15!$E$33:$H$40,3) -> 0.304 | BH16: =VLOOKUP(BF16,Hoja15!$E$33:$H$40,4) -> 1215846.8 | BI16: =BF16*BG16-BH16 -> 1260592.5 | BM16: =M16/Hoja15!C9 -> 18.455076 | BN16: =Q16/Hoja15!C9 -> 0
B17: Mayo | C17: =Hoja14!F18 -> 39189.45 | D17: =Hoja14!$G$26/12 -> 8750000 | F17: =IF(D17-Y17-Z17-AA17-AB17<(50*C17),D17-Y17-Z17-AA17-AB17,50*C17) -> 1959472.5 | G17: 0 | H17: 0 | I17: 0 | J17: 0 | K17: =D17-Y17-Z17-AA17-AB17-AC17 -> 8144419.5 | M17: =K17*W17-X17 -> 1253969.1 | O17: =AT17 -> 0 | Q17: =AT17*AU17-AV17 -> 0 | S17: =Hoja14!V18 -> 0 | U17: =S17*12.25% -> 0 | W17: =VLOOKUP(K17,Hoja15!$E$42:$H$49,3) -> 0.304 | X17: =VLOOKUP(K17,Hoja15!$E$42:$H$49,4) -> 1221934.4 | Y17: =IF($BC$6=0,0,IF(D17>81.6*C17,7.83*C17,10%*D17)) -> 306853.39 | Z17: =IF($BC$6=0,0,(IF(D17>81.6*C17,81.6*C17*1.44%,1.44%*D17))) -> 46049.171 | AA17: =IF(D17>81.6*C17,81.6*7%*C17,7%*D17) -> 223850.14 | AB17: =IF($BC$6=0,0,IF($HP$5="No",0,IF(D17>122.6*C17,0.6%*122.6*C17,0.6%*D17))) -> 28827.759 | AC17: =IF($AG$41=2,G17*C17,G17) -> 0 | AD17: =IF($AH$41=2,J17*C17,J17) -> 0 | AE17: =IF($AI$41=2,I17*C17,I17) -> 0 | AF17: =IF($AJ$41=2,J17*C17,J17) -> 0 | AG17: =IF(AC17>F17,1,0) -> 0 | AH17: =F17/C17 -> 50 | AI17: =AC17/C17 -> 0 | AJ17: =AD17/C17 -> 0 | AK17: =AE17/C17 -> 0 | AL17: =AF17/C17 -> 0 | AO17: =M17/C17 -> 31.99762 | AT17: =BC17-AY17-AW17 -> 0 | AU17: =VLOOKUP(AT17,Hoja15!$E$42:$H$49,3) -> 0 | AV17: =VLOOKUP(AT17,Hoja15!$E$42:$H$49,4) -> 0 | AX17: =1.25%*BC17 -> 0 | AY17: =IF(BC17>81.6*C17,81.6*7%*C17,7%*BC17) -> 0 | AZ17: =IF($HP$5="No",0,IF(AI17>122.6*AH17,0.6%*122.6*AH17,0.6%*AI17)) -> 0 | BA17: =IF(BC17>81.6*C17,81.6*C17*1.44%,1.44%*BC17) -> 0 | BC17: =IF($N$4="No pensionado",0,E17) -> 0 | BF17: =K17+O17 -> 8144419.5 | BG17: =VLOOKUP(BF17,Hoja15!$E$42:$H$49,3) -> 0.304 | BH17: =VLOOKUP(BF17,Hoja15!$E$42:$H$49,4) -> 1221934.4 | BI17: =BF17*BG17-BH17 -> 1253969.1 | BM17: =M17/Hoja15!C10 -> 18.266652 | BN17: =Q17/Hoja15!C10 -> 0
B18: Junio | C18: =Hoja14!F19 -> 39267.07 | D18: =Hoja14!$G$26/12 -> 8750000 | F18: =IF(D18-Y18-Z18-AA18-AB18<(50*C18),D18-Y18-Z18-AA18-AB18,50*C18) -> 1963353.5 | G18: 0 | H18: 0 | I18: 0 | J18: 0 | K18: =D18-Y18-Z18-AA18-AB18-AC18 -> 8143220.1 | M18: =K18*W18-X18 -> 1251165.9 | O18: =AT18 -> 0 | Q18: =AT18*AU18-AV18 -> 0 | S18: =Hoja14!V19 -> 0 | U18: =S18*12.25% -> 0 | W18: =VLOOKUP(K18,Hoja15!$E$51:$H$58,3) -> 0.304 | X18: =VLOOKUP(K18,Hoja15!$E$51:$H$58,4) -> 1224373 | Y18: =IF($BC$6=0,0,IF(D18>81.6*C18,7.83*C18,10%*D18)) -> 307461.16 | Z18: =IF($BC$6=0,0,(IF(D18>81.6*C18,81.6*C18*1.44%,1.44%*D18))) -> 46140.378 | AA18: =IF(D18>81.6*C18,81.6*7%*C18,7%*D18) -> 224293.5 | AB18: =IF($BC$6=0,0,IF($HP$5="No",0,IF(D18>122.6*C18,0.6%*122.6*C18,0.6%*D18))) -> 28884.857 | AC18: =IF($AG$41=2,G18*C18,G18) -> 0 | AD18: =IF($AH$41=2,J18*C18,J18) -> 0 | AE18: =IF($AI$41=2,I18*C18,I18) -> 0 | AF18: =IF($AJ$41=2,J18*C18,J18) -> 0 | AG18: =IF(AC18>F18,1,0) -> 0 | AH18: =F18/C18 -> 50 | AI18: =AC18/C18 -> 0 | AJ18: =AD18/C18 -> 0 | AK18: =AE18/C18 -> 0 | AL18: =AF18/C18 -> 0 | AO18: =M18/C18 -> 31.862981 | AT18: =BC18-AY18-AW18 -> 0 | AU18: =VLOOKUP(AT18,Hoja15!$E$51:$H$58,3) -> 0 | AV18: =VLOOKUP(AT18,Hoja15!$E$51:$H$58,4) -> 0 | AX18: =1.25%*BC18 -> 0 | AY18: =IF(BC18>81.6*C18,81.6*7%*C18,7%*BC18) -> 0 | AZ18: =IF($HP$5="No",0,IF(AI18>122.6*AH18,0.6%*122.6*AH18,0.6%*AI18)) -> 0 | BA18: =IF(BC18>81.6*C18,81.6*C18*1.44%,1.44%*BC18) -> 0 | BC18: =IF($N$4="No pensionado",0,E18) -> 0 | BF18: =K18+O18 -> 8143220.1 | BG18: =VLOOKUP(BF18,Hoja15!$E$51:$H$58,3) -> 0.304 | BH18: =VLOOKUP(BF18,Hoja15!$E$51:$H$58,4) -> 1224373 | BI18: =BF18*BG18-BH18 -> 1251165.9 | BM18: =M18/Hoja15!C11 -> 18.189517 | BN18: =Q18/Hoja15!C11 -> 0
B19: Julio | C19: =Hoja14!F20 -> 39179.01 | D19: =Hoja14!$G$26/12 -> 8750000 | F19: =IF(D19-Y19-Z19-AA19-AB19<(50*C19),D19-Y19-Z19-AA19-AB19,50*C19) -> 1958950.5 | G19: 0 | H19: 0 | I19: 0 | J19: 0 | K19: =D19-Y19-Z19-AA19-AB19-AC19 -> 8144580.9 | M19: =K19*W19-X19 -> 1249123.2 | O19: =AT19 -> 0 | Q19: =AT19*AU19-AV19 -> 0 | S19: =Hoja14!V20 -> 0 | U19: =S19*12.25% -> 0 | W19: =VLOOKUP(K19,Hoja15!$E$60:$H$67,3) -> 0.304 | X19: =VLOOKUP(K19,Hoja15!$E$60:$H$67,4) -> 1226829.4 | Y19: =IF($BC$6=0,0,IF(D19>81.6*C19,7.83*C19,10%*D19)) -> 306771.65 | Z19: =IF($BC$6=0,0,(IF(D19>81.6*C19,81.6*C19*1.44%,1.44%*D19))) -> 46036.904 | AA19: =IF(D19>81.6*C19,81.6*7%*C19,7%*D19) -> 223790.51 | AB19: =IF($BC$6=0,0,IF($HP$5="No",0,IF(D19>122.6*C19,0.6%*122.6*C19,0.6%*D19))) -> 28820.08 | AC19: =IF($AG$41=2,G19*C19,G19) -> 0 | AD19: =IF($AH$41=2,J19*C19,J19) -> 0 | AE19: =IF($AI$41=2,I19*C19,I19) -> 0 | AF19: =IF($AJ$41=2,J19*C19,J19) -> 0 | AG19: =IF(AC19>F19,1,0) -> 0 | AH19: =F19/C19 -> 50 | AI19: =AC19/C19 -> 0 | AJ19: =AD19/C19 -> 0 | AK19: =AE19/C19 -> 0 | AL19: =AF19/C19 -> 0 | AO19: =M19/C19 -> 31.882459 | AT19: =BC19-AY19-AW19 -> 0 | AU19: =VLOOKUP(AT19,Hoja15!$E$60:$H$67,3) -> 0 | AV19: =VLOOKUP(AT19,Hoja15!$E$60:$H$67,4) -> 0 | AX19: =1.25%*BC19 -> 0 | AY19: =IF(BC19>81.6*C19,81.6*7%*C19,7%*BC19) -> 0 | AZ19: =IF($HP$5="No",0,IF(AI19>122.6*AH19,0.6%*122.6*AH19,0.6%*AI19)) -> 0 | BA19: =IF(BC19>81.6*C19,81.6*C19*1.44%,1.44%*BC19) -> 0 | BC19: =IF($N$4="No pensionado",0,E19) -> 0 | BF19: =K19+O19 -> 8144580.9 | BG19: =VLOOKUP(BF19,Hoja15!$E$60:$H$67,3) -> 0.304 | BH19: =VLOOKUP(BF19,Hoja15!$E$60:$H$67,4) -> 1226829.4 | BI19: =BF19*BG19-BH19 -> 1249123.2 | BM19: =M19/Hoja15!C12 -> 18.123459 | BN19: =Q19/Hoja15!C12 -> 0
B20: Agosto | C20: =Hoja14!F21 -> 39383.07 | D20: =Hoja14!$G$26/12 -> 8750000 | F20: =IF(D20-Y20-Z20-AA20-AB20<(50*C20),D20-Y20-Z20-AA20-AB20,50*C20) -> 1969153.5 | G20: 0 | H20: 0 | I20: 0 | J20: 0 | K20: =D20-Y20-Z20-AA20-AB20-AC20 -> 8141427.6 | M20: =K20*W20-X20 -> 1253077.4 | O20: =AT20 -> 0 | Q20: =AT20*AU20-AV20 -> 0 | S20: =Hoja14!V21 -> 0 | U20: =S20*12.25% -> 0 | W20: =VLOOKUP(K20,Hoja15!$E$69:$H$76,3) -> 0.304 | X20: =VLOOKUP(K20,Hoja15!$E$69:$H$76,4) -> 1221916.6 | Y20: =IF($BC$6=0,0,IF(D20>81.6*C20,7.83*C20,10%*D20)) -> 308369.44 | Z20: =IF($BC$6=0,0,(IF(D20>81.6*C20,81.6*C20*1.44%,1.44%*D20))) -> 46276.683 | AA20: =IF(D20>81.6*C20,81.6*7%*C20,7%*D20) -> 224956.1 | AB20: =IF($BC$6=0,0,IF($HP$5="No",0,IF(D20>122.6*C20,0.6%*122.6*C20,0.6%*D20))) -> 28970.186 | AC20: =IF($AG$41=2,G20*C20,G20) -> 0 | AD20: =IF($AH$41=2,J20*C20,J20) -> 0 | AE20: =IF($AI$41=2,I20*C20,I20) -> 0 | AF20: =IF($AJ$41=2,J20*C20,J20) -> 0 | AG20: =IF(AC20>F20,1,0) -> 0 | AH20: =F20/C20 -> 50 | AI20: =AC20/C20 -> 0 | AJ20: =AD20/C20 -> 0 | AK20: =AE20/C20 -> 0 | AL20: =AF20/C20 -> 0 | AO20: =M20/C20 -> 31.817667 | AT20: =BC20-AY20-AW20 -> 0 | AU20: =VLOOKUP(AT20,Hoja15!$E$69:$H$76,3) -> 0 | AV20: =VLOOKUP(AT20,Hoja15!$E$69:$H$76,4) -> 0 | AX20: =1.25%*BC20 -> 0 | AY20: =IF(BC20>81.6*C20,81.6*7%*C20,7%*BC20) -> 0 | AZ20: =IF($HP$5="No",0,IF(AI20>122.6*AH20,0.6%*122.6*AH20,0.6%*AI20)) -> 0 | BA20: =IF(BC20>81.6*C20,81.6*C20*1.44%,1.44%*BC20) -> 0 | BC20: =IF($N$4="No pensionado",0,E20) -> 0 | BF20: =K20+O20 -> 8141427.6 | BG20: =VLOOKUP(BF20,Hoja15!$E$69:$H$76,3) -> 0.304 | BH20: =VLOOKUP(BF20,Hoja15!$E$69:$H$76,4) -> 1221916.6 | BI20: =BF20*BG20-BH20 -> 1253077.4 | BM20: =M20/Hoja15!C13 -> 18.253928 | BN20: =Q20/Hoja15!C13 -> 0
B21: Septiembre | C21: =Hoja14!F22 -> 39485.65 | D21: =Hoja14!$G$26/12 -> 8750000 | F21: =IF(D21-Y21-Z21-AA21-AB21<(50*C21),D21-Y21-Z21-AA21-AB21,50*C21) -> 1974282.5 | G21: 0 | H21: 0 | I21: 0 | J21: 0 | K21: =D21-Y21-Z21-AA21-AB21-AC21 -> 8139842.5 | M21: =K21*W21-X21 -> 1241595.1 | O21: =AT21 -> 0 | Q21: =AT21*AU21-AV21 -> 0 | S21: =Hoja14!V22 -> 0 | U21: =S21*12.25% -> 0 | W21: =VLOOKUP(K21,Hoja15!$E$78:$H$85,3) -> 0.304 | X21: =VLOOKUP(K21,Hoja15!$E$78:$H$85,4) -> 1232917 | Y21: =IF($BC$6=0,0,IF(D21>81.6*C21,7.83*C21,10%*D21)) -> 309172.64 | Z21: =IF($BC$6=0,0,(IF(D21>81.6*C21,81.6*C21*1.44%,1.44%*D21))) -> 46397.218 | AA21: =IF(D21>81.6*C21,81.6*7%*C21,7%*D21) -> 225542.03 | AB21: =IF($BC$6=0,0,IF($HP$5="No",0,IF(D21>122.6*C21,0.6%*122.6*C21,0.6%*D21))) -> 29045.644 | AC21: =IF($AG$41=2,G21*C21,G21) -> 0 | AD21: =IF($AH$41=2,J21*C21,J21) -> 0 | AE21: =IF($AI$41=2,I21*C21,I21) -> 0 | AF21: =IF($AJ$41=2,J21*C21,J21) -> 0 | AG21: =IF(AC21>F21,1,0) -> 0 | AH21: =F21/C21 -> 50 | AI21: =AC21/C21 -> 0 | AJ21: =AD21/C21 -> 0 | AK21: =AE21/C21 -> 0 | AL21: =AF21/C21 -> 0 | AO21: =M21/C21 -> 31.444211 | AT21: =BC21-AY21-AW21 -> 0 | AU21: =VLOOKUP(AT21,Hoja15!$E$78:$H$85,3) -> 0 | AV21: =VLOOKUP(AT21,Hoja15!$E$78:$H$85,4) -> 0 | AX21: =1.25%*BC21 -> 0 | AY21: =IF(BC21>81.6*C21,81.6*7%*C21,7%*BC21) -> 0 | AZ21: =IF($HP$5="No",0,IF(AI21>122.6*AH21,0.6%*122.6*AH21,0.6%*AI21)) -> 0 | BA21: =IF(BC21>81.6*C21,81.6*C21*1.44%,1.44%*BC21) -> 0 | BC21: =IF($N$4="No pensionado",0,E21) -> 0 | BF21: =K21+O21 -> 8139842.5 | BG21: =VLOOKUP(BF21,Hoja15!$E$78:$H$85,3) -> 0.304 | BH21: =VLOOKUP(BF21,Hoja15!$E$78:$H$85,4) -> 1232917 | BI21: =BF21*BG21-BH21 -> 1241595.1 | BM21: =M21/Hoja15!C14 -> 17.925289 | BN21: =Q21/Hoja15!C14 -> 0
B22: Octubre | C22: =Hoja14!F23 -> 39485.65 | D22: =Hoja14!$G$26/12 -> 8750000 | F22: =IF(D22-Y22-Z22-AA22-AB22<(50*C22),D22-Y22-Z22-AA22-AB22,50*C22) -> 1974282.5 | G22: 0 | H22: 0 | J22: 0 | K22: =D22-Y22-Z22-AA22-AB22-AC22 -> 8139842.5 | M22: =K22*W22-X22 -> 1241595.1 | O22: =AT22 -> 0 | Q22: =AT22*AU22-AV22 -> 0 | S22: =Hoja14!V23 -> 0 | U22: =S22*12.25% -> 0 | W22: =VLOOKUP(K22,Hoja15!$E$87:$H$94,3) -> 0.304 | X22: =VLOOKUP(K22,Hoja15!$E$87:$H$94,4) -> 1232917 | Y22: =IF($BC$6=0,0,IF(D22>81.6*C22,7.83*C22,10%*D22)) -> 309172.64 | Z22: =IF($BC$6=0,0,(IF(D22>81.6*C22,81.6*C22*1.44%,1.44%*D22))) -> 46397.218 | AA22: =IF(D22>81.6*C22,81.6*7%*C22,7%*D22) -> 225542.03 | AB22: =IF($BC$6=0,0,IF($HP$5="No",0,IF(D22>122.6*C22,0.6%*122.6*C22,0.6%*D22))) -> 29045.644 | AC22: =IF($AG$41=2,G22*C22,G22) -> 0 | AD22: =IF($AH$41=2,J22*C22,J22) -> 0 | AE22: =IF($AI$41=2,I22*C22,I22) -> 0 | AF22: =IF($AJ$41=2,J22*C22,J22) -> 0 | AG22: =IF(AC22>F22,1,0) -> 0 | AH22: =F22/C22 -> 50 | AI22: =AC22/C22 -> 0 | AJ22: =AD22/C22 -> 0 | AK22: =AE22/C22 -> 0 | AL22: =AF22/C22 -> 0 | AO22: =M22/C22 -> 31.444211 | AT22: =BC22-AY22-AW22 -> 0 | AU22: =VLOOKUP(AT22,Hoja15!$E$87:$H$94,3) -> 0 | AV22: =VLOOKUP(AT22,Hoja15!$E$87:$H$94,4) -> 0 | AX22: =1.25%*BC22 -> 0 | AY22: =IF(BC22>81.6*C22,81.6*7%*C22,7%*BC22) -> 0 | AZ22: =IF($HP$5="No",0,IF(AI22>122.6*AH22,0.6%*122.6*AH22,0.6%*AI22)) -> 0 | BA22: =IF(BC22>81.6*C22,81.6*C22*1.44%,1.44%*BC22) -> 0 | BC22: =IF($N$4="No pensionado",0,E22) -> 0 | BF22: =K22+O22 -> 8139842.5 | BG22: =VLOOKUP(BF22,Hoja15!$E$87:$H$94,3) -> 0.304 | BH22: =VLOOKUP(BF22,Hoja15!$E$87:$H$94,4) -> 1232917 | BI22: =BF22*BG22-BH22 -> 1241595.1 | BM22: =M22/Hoja15!C15 -> 17.925289 | BN22: =Q22/Hoja15!C15 -> 0
B23: Noviembre | C23: =Hoja14!F24 -> 39597.67 | D23: =Hoja14!$G$26/12 -> 8750000 | F23: =IF(D23-Y23-Z23-AA23-AB23<(50*C23),D23-Y23-Z23-AA23-AB23,50*C23) -> 1979883.5 | G23: 0 | H23: 0 | I23: 0 | J23: 0 | K23: =D23-Y23-Z23-AA23-AB23-AC23 -> 8138111.5 | M23: =K23*W23-X23 -> 1236138.3 | O23: =AT23 -> 0 | Q23: =AT23*AU23-AV23 -> 0 | S23: =Hoja14!V24 -> 0 | U23: =S23*12.25% -> 0 | W23: =VLOOKUP(K23,Hoja15!$E$96:$H$103,3) -> 0.304 | X23: =VLOOKUP(K23,Hoja15!$E$96:$H$103,4) -> 1237847.6 | Y23: =IF($BC$6=0,0,IF(D23>81.6*C23,7.83*C23,10%*D23)) -> 310049.76 | Z23: =IF($BC$6=0,0,(IF(D23>81.6*C23,81.6*C23*1.44%,1.44%*D23))) -> 46528.846 | AA23: =IF(D23>81.6*C23,81.6*7%*C23,7%*D23) -> 226181.89 | AB23: =IF($BC$6=0,0,IF($HP$5="No",0,IF(D23>122.6*C23,0.6%*122.6*C23,0.6%*D23))) -> 29128.046 | AC23: =IF($AG$41=2,G23*C23,G23) -> 0 | AD23: =IF($AH$41=2,J23*C23,J23) -> 0 | AE23: =IF($AI$41=2,I23*C23,I23) -> 0 | AF23: =IF($AJ$41=2,J23*C23,J23) -> 0 | AG23: =IF(AC23>F23,1,0) -> 0 | AH23: =F23/C23 -> 50 | AI23: =AC23/C23 -> 0 | AJ23: =AD23/C23 -> 0 | AK23: =AE23/C23 -> 0 | AL23: =AF23/C23 -> 0 | AO23: =M23/C23 -> 31.21745 | AT23: =BC23-AY23-AW23 -> 0 | AU23: =VLOOKUP(AT23,Hoja15!$E$96:$H$103,3) -> 0 | AV23: =VLOOKUP(AT23,Hoja15!$E$96:$H$103,4) -> 0 | AX23: =1.25%*BC23 -> 0 | AY23: =IF(BC23>81.6*C23,81.6*7%*C23,7%*BC23) -> 0 | AZ23: =IF($HP$5="No",0,IF(AI23>122.6*AH23,0.6%*122.6*AH23,0.6%*AI23)) -> 0 | BA23: =IF(BC23>81.6*C23,81.6*C23*1.44%,1.44%*BC23) -> 0 | BC23: =IF($N$4="No pensionado",0,E23) -> 0 | BF23: =K23+O23 -> 8138111.5 | BG23: =VLOOKUP(BF23,Hoja15!$E$96:$H$103,3) -> 0.304 | BH23: =VLOOKUP(BF23,Hoja15!$E$96:$H$103,4) -> 1237847.6 | BI23: =BF23*BG23-BH23 -> 1236138.3 | BM23: =M23/Hoja15!C16 -> 17.77542 | BN23: =Q23/Hoja15!C16 -> 0
B24: Diciembre | C24: =Hoja14!F25 -> 39643.59 | D24: =Hoja14!$G$26/12 -> 8750000 | F24: =IF(D24-Y24-Z24-AA24-AB24<(50*C24),D24-Y24-Z24-AA24-AB24,50*C24) -> 1982179.5 | G24: 0 | H24: 0 | I24: 0 | J24: 0 | K24: =D24-Y24-Z24-AA24-AB24-AC24 -> 8137401.9 | M24: =K24*W24-X24 -> 1235922.6 | O24: =AT24 -> 0 | Q24: =AT24*AU24-AV24 -> 0 | S24: =Hoja14!V25 -> 0 | U24: =S24*12.25% -> 0 | W24: =VLOOKUP(K24,Hoja15!$E$105:$H$112,3) -> 0.304 | X24: =VLOOKUP(K24,Hoja15!$E$105:$H$112,4) -> 1237847.6 | Y24: =IF($BC$6=0,0,IF(D24>81.6*C24,7.83*C24,10%*D24)) -> 310409.31 | Z24: =IF($BC$6=0,0,(IF(D24>81.6*C24,81.6*C24*1.44%,1.44%*D24))) -> 46582.804 | AA24: =IF(D24>81.6*C24,81.6*7%*C24,7%*D24) -> 226444.19 | AB24: =IF($BC$6=0,0,IF($HP$5="No",0,IF(D24>122.6*C24,0.6%*122.6*C24,0.6%*D24))) -> 29161.825 | AC24: =IF($AG$41=2,G24*C24,G24) -> 0 | AD24: =IF($AH$41=2,J24*C24,J24) -> 0 | AE24: =IF($AI$41=2,I24*C24,I24) -> 0 | AF24: =IF($AJ$41=2,J24*C24,J24) -> 0 | AG24: =IF(AC24>F24,1,0) -> 0 | AH24: =F24/C24 -> 50 | AI24: =AC24/C24 -> 0 | AJ24: =AD24/C24 -> 0 | AK24: =AE24/C24 -> 0 | AL24: =AF24/C24 -> 0 | AO24: =M24/C24 -> 31.175849 | AT24: =BC24-AY24-AW24 -> 0 | AU24: =VLOOKUP(AT24,Hoja15!$E$105:$H$112,3) -> 0 | AV24: =VLOOKUP(AT24,Hoja15!$E$105:$H$112,4) -> 0 | AX24: =1.25%*BC24 -> 0 | AY24: =IF(BC24>81.6*C24,81.6*7%*C24,7%*BC24) -> 0 | AZ24: =IF($HP$5="No",0,IF(AI24>122.6*AH24,0.6%*122.6*AH24,0.6%*AI24)) -> 0 | BA24: =IF(BC24>81.6*C24,81.6*C24*1.44%,1.44%*BC24) -> 0 | BC24: =IF($N$4="No pensionado",0,E24) -> 0 | BF24: =K24+O24 -> 8137401.9 | BG24: =VLOOKUP(BF24,Hoja15!$E$105:$H$112,3) -> 0.304 | BH24: =VLOOKUP(BF24,Hoja15!$E$105:$H$112,4) -> 1237847.6 | BI24: =BF24*BG24-BH24 -> 1235922.6 | BM24: =M24/Hoja15!C17 -> 17.772318 | BN24: =Q24/Hoja15!C17 -> 0
B25: Total | D25: =SUM(D13:D24) -> 105000000 | E25: =SUM(E13:E24) -> 0 | F25: =SUM(F13:F24) -> 23511652 | G25: =AC25 -> 0 | H25: =AD25 -> 0 | I25: =AE25 -> 0 | J25: =(IF(AH41=1,SUM(J13:J24),AF25))+S61 -> 0 | K25: =SUM(K13:K24) -> 97733658 | M25: =SUM(M13:M24) -> 15056101 | O25: =SUM(O13:O24) -> 0 | Q25: =SUM(Q13:Q24) -> 0 | S25: =SUM(S13:S24) -> 0 | U25: =SUM(U13:U24) -> 0 | Y25: =SUM(Y13:Y24) -> 3681924.6 | Z25: =SUM(Z13:Z24) -> 552542.62 | AA25: =SUM(AA13:AA24) -> 2685971.1 | AB25: =SUM(AB13:AB24) -> 345903.42 | AC25: =SUM(AC13:AC24) -> 0 | AD25: =SUM(AD13:AD24) -> 0 | AE25: =IF(AH41=2,SUMPRODUCT(C13:C24,AE13:AE24),SUM(AE13:AE24)) -> 0 | AF25: =SUMPRODUCT(AF13:AF24,C13:C24) -> 0 | AG25: =IF(AC25>F25,1,0) -> 0 | AH25: =SUM(AH13:AH24) -> 600 | AI25: =SUM(AI13:AI24) -> 0 | AJ25: =SUM(AJ13:AJ24) -> 0 | AK25: =SUM(AK13:AK24) -> 0 | AL25: =SUM(AL13:AL24) -> 0 | AO25: =SUM(AO13:AO24) -> 384.29872 | AP25: =AO25*Hoja14!F25 -> 15234981 | AT25: =SUM(AT13:AT24) -> 0 | AW25: =SUM(AW13:AW24) -> 0 | AX25: =SUM(AX13:AX24) -> 0 | AY25: =SUM(AY13:AY24) -> 0 | AZ25: =SUM(AZ13:AZ24) -> 0 | BA25: =SUM(BA13:BA24) -> 0 | BI25: =SUM(BI13:BI24) -> 15056101 | BM25: =SUM(BM13:BM24)*Hoja15!C17 -> 15257652 | BN25: =SUM(BN13:BN24)*Hoja15!C17 -> 0 | BO25: =BM25+BN25 -> 15257652
B29: Rentas Artículo 42 N° 1 (sueldos) | G29: =Hoja1!I17 -> 99029727 | J29: (actualizado) | S29: =STDEVA(D13:D24) -> 0
B30: Rentas Artículo 42 N° 1 (pensiones) | G30: =O25 -> 0 | W30: 20939.49 | X30: 20865.85 | Y30: 20924.09 | Z30: 21000.55 | AA30: 21032.2 | AB30: 21115.8 | AC30: 21204.99 | AD30: 21227.57
B31: Rentas Artículo 42 N° 2 (honorarios) | G31: =Y40 -> 0
B33: Pagos Directos efectuados en el año | G33: =J25 -> 0 | L33: IMPUESTO GLOBAL COMPLEMENTARIO | U33: =IF(AB42>0,G39-G40,0) -> 0
B34: APV B máx. para utilizar 100% del beneficio tributario | G34: =(AH25-(AI25+AJ25))*C24 -> 23786154 | L34: Diferencia de Reliquidación Formulario 2514 | U34: =BI25-M25-Q25 -> 0 | W34: No pensionado
B35: Pago Directo APV opción B final | G35: 0 | L35: Impuesto único por retiros de Ahorro Previsional Voluntario | U35: =AC55 -> 0 | W35: Pensionado no cotizante | Y35: =IF(T4>8*Hoja15!B23,8*Hoja15!B23,Hoja14!P5) -> 0 | AW35: =M25 -> 15056101
B36: Intereses Crédito Hipotecario (Art. 55 bis) | G36: =IF(J36=" ",0,J36*HJ4) -> 0 | J36: =IF(T4=0," ",Hoja15!N27) | L36: Retención de honorarios | U36: =U25 -> 0 | W36: Pensionado cotizante | AW36: =U25 -> 0
AW37: =K25 -> 97733658 | AX37: =AW37+AW38 -> 97733658
B38: BASE IMPONIBLE GLOBAL COMPLEMENTARIO | G38: =G29+G31-G33-G35-G36 -> 99029727 | L38: =CONCATENATE("RESULTADO RELIQUIDACION DE IMPUESTO : ",W63) -> RESULTADO RELIQUIDACION DE IMPUESTO : (A favor) | U38: =IF((U33+U34+U35-U36-U37)>0,(U33+U34+U35-U36-U37),IF(AB42=0,0,U33+U34+U35-U36-U37)) -> 0 | Y38: =Hoja15!C17*15*12 -> 12517560 | AW38: =S25 -> 0
B39: Impuesto global complementario según tabla. (Art. 52) | G39: =(G38*VLOOKUP(G38,Hoja15!$J$105:$M$112,3))-(VLOOKUP(G38,Hoja15!$J$105:$M$112,4)) -> 15250866 | Y39: =IF(30%*S25>Y38,Y38,30%*S25) -> 0 | AA39: Directos anuales | AB39: =IF(J25>0,1,0) -> 0 | AG39: pesos ($) | AH39: Si | AW39: =IF((I109+I110)=0,0,IF(I110=0,0,J83-J93)) -> 0
B40: Crédito por impuesto único segunda categoría. (Art. 56 N° 2) | G40: =Hoja1!J17 -> 15257652 | J40: (actualizado) | Y40: =S25-Y39 -> 0 | AA40: Directo final | AB40: =IF(G35>0,1,0) -> 0 | AG40: UF | AH40: No
AA41: 55 bis | AB41: =IF(G36>0,1,0) -> 0 | AG41: 2 | AH41: 2 | AI41: 1 | AJ41: 1 | AW41: =IF((J85+J87)>0,AW39,IF(S25>0,Hoja15!R109,Hoja14!AZ40)) -> 0
X42: =K25+O25 -> 97733658 | AB42: =SUM(AB39:AB41) -> 0
U43: =U33+U34-U35-U36-U37 -> 0 | X43: =Hoja14!AA43*Hoja15!L110-Hoja15!M110 -> 11898728
U46: =IF(AB42=0,0,U33) -> 0
B47: Renta | E47: =IF(D25>0,1,0) -> 1
B48: Pensión | E48: =IF(AT25>0,1,0) -> 0 | U48: =U33+U34+U35-U36-U37 -> 0
B49: Honorarios | E49: =IF(S25>0,1,0) -> 0
B50: Pago directo parcial | E50: =IF(G33>0,1,0) -> 0
B51: Pago directo final | E51: =IF(G35>0,1,0) -> 0
B52: 55 bis | E52: =IF(G36>0,1,0) -> 0
B53: Retiro APV | E53: =IF(T7>0,1,0) -> 0 | X53: Retiro APV opción B
X54: Retiro APV opción B | AC54: =T7 -> 0
X55: Impuesto al retiro de APV opción B (%) | AC55: =IF(AC54=0,0,AC54*AC56) -> 0
X56: Impuesto al retiro de APV opción B ($) | AC56: =IF(AC54=0,0,IF(N4="No pensionado",Hoja15!R118,Hoja15!R117)) -> 0
X57: Retención 15% | AC57: =IF(AC54=0,0,T7*15%) -> 0
X58: Diferencia a reliquidar | AC58: =IF(AC54=0,0,AC57-AC55) -> 0
G59: =Hoja15!B39*Hoja15!C17 -> 13952288
S60: 1e-06 | X60: =M25+Q25 -> 15056101
S61: =IF(S25>0,S60,0) -> 0
W63: =IF(U38>0, "(En contra)","(A favor)") -> (A favor)
W66: 20939.49
B67: MATERIAL DE USO INTERNO | W67: 20865.85
W68: 20924.09
W69: 21000.55
W70: 21032.2
W71: 21115.8
W72: 21204.99
W73: 21227.57
B78: Nueva Base tributable anual | J78: =G29-#REF!-G33-G35 -> #REF!
B79: Impuesto Calculado sobre nueva Base | J79: =Hoja15!R78 -> 0
B80: Reliquidación Anual de Impuesto | J80: =G31-J79+T2 -> 0
B82: Base tributable anual | J82: =K25+O25+S25 -> 97733658
B83: Impuestos Pagados y retenciones enteradas en el año | J83: =M25+U25+Q25 -> 15056101
B85: Pagos Directos efectuados en el año | J85: =AD25 -> 0
B86: APV B máximo restante para utilizar 100% del beneficio tributario | J86: =(AH25-(AI25+AJ25))*C24 -> 23786154
B87: Pago Directo APV opción B final | J87: 0
B88: Intereses Crédito Hipotecario (Art. 55 bis)
B92: Nueva Base tributable anual | J92: =J82-G36-J85-J87 -> 97733658
B93: Impuesto Calculado sobre nueva Base | J93: =Hoja15!R113 -> 15546728
B94: Reliquidación Anual de Impuesto | J94: =J83-J93+AC58 -> -490626.79
C102: (*) Total Haberes afectos: Renta bruta menos asignación de colación y movilización.
C103: (**) APV opción B máximo con Beneficio Tributario = sumatoria cotizaciones obligatorias enteradas durante el año * 8.33, con tope UF 600.
C107: =STDEV(D13:D24) -> 0 | I107: =J83-J93 -> -490626.79
G108: =IF((J85+J87)=0,J83,(J92*Hoja15!J114-Hoja15!K114)) -> 15056101 | I108: =IF((J85+J87)>0,J83-J93,0) -> 0
G109: =J92*Hoja15!J114-Hoja15!K114 -> 14856861 | I109: =IF(C107>0,1,0) -> 0 | J109: =IF(I109=0,"FIJO","VARIABLE") -> FIJO
C110: Impuestos Pagados durante el año | I110: =IF((J85+J87)>0,1,0) -> 0 | J110: =IF(I110=0,"NO HAY","SI HAY") -> NO HAY
C111: Base tributable anual | G111: =M25 -> 15056101
C112: Pagos Directos efectuados en el año | G112: =K25 -> 97733658 | I112: =IF((I109+I110)=0,0,IF(I110=0,0,J83-J93)) -> 0
C113: Pago Directo APV opción B final | G113: 0

Sheet Hoja5
G2: =F3+F4 -> 88002957 | H2: 0 | R2: Renta tributable | S2: Pensión tributable | T2: Boletas tributable | U2: APV directo | W2: Impuesto sueldo | X2: Impuesto pensión | Y2: Rerención
E3: Renta tributable mensual | F3: =Hoja14!N26 -> 88002957 | G3: =R16 -> 89358141 | Q3: =Hoja15!B6 -> Enero | R3: =Hoja14!N14/Hoja15!C6 -> 83.236547 | S3: =Hoja14!R14/Hoja15!C6 -> 0 | T3: =Hoja14!V14/Hoja15!C6 -> 0 | U3: =Hoja14!AG14/Hoja15!C6 -> 0 | W3: =Hoja14!P14/Hoja15!C6 -> 8.0044058 | X3: =Hoja14!T14/Hoja15!C6 -> 0 | Y3: =Hoja14!X14/Hoja15!C6 -> 0
E4: Pensiones | F4: =Hoja14!R26 -> 0 | G4: =S16 -> 0 | Q4: =Hoja15!B7 -> Febrero | R4: =Hoja14!N15/Hoja15!C7 -> 83.261978 | S4: =Hoja14!R15/Hoja15!C7 -> 0 | T4: =Hoja14!V15/Hoja15!C7 -> 0 | U4: =Hoja14!AG15/Hoja15!C7 -> 0 | W4: =Hoja14!P15/Hoja15!C7 -> 8.010255 | X4: =Hoja14!T15/Hoja15!C7 -> 0 | Y4: =Hoja14!X15/Hoja15!C7 -> 0
E5: Honorarios afectos | F5: =Hoja14!V26-(MIN(30%*Hoja14!V26,Hoja5!I5)) -> 0 | G5: =T16 -> 0 | H5: Renta presunta | I5: =15*Hoja15!C17*12 -> 12517560 | J5: =Hoja14!V26*30% -> 0 | M5: =1.667*(250-L8)/100 -> 2.4095584 | Q5: =Hoja15!B8 -> Marzo | R5: =Hoja14!N16/Hoja15!C8 -> 390.89475 | S5: =Hoja14!R16/Hoja15!C8 -> 0 | T5: =Hoja14!V16/Hoja15!C8 -> 0 | U5: =Hoja14!AG16/Hoja15!C8 -> 0 | W5: =Hoja14!P16/Hoja15!C8 -> 117.5379 | X5: =Hoja14!T16/Hoja15!C8 -> 0 | Y5: =Hoja14!X16/Hoja15!C8 -> 0
E6: Sub Total | F6: =F3+F4+F5 -> 88002957 | G6: =G3+G4+G5 -> 89358141 | Q6: =Hoja15!B9 -> Abril | R6: =Hoja14!N17/Hoja15!C9 -> 81.802188 | S6: =Hoja14!R17/Hoja15!C9 -> 0 | T6: =Hoja14!V17/Hoja15!C9 -> 0 | U6: =Hoja14!AG17/Hoja15!C9 -> 0 | W6: =Hoja14!P17/Hoja15!C9 -> 7.6745032 | X6: =Hoja14!T17/Hoja15!C9 -> 0 | Y6: =Hoja14!X17/Hoja15!C9 -> 0
E7: menos APV directo | F7: =F6-Hoja14!J272-Hoja14!J34 -> 88002957 | G7: =G6-(U16+Hoja14!J34) -> 89358141 | H7: Pagos directos | I7: =Hoja14!J272+Hoja14!J34 -> 0 | Q7: =Hoja15!B10 -> Mayo | R7: =Hoja14!N18/Hoja15!C10 -> 81.334608 | S7: =Hoja14!R18/Hoja15!C10 -> 0 | T7: =Hoja14!V18/Hoja15!C10 -> 0 | U7: =Hoja14!AG18/Hoja15!C10 -> 0 | W7: =Hoja14!P18/Hoja15!C10 -> 7.5669597 | X7: =Hoja14!T18/Hoja15!C10 -> 0 | Y7: =Hoja14!X18/Hoja15!C10 -> 0
E8: menos intereses hipocario | F8: =F7-I8 -> 88002957 | G8: =G7-Hoja14!R5 -> 89358141 | H8: Intereses hipotecario | I8: =MIN(8*Hoja15!C17*12,Hoja5!M8*Hoja14!P5) -> 0 | L8: =F7/(Hoja15!C17*12) -> 105.4554 | M8: =IF(L8<=90,100%,IF(L8>150,0%,(250-L8*1.667)/100)) -> 0.74205841 | Q8: =Hoja15!B11 -> Junio | R8: =Hoja14!N19/Hoja15!C11 -> 81.131824 | S8: =Hoja14!R19/Hoja15!C11 -> 0 | T8: =Hoja14!V19/Hoja15!C11 -> 0 | U8: =Hoja14!AG19/Hoja15!C11 -> 0 | W8: =Hoja14!P19/Hoja15!C11 -> 7.5203194 | X8: =Hoja14!T19/Hoja15!C11 -> 0 | Y8: =Hoja14!X19/Hoja15!C11 -> 0
E9: Impuesto según tabla | F9: =(F8*VLOOKUP(F8,Hoja15!$J$105:$M$112,3))-(VLOOKUP(F8,Hoja15!$J$105:$M$112,4)) -> 11898728 | G9: =(G8*VLOOKUP(G8,Hoja15!$J$105:$M$112,3))-(VLOOKUP(G8,Hoja15!$J$105:$M$112,4)) -> 12310704 | Q9: =Hoja15!B12 -> Julio | R9: =Hoja14!N20/Hoja15!C12 -> 81.015561 | S9: =Hoja14!R20/Hoja15!C12 -> 0 | T9: =Hoja14!V20/Hoja15!C12 -> 0 | U9: =Hoja14!AG20/Hoja15!C12 -> 0 | W9: =Hoja14!P20/Hoja15!C12 -> 7.493579 | X9: =Hoja14!T20/Hoja15!C12 -> 0 | Y9: =Hoja14!X20/Hoja15!C12 -> 0
E10: Creditos | F10: =Hoja14!P26+Hoja14!T26+Hoja14!X26 -> 13702706 | G10: =W16+X16+Y16 -> 13952288 | L10: =8*Hoja15!C17*12 -> 6676032 | Q10: =Hoja15!B13 -> Agosto | R10: =Hoja14!N21/Hoja15!C13 -> 81.233842 | S10: =Hoja14!R21/Hoja15!C13 -> 0 | T10: =Hoja14!V21/Hoja15!C13 -> 0 | U10: =Hoja14!AG21/Hoja15!C13 -> 0 | W10: =Hoja14!P21/Hoja15!C13 -> 7.5437837 | X10: =Hoja14!T21/Hoja15!C13 -> 0 | Y10: =Hoja14!X21/Hoja15!C13 -> 0
F11: =(F9-F10)*F19 -> -1803978.8 | G11: =(G9-G10) -> -1641584.1 | Q11: =Hoja15!B14 -> Septiembre | R11: =Hoja14!N22/Hoja15!C14 -> 80.455521 | S11: =Hoja14!R22/Hoja15!C14 -> 0 | T11: =Hoja14!V22/Hoja15!C14 -> 0 | U11: =Hoja14!AG22/Hoja15!C14 -> 0 | W11: =Hoja14!P22/Hoja15!C14 -> 7.3647699 | X11: =Hoja14!T22/Hoja15!C14 -> 0 | Y11: =Hoja14!X22/Hoja15!C14 -> 0
Q12: =Hoja15!B15 -> Octubre | R12: =Hoja14!N23/Hoja15!C15 -> 80.455521 | S12: =Hoja14!R23/Hoja15!C15 -> 0 | T12: =Hoja14!V23/Hoja15!C15 -> 0 | U12: =Hoja14!AG23/Hoja15!C15 -> 0 | W12: =Hoja14!P23/Hoja15!C15 -> 7.3647699 | X12: =Hoja14!T23/Hoja15!C15 -> 0 | Y12: =Hoja14!X23/Hoja15!C15 -> 0
Q13: =Hoja15!B16 -> Noviembre | R13: =Hoja14!N24/Hoja15!C16 -> 80.076826 | S13: =Hoja14!R24/Hoja15!C16 -> 0 | T13: =Hoja14!V24/Hoja15!C16 -> 0 | U13: =Hoja14!AG24/Hoja15!C16 -> 0 | W13: =Hoja14!P24/Hoja15!C16 -> 7.2776699 | X13: =Hoja14!T24/Hoja15!C16 -> 0 | Y13: =Hoja14!X24/Hoja15!C16 -> 0
Q14: =Hoja15!B17 -> Diciembre | R14: =Hoja14!N25/Hoja15!C17 -> 80.052958 | S14: =Hoja14!R25/Hoja15!C17 -> 0 | T14: =Hoja14!V25/Hoja15!C17 -> 0 | U14: =Hoja14!AG25/Hoja15!C17 -> 0 | W14: =Hoja14!P25/Hoja15!C17 -> 7.2721803 | X14: =Hoja14!T25/Hoja15!C17 -> 0 | Y14: =Hoja14!X25/Hoja15!C17 -> 0
F15: =IF(Hoja14!P5+Hoja14!R26+Hoja14!V26+Hoja14!J26+Hoja14!K26+Hoja14!J34+Hoja14!R7=0,1,0) -> 0 | R15: =SUM(R3:R14) -> 1284.9521 | S15: =SUM(S3:S14) -> 0 | T15: =SUM(T3:T14) -> 0 | U15: =SUM(U3:U14) -> 0 | W15: =SUM(W3:W14) -> 200.6311 | X15: =SUM(X3:X14) -> 0 | Y15: =SUM(Y3:Y14) -> 0
R16: =Hoja15!$C$17*Hoja5!R15 -> 89358141 | S16: =Hoja15!$C$17*Hoja5!S15 -> 0 | T16: =Hoja15!$C$17*Hoja5!T15 -> 0 | U16: =Hoja15!$C$17*Hoja5!U15 -> 0 | W16: =Hoja15!$C$17*Hoja5!W15 -> 13952288 | X16: =Hoja15!$C$17*Hoja5!X15 -> 0 | Y16: =Hoja15!$C$17*Hoja5!Y15 -> 0
F17: =IF(Hoja14!G14=AVERAGE(Hoja14!G14:G25),1,0) -> 0 | H17: =F8 -> 88002957 | I17: =F9 -> 11898728
H18: =H17+Hoja14!P4 -> 98002957 | I18: =(H18*VLOOKUP(H18,Hoja15!$J$105:$M$112,3))-(VLOOKUP(H18,Hoja15!$J$105:$M$112,4)) -> 14938728
F19: =IF(AND(F15=1,F17=1),0,1) -> 1
I20: =(I18-I17)/Hoja14!P4 -> 0.304 | J20: =I20*Hoja14!P4 -> 3040000 | K20: =J20-15%*Hoja14!P4 -> 1540000
I21: =(I20*1.1)+3% -> 0.3644 | J21: =I21*Hoja14!P4 -> 3644000 | K21: =J21-Hoja14!P4*15% -> 2144000 | M21: =IF(Hoja14!P4=0,0,IF(Hoja14!P3="No pensionado",Hoja5!K21,Hoja5!K20)) -> 1540000
F22: =F8*Hoja15!L110-Hoja15!M110 -> 11898728
E27: =Hoja14!V26+Hoja14!R26-SUM(Hoja14!M20:M24)-Hoja5!I5 -> -12517560
E28: =E27-Hoja15!J111 -> -1.1265804e+08

Sheet Hoja6
C5: 23435.87
C6: 23508.46
C7: 23606.97
C8: 23773.41
C9: 23931.69
C10: 24023.61
C11: 24062.27
C12: 24103.41
C13: 24168.02
C14: 24326.93
C15: 24553.7
C16: 24627.1
